Workbook

Sheet README
A1: Carvana（CVNA）個股模型 v0.3.2（2026-10-29）— 命題＋營收線＋收支平衡＋信用風險
A2: 命題：Carvana 的高成長與獲利，毛利約三成、調整後 EBITDA 約一半來自「把車貸賣掉的利得」；只要消費信用與 ABS 市場正常，它能自我融資，一旦信用循環轉向，利得、放款與台數會同時被壓縮——問題是它的現金與債務結構撐不撐得住
A3: 核心問題：在信用循環轉差時，Carvana 能否不靠新股與新債維持收支平衡？債務／EBITDA 會不會越過評等門檻？
A4: 重點觀察（數字取自本活頁簿）
A5: ="① 收支：情境 B 的 FY2027–FY2031 收支關卡合計 "&TEXT(CF!D4,"#,##0")&"（百萬美元），情境 C 為 "&TEXT(CF!E4,"#,##0")&"；情境 C 期間最低現金 "&TEXT(CF!E6,"#,##0")&"，新增外部融資需求 "&TEXT(CF!E5,"#,##0")&"。" -> ① 收支：情境 B 的 FY2027–FY2031 收支關卡合計 16,038（百萬美元），情境 C 為 5,947；情境 C 期間最低現金 4,225，新增外部融資需求 0。
A6: ="② 債信：2026-09-30 TTM 債務／EBITDA "&TEXT(ttm_lev,"0.0")&"x，扣除貸款出售利得後為 "&TEXT(ttm_lev_xg,"0.0")&"x；情境 C 2027 年債務／EBITDA "&TEXT(Credit!E47,"0.0")&"x（Moody's 升評門檻 4.0x）。" -> ② 債信：2026-09-30 TTM 債務／EBITDA 1.9x，扣除貸款出售利得後為 3.9x；情境 C 2027 年債務／EBITDA 3.8x（Moody's 升評門檻 4.0x）。
A7: ="③ 貸款去化：已承諾承購（Ally＋整批出售）只涵蓋情境 B 2027 年發放量的 "&TEXT(Credit!E37,"0%")&"；若所有買方與 ABS 同時停止，現金與倉儲額度約可撐 "&TEXT(Credit!C92,"0.0")&" 個月（Ally 照常則 "&TEXT(Credit!D92,"0.0")&" 個月）。" -> ③ 貸款去化：已承諾承購（Ally＋整批出售）只涵蓋情境 B 2027 年發放量的 59%；若所有買方與 ABS 同時停止，現金與倉儲額度約可撐 3.7 個月（Ally 照常則 6.3 個月）。
A8: ="④ 消費信用：管理組合年化淨沖銷率 2026 上半年 "&TEXT(Credit!I66,"0.00%")&"（非 Prime 推得 "&TEXT(Credit!I68,"0.0%")&"），以一年前餘額計為 "&TEXT(Credit!I69,"0.00%")&"——改善有一部分來自組合快速成長的分母稀釋。" -> ④ 消費信用：管理組合年化淨沖銷率 2026 上半年 3.16%（非 Prime 推得 6.0%），以一年前餘額計為 4.10%——改善有一部分來自組合快速成長的分母稀釋。
A9: ="⑤ 估值：加權目標價 "&TEXT(v_tp_w,"0.0")&" 美元，相對現價 "&TEXT(v_up,"+0%;-0%")&"（"&Val!C94&"）；市場隱含 2030 年須有約 "&TEXT(Val!C93/10000,"0")&" 萬台零售量（以情境 B 每台 EBITDA 換算；情境 B 為 "&TEXT(Thesis!H34/10000,"0")&" 萬台）。三情境 IRR 機率加權 "&TEXT(v_irr_w,"0.0%")&"，低於 WACC "&TEXT(v_wacc,"0.0%")&"——結論取決於折現率。" -> ⑤ 估值：加權目標價 35.6 美元，相對現價 -44%（放空）；市場隱含 2030 年須有約 218 萬台零售量（以情境 B 每台 EBITDA 換算；情境 B 為 163 萬台）。三情境 IRR 機率加權 12.7%，低於 WACC 17.7%——結論取決於折現率。
A11: 工作表：README → In（輸入）→ Q（事實總帳）→ Thesis（命題：台數 × 單位經濟）→ PL（營收線 → 損益）→ CF（收支模組、債務表）→ Credit（信用風險七節）→ Val（DCF＋倍數）→ Recon（對帳）→ Sens（敏感度）→ Sources
A12: 會計年度＝曆年；金額百萬美元；每台金額美元。FY2026E＝前三季實績＋第四季模型（v0.2 起）；公司自 Q4 2026 起不再提供季度與年度指引，2027 年起改以 GAAP 指標（中期目標：300 萬台、營業利益率 12.5%，2030–2035）
A13: 營收分部層：Carvana 只有一個應報導部門（10-Q 附註 2）；營收列採公司固定揭露的三條營收線（零售、批發、其他），其他營收下拆「貸款出售利得」與「非貸款」兩個命題子列，PL 頁核對列為 0
A14: 與專案既有模型的關係：比照 company-models 的 Oracle v0.4（命題＋分部架構、五級評等、DCF 50%＋倍數 50%、rf 5.00%）與 CoreWeave 收支模型「Backlog 不是現金」的收支精神；本模型不讀 Tokenomics（Carvana 與算力無關）
A15: v0.1 → v0.2（2026-10-29）：納入 Q3 2026 實績（台數 217,385，高於共識 3.4%；零售 GPU 3,556 高於共識、批發 GPU 708 低於共識、其他 GPU 2,733 持平；SG&A 805 偏高）；2026 年改為前三季實績＋Q4 模型；債務表改為實際（定期貸款 B 1,660 以利率交換固定 4.055% 至 2028-07、2030 年票據已以溢價 50 贖回、車隊融資 142）；SG&A 變動成本 2,700 → 2,900；出售貸款存續期間 1.8 → 2.0（貸款池模擬）；現價改為 2026-10-28 盤後 63.99（v0.2.1，Andy 指定）；TTM 改為 Q4 2025–Q3 2026。v0.3（2026-10-29，Andy 選項 ③）：對 Q3 利多與利空對稱處理——SG&A 變動成本 2,900 → 2,800、情境 B 零售 GPU 2027 年 3,350 → 3,450、長期 3,300 → 3,350。v0.3.1：情境 C 存貨天數改為兩年路徑（2027 年 70、2028 年 65、2029 年起 60；原為 2027 年 75、2028 年即回 60）
A16: 已知限制
A17: 1. 非 Prime（144A）證券化的靜態池損失未公開，非 Prime 淨沖銷率以「全部 − Prime」推得。2. 利息以期初餘額計，忽略年內再融資時點（再融資年度另以月數拆）。3. TRA 以平均攤付處理，未隨課稅所得與未來交換變動。4. 產能建置成本、維護資本支出、利得率對損失與利差的傳導係數皆為 Assumed。5. 估值折現基準點為 2026 年底，未計 2026 年第四季現金流。6. 關係人與放空報告主張無法以公開資料驗證，只列對照。7. 2026 年評等動作未找到，門檻沿用 2025 年公開說法。

Sheet In
A1: In — 輸入（藍字＝輸入；黑字＝公式；基準欄 E，低 D、高 F）。金額：百萬美元（US$M）；每台金額：美元；台數：輛
A2: 標記：Verified／Interested-party／Analogy／Assumed／Derived；Analogy、Assumed 給低／高區間。公司財報數字依專案慣例標 Interested-party（公司自述、經會計師核閱或查核）
A3: 鍵 | B3: 項目 | C3: 單位 | D3: 低 | E3: 基準 | F3: 高 | G3: 標記 | H3: 來源1 | I3: 來源2／說明
A4: A. 股價、股數
A5: px | B5: 現價（2026-10-28 盤後） | C5: US$ | E5: 63.99 | G5: Interested-party | H5: StockStory（2026-10-28）：Q3 財報公布後盤後上漲 8.4% 至 63.99 | I5: Andy 2026-10-29 指定用盤後價；推得收盤約 59.03；2026-10-26 收盤 56.61（stockanalysis）
A6: sh_fx | B6: 完全轉換股數（LLC 單位全數交換＋其他稀釋） | C6: 百萬股 | E6: 1127 | G6: Interested-party | H6: Carvana Q2 2026 股東信（8-K 2026-07-29 附件 99.1） 第 1 頁：Assuming full conversion … 1.127 billion shares | I6: A 類流通 719.0 百萬股＋B 類 380.5 百萬股（B 類為表決權股；經濟權益以 LLC 單位交換計）
A7: B. 命題：零售台數路徑
A8: u_q4 | B8: 2026Q4 零售台數 | C8: 輛 | E8: =lq_units*(1+q4_seq) -> 221732.7 | G8: Derived | H8: Q3 2026 實績 217,385 ×（1＋季增） | I8: 公司指引 Q4 較 Q3 增加（Q3 2026 股東信）
A9: q4_adj | B9: 2026Q4 每台總毛利季節性調整（相對 Q3） | C9: US$ | D9: -935 | E9: -600 | F9: -300 | G9: Derived | H9: Q4 2025 總 GPU 6,427 較 Q3 2025 7,362 低 935（零售 −466、其他 −233、批發 −236；Q 頁） | I9: 季節性；以零售毛利承載
A10: q4_seq | B10: 2026Q4 台數相對 Q3 變化 | C10: % | D10: 0 | E10: 0.02 | F10: 0.05 | G10: Assumed | H10: 公司指引：sequential increase（Q3 2026 股東信）；2025 Q4／Q3＝+4.9% | I10: —
A11: g27_A | B11: 情境 A：2027 年零售台數年增 | C11: % | D11: 0.24 | E11: 0.32 | F11: 0.4 | G11: Assumed | H11: 公司目標 2030–2035 年 300 萬台（股東信）；此路徑約 2033 年觸及用地上限 | I11: —
A12: g28_A | B12: 情境 A：2028 年零售台數年增 | C12: % | D12: 0.2 | E12: 0.28 | F12: 0.36 | G12: Assumed | H12: 同上 | I12: —
A13: g30_A | B13: 情境 A：2030 年零售台數年增（2029 年取 2028 與 2030 中點） | C13: % | D13: 0.15 | E13: 0.2 | F13: 0.25 | G13: Assumed | H13: 同上 | I13: —
A14: g35_A | B14: 情境 A：2035 年零售台數年增（2031–2034 線性） | C14: % | D14: 0.05 | E14: 0.08 | F14: 0.11 | G14: Assumed | H14: 同上 | I14: —
A15: g27_B | B15: 情境 B：2027 年零售台數年增 | C15: % | D15: 0.17 | E15: 0.25 | F15: 0.33 | G15: Assumed | H15: 2025 年 +43%、2026 上半年 +39%、Q3 共識 +35%，逐年放緩；2035 年約為二手零售市場 6% | I15: —
A16: g28_B | B16: 情境 B：2028 年零售台數年增 | C16: % | D16: 0.12 | E16: 0.2 | F16: 0.28 | G16: Assumed | H16: 同上 | I16: —
A17: g30_B | B17: 情境 B：2030 年零售台數年增（2029 年取 2028 與 2030 中點） | C17: % | D17: 0.08 | E17: 0.13 | F17: 0.18 | G17: Assumed | H17: 同上 | I17: —
A18: g35_B | B18: 情境 B：2035 年零售台數年增（2031–2034 線性） | C18: % | D18: 0.02 | E18: 0.05 | F18: 0.08 | G18: Assumed | H18: 同上 | I18: —
A19: g27_C | B19: 情境 C：2027 年零售台數年增 | C19: % | D19: -0.18 | E19: -0.1 | F19: -0.02 | G19: Assumed | H19: 2027 年次級車貸循環：放款收緊、二手車價下跌，台數 −10%；2028 年起緩步恢復 | I19: —
A20: g28_C | B20: 情境 C：2028 年零售台數年增 | C20: % | D20: -0.03 | E20: 0.05 | F20: 0.13 | G20: Assumed | H20: 同上 | I20: —
... A22: g35_C | B22: 情境 C：2035 年零售台數年增（2031–2034 線性） | C22: % | D22: 0.01 | E22: 0.04 | F22: 0.07 | G22: Assumed | H22: 同上 | I22: —
A23: unit_cap | B23: 生產用地可支援的年零售台數上限 | C23: 輛 | E23: 3000000 | G23: Interested-party | H23: Carvana Q2 2026 股東信（8-K 2026-07-29 附件 99.1） 第 3 頁：real estate to support annual retail production of 3 million | I23: 台數路徑以此為上限
A24: cap_0 | B24: 已完成建置的年產能（2026 年中） | C24: 輛 | E24: 1500000 | G24: Interested-party | H24: Carvana Q2 2026 股東信（8-K 2026-07-29 附件 99.1） 第 3 頁：fully built out annual capacity for approximately 1.5 million | I24: —
A25: util | B25: 產能利用率上限（超過即需擴建） | C25: % | D25: 0.75 | E25: 0.85 | F25: 0.95 | G25: Assumed | H25: 公司未揭露（未找到） | I25: —
A26: capcost | B26: 每台年產能建置成本 | C26: US$／台 | D26: 400 | E26: 600 | F26: 1000 | G26: Assumed | H26: ADESA 站點全面改建成本：未找到（公司只揭露首個全面改建 2027 年初投產） | I26: 成長性資本支出＝新增產能 × 每台成本
A27: C. 命題：單位經濟（每零售台）
A28: asp_q4 | B28: 2026Q4 零售每台營收 | C28: US$ | D28: 27500 | E28: 28263 | F28: 28800 | G28: Interested-party | H28: Carvana Q3 2026 股東信（8-K 2026-10-28 附件 99.1）：Q3 2026 零售每台營收 28,263 | I28: —
A29: asp_g | B29: 零售每台售價年增（2027 起） | C29: % | D29: 0 | E29: 0.02 | F29: 0.04 | G29: Assumed | H29: 二手車價（Manheim 指數 2026-09 為 205.9，年減 0.6%，Cox Automotive） | I29: 貸款發放額、批發營收同幅
A30: whs_pu | B30: 批發營收 ÷ 零售台數（2026Q4 起） | C30: US$ | E30: =Q!K7*1000000/Q!K4 -> 6183.3274 | G30: Derived | H30: 2026 前三季批發營收 3,723 ÷ 零售 602,103 台（Q 頁） | I30: Q3 單季 5,989
A31: gpr_q4 | B31: 2026Q4 零售毛利／台（季節調整前） | C31: US$ | D31: 3165 | E31: 3556 | F31: 3600 | G31: Interested-party | H31: Carvana Q3 2026 股東信（8-K 2026-10-28 附件 99.1）：Q3 2026 零售 GPU 3,556（共識 3,404） | I31: 低＝Q1 2026 實績
A32: gpr27_A | B32: 情境 A：2027 年零售 GPU | C32: US$ | D32: 3300 | E32: 3600 | F32: 3900 | G32: Assumed | H32: 2024 年 3,312、2025 年 3,315、2026 前三季 3,431、Q3 3,556（共識 3,404） | I32: 2028–2029 線性收斂至長期值
A33: gprLT_A | B33: 情境 A：2030 年起零售 GPU | C33: US$ | D33: 3400 | E33: 3700 | F33: 4000 | G33: Assumed | H33: 同上 | I33: —
A34: gpr27_B | B34: 情境 B：2027 年零售 GPU | C34: US$ | D34: 3150 | E34: 3450 | F34: 3750 | G34: Assumed | H34: 2024 年 3,312、2025 年 3,315、2026 前三季 3,431、Q3 3,556（共識 3,404）；情境 B：Q3 利多延續一半（Andy 2026-10-29 選項 ③；v0.2 為 2027 年 3,350、長期 3,300） | I34: 2028–2029 線性收斂至長期值
A35: gprLT_B | B35: 情境 B：2030 年起零售 GPU | C35: US$ | D35: 3050 | E35: 3350 | F35: 3650 | G35: Assumed | H35: 同上 | I35: —
A36: gpr27_C | B36: 情境 C：2027 年零售 GPU | C36: US$ | D36: 2400 | E36: 2700 | F36: 3000 | G36: Assumed | H36: 2024 年 3,312、2025 年 3,315、2026 前三季 3,431、Q3 3,556（共識 3,404）；情境 C：二手車價下跌時零售毛利受壓（2022 年循環曾大幅下滑） | I36: 2028–2029 線性收斂至長期值
A37: gprLT_C | B37: 情境 C：2030 年起零售 GPU | C37: US$ | D37: 2800 | E37: 3100 | F37: 3400 | G37: Assumed | H37: 同上 | I37: —
A38: gpw_h2 | B38: 2026Q4 起批發毛利／零售台 | C38: US$ | D38: 650 | E38: 708 | F38: 806 | G38: Interested-party | H38: Carvana Q3 2026 股東信（8-K 2026-10-28 附件 99.1）：Q3 2026 批發 GPU 708（共識 812） | I38: 高＝2026 上半年 806
A39: gpw27_C | B39: 情境 C：2027 年批發毛利／零售台 | C39: US$ | D39: 550 | E39: 650 | F39: 750 | G39: Assumed | H39: 批發車價下跌時批發毛利下降 | I39: 情境 A、B 沿用 gpw_h2
A40: opu | B40: 每零售台貸款發放金額（2026Q4） | C40: US$ | E40: =Q!J16*1000000/Q!J4 -> 23837.891 | G40: Derived | H40: Q3 2026 發放 5,182（前三季 14,187 − 上半年 9,005）÷ 217,385 台（Q 頁） | I40: 2027 起隨售價年增
A41: gos_h2 | B41: 2026Q4 貸款出售利得率（利得 ÷ 發放額） | C41: % | D41: 0.065 | E41: =Q!J17/Q!J16 -> 0.073523736 | F41: 0.08 | G41: Derived | H41: Q3 2026 利得 381（前三季 1,084 − 上半年 703）÷ 發放 5,182（Q 頁） | I41: Q2 2026 7.35%；公司稱 Q3 受基準利率快速上升與油價影響每台約 −200
A42: gos27_A | B42: 情境 A：2027 年貸款出售利得率 | C42: % | D42: 0.07 | E42: 0.08 | F42: 0.09 | G42: Assumed | H42: 2025 年 9.3%、2026 上半年 7.8%、Q2 7.3%（Q 頁） | I42: 2028–2029 線性收斂至長期值
A43: gosLT_A | B43: 情境 A：2030 年起貸款出售利得率 | C43: % | D43: 0.07 | E43: 0.08 | F43: 0.09 | G43: Assumed | H43: 同上 | I43: —
A44: gos27_B | B44: 情境 B：2027 年貸款出售利得率 | C44: % | D44: 0.062 | E44: 0.072 | F44: 0.082 | G44: Assumed | H44: 2025 年 9.3%、2026 上半年 7.8%、Q2 7.3%（Q 頁） | I44: 2028–2029 線性收斂至長期值
A45: gosLT_B | B45: 情境 B：2030 年起貸款出售利得率 | C45: % | D45: 0.06 | E45: 0.07 | F45: 0.08 | G45: Assumed | H45: 同上 | I45: —
A46: gos27_C | B46: 情境 C：2027 年貸款出售利得率 | C46: % | E46: =gos27_B-loss_pt*dcnl_C-dur*dspr_C -> 0.034 | G46: Derived | H46: 情境 B 2027 年 − 損失傳導 × 終身損失增幅 − 存續期間 × 利差擴大（Credit 頁 S2） | I46: —
A47: gosLT_C | B47: 情境 C：2030 年起貸款出售利得率 | C47: % | D47: 0.05 | E47: 0.06 | F47: 0.07 | G47: Assumed | H47: 循環後部分回復 | I47: —
A48: oth_pu | B48: 其他毛利中非貸款部分／零售台（VSC、GAP、權證等） | C48: US$ | E48: =(Q!J8-Q!J17)*1000000/Q!J4 -> 979.82842 | G48: Derived | H48: Q3 2026（其他毛利 594 − 出售利得 381）÷ 217,385 台（Q 頁） | I48: VSC 佣金來自 DriveTime（關係人）
A49: oth_g | B49: 非貸款其他毛利／台年增 | C49: % | D49: -0.03 | E49: 0 | F49: 0.03 | G49: Assumed | H49: — | I49: —
A50: D. 費用、折舊、資本支出
A51: sga_fix | B51: SG&A 固定部分（每季） | C51: US$M | D51: 140 | E51: 170 | F51: 200 | G51: Derived | H51: 季度 SG&A 對零售台數迴歸（Q 頁） | I51: Q3 2026 驗算：170＋217,385 × 2,900＝800（實績 805）
A52: sga_var | B52: SG&A 變動部分／台（2026 年） | C52: US$ | D52: 2700 | E52: 2800 | F52: 2900 | G52: Derived | H52: 固定 170／季時：Q2 2026 反推約 2,700、Q3 2026 約 2,920（Q3 廣告 152、物流 68 受油價推升）；取中點，約一半視為暫時性（Andy 2026-10-29 選項 ③） | I52: v0.1 為 2,700；v0.2 為 2,900
A53: infl | B53: 固定費用、折舊、SBC 年增 | C53: % | D53: 0.02 | E53: 0.03 | F53: 0.04 | G53: Assumed | H53: — | I53: —
A54: eff_A | B54: 情境 A：變動 SG&A／台每年下降 | C54: % | D54: 0.015 | E54: 0.03 | F54: 0.045 | G54: Assumed | H54: 公司稱已承擔可支援更大量的固定成本、規模可再擴 EBITDA 率（Q1 2025 股東信，Interested-party） | I54: —
A55: eff_B | B55: 情境 B：變動 SG&A／台每年下降 | C55: % | D55: 0 | E55: 0.015 | F55: 0.03 | G55: Assumed | H55: 公司稱已承擔可支援更大量的固定成本、規模可再擴 EBITDA 率（Q1 2025 股東信，Interested-party） | I55: —
A56: eff_C | B56: 情境 C：變動 SG&A／台每年下降 | C56: % | D56: 0 | E56: 0 | F56: 0.015 | G56: Assumed | H56: 公司稱已承擔可支援更大量的固定成本、規模可再擴 EBITDA 率（Q1 2025 股東信，Interested-party） | I56: —
A57: da_q4 | B57: 2026Q4 折舊攤銷 | C57: US$M | E57: =Q!J14 -> 64 | G57: Derived | H57: 沿用 Q3 2026 的 64（Q 頁） | I57: 2027 起隨 infl 成長＋成長性資本支出 ÷ 年限
A58: life | B58: 成長性資本支出折舊年限 | C58: 年 | D58: 10 | E58: 15 | F58: 20 | G58: Assumed | H58: 公司未揭露（建物與改裝設備混合） | I58: —
A59: sbc_q4 | B59: 2026Q4 SBC | C59: US$M | E59: =Q!J15 -> 25 | G59: Derived | H59: 沿用 Q3 2026 的 25（Q 頁） | I59: —
A60: warr | B60: 權證營收（Root，自調整後 EBITDA 扣除） | C60: US$M／年 | E60: 21 | G60: Interested-party | H60: 2025 全年 21（Q4 2025 股東信非 GAAP 對帳） | I60: —
A61: capex_q4 | B61: 2026Q4 資本支出 | C61: US$M | D61: 60 | E61: 70 | F61: 100 | G61: Assumed | H61: Q3 2026 為 64；三個 ADESA 全面改建施工中（Q3 股東信） | I61: —
A62: mcx | B62: 維護性資本支出 ÷ 營收 | C62: % | D62: 0.003 | E62: 0.005 | F62: 0.008 | G62: Assumed | H62: 2025 年總資本支出 147 ÷ 營收 20,322＝0.72%（含成長性） | I62: —
A63: E. 營運資金與風險自留
A64: inv_d | B64: 存貨天數（÷ 零售銷貨成本） | C64: 天 | D64: 55 | E64: 60 | F64: 65 | G64: Derived | H64: 2025-12-31：2,408 ÷（Q4 零售成本 3,667 × 4）× 365＝60；2026-06-30＝62（Q 頁） | I64: —
A65: inv_d_C | B65: 情境 C：2027 年存貨天數 | C65: 天 | D65: 65 | E65: 70 | F65: 80 | G65: Assumed | H65: 需求下滑時週轉變慢；2022 年 Carvana 上半年堆積、下半年去化（Andy 2026-10-29 選兩年路徑） | I65: v0.3 為 75 天且只設一年
A66: inv_d_C28 | B66: 情境 C：2028 年存貨天數 | C66: 天 | D66: 60 | E66: 65 | F66: 70 | G66: Assumed | H66: 逐步去化；2029 年起回到 inv_d | I66: —
A67: fr_d | B67: 待售貸款天數（÷ 年發放額） | C67: 天 | D67: 14 | E67: 16 | F67: 20 | G67: Derived | H67: 2026-09-30：896 ÷（Q3 發放 5,182 × 4）× 365＝15.8（Q 頁） | I67: v0.1 為 18
A68: ap_pct | B68: 應付與應計 ÷（銷貨成本＋SG&A）年額 | C68: % | E68: 0.054 | G68: Derived | H68: 2026-09-30：1,574 ÷（Q3 銷貨成本 6,519＋SG&A 805）× 4＝5.4% | I68: —
A69: abs_sh | B69: 證券化占貸款出售比例 | C69: % | E69: =3.7/(5.7+3.7+4.5) -> 0.26618705 | G69: Derived | H69: Carvana 10-Q Q3 2026（2026-10-28） 附註 7：2026 前三季證券化 3.7B ÷（Ally 5.7＋證券化 3.7＋整批出售 4.5） | I69: —
A70: bi_ret | B70: 證券化風險自留比例 | C70: % | E70: 0.05 | G70: Verified | H70: Regulation RR（10-Q 附註 8：at least 5%） | I70: —
A71: bi_adv | B71: 自留受益權的融資成數 | C71: % | E71: =427/557 -> 0.76660682 | G71: Derived | H71: Carvana 10-Q Q3 2026（2026-10-28） 附註 8、9：受益權融資 427 ÷ 受益權 557 | I71: 公允價值下跌時須補擔保
A72: F. 稅與 TRA（應收稅款協議）
A73: etr_26 | B73: 2026Q4 有效稅率 | C73: % | E73: =Q!K22/(Q!K13-Q!K20-Q!K21) -> 0.10877863 | G73: Derived | H73: 2026 前三季所得稅 171 ÷ 稅前 1,572 | I73: —
A74: etr_27 | B74: 2027 年有效稅率 | C74: % | D74: 0.08 | E74: 0.12 | F74: 0.16 | G74: Assumed | H74: 非控制權益（LLC 單位）部分不在 Carvana Co. 課稅；交換越多稅率越高 | I74: 2028–2029 線性
A75: etr_30 | B75: 2030 年起有效稅率 | C75: % | D75: 0.12 | E75: 0.18 | F75: 0.25 | G75: Assumed | H75: 同上 | I75: —
A76: ctr | B76: 現金稅率（2026–2028，遞延所得稅資產抵用期） | C76: % | D76: 0 | E76: 0.03 | F76: 0.08 | G76: Assumed | H76: 遞延所得稅資產 2,905（2026-09-30）；舊註 2,968（2026-06-30）；2026 上半年付稅 8（XBRL IncomeTaxesPaid） | I76: 2029 起現金稅＝帳面稅
A77: tra_0 | B77: TRA 負債（2026-09-30） | C77: US$M | E77: 2130 | G77: Interested-party | H77: Carvana 10-Q Q3 2026（2026-10-28） 資產負債表：2,130，其中關係人 1,645 | I77: TRA：公司須支付已實現節稅的 85%
A78: tra_q4 | B78: 2026Q4 TRA 付款 | C78: US$M | D78: 0 | E78: 0 | F78: 40 | G78: Derived | H78: 2026 前三季付款 37 全在上半年（現金流量表） | I78: —
A79: tra_yrs | B79: TRA 平均償付年數（2027 起平均攤付） | C79: 年 | D79: 10 | E79: 15 | F79: 20 | G79: Assumed | H79: 公司未揭露償付時程（未找到）；實際付款隨課稅所得與交換而變 | I79: 之後新增交換會再增加 TRA 負債（本版未建模）
A80: ncitax | B80: 代非控制權益繳稅 | C80: US$M／年 | E80: 8 | G80: Derived | H80: 2026 上半年 4（現金流量表） | I80: —
A81: G. 債務與利率（2026-09-30 結構；2030 年擔保票據已於 2026-08 以定期貸款 B 贖回）
A82: sofr | B82: SOFR（2026-10-26） | C82: % | E82: 0.0393 | G82: Verified | H82: sofrrate.com 2026-10 每日表：2026-10-26 為 3.93% | I82: 各年持平（判斷）
A83: tlb | B83: 定期貸款 B（2033-08-14 到期） | C83: US$M | E83: 1660 | G83: Interested-party | H83: Carvana 10-Q Q3 2026（2026-10-28） 附註 9：1,660（OID 4、發行成本 17） | I83: 每季攤還原始本金 0.25%（2027 起）
A84: swap_fix | B84: 利率交換固定利率（付固定、收 1 個月 Term SOFR；名目 1,660，至 2028-07-31） | C84: % | E84: 0.04055 | G84: Interested-party | H84: Carvana 10-Q Q3 2026（2026-10-28） 附註 17、第 3 項：4.055% | I84: 交換期間定期貸款 B 實質固定在 6.305%；之後隨 SOFR 浮動
A85: tlb_sp | B85: 定期貸款 B 利差（SOFR＋） | C85: % | E85: 0.0225 | G85: Interested-party | H85: 同上：Term SOFR＋2.25% | I85: 公司稱每年省利息約 45（2026-08-12 新聞稿）
A86: ssn_31 | B86: 2031 年到期擔保票據 | C86: US$M | E86: 2269 | G86: Interested-party | H86: Carvana 10-Q Q2 2026（2026-07-29） 附註 9 | I86: 2028-08-15 前僅能以補償溢價贖回
A87: ssn_r | B87: 擔保票據現金利率 | C87: % | E87: 0.09 | G87: Interested-party | H87: Carvana 10-Q Q2 2026（2026-07-29） 附註 9：9%（PIK 已於 2025-08 結束） | I87: —
A88: refi_yr | B88: 情境 A、B：2031 年票據再融資年度 | C88: 年 | E88: 2028 | G88: Assumed | H88: 2028-08-15 起可依贖回價格贖回（10-Q 附註 9） | I88: 情境 C 於 2031 年到期時再融資
A89: refi_sp | B89: 情境 A、B：再融資利差（SOFR＋） | C89: % | D89: 0.0225 | E89: 0.0275 | F89: 0.035 | G89: Assumed | H89: 比照 2026 年定期貸款 B 2.25% | I89: —
A90: refi_prem | B90: 2031 年票據提前贖回溢價 | C90: % | D90: 0.0225 | E90: 0.045 | F90: 0.045 | G90: Assumed | H90: 贖回價格表：未找到（契約未在本次取得的文件中）；高收益債慣例首個贖回日為票面＋半年息 | I90: —
A91: stress_sp | B91: 情境 C：2031 年到期再融資利差（SOFR＋） | C91: % | D91: 0.04 | E91: 0.05 | F91: 0.07 | G91: Assumed | H91: 信用循環中的高收益擔保債利差（判斷） | I91: —
A92: uns | B92: 無擔保票據（2027–2030 到期） | C92: US$M | E92: 107 | G92: Interested-party | H92: Carvana 10-Q Q2 2026（2026-07-29） 附註 9：2027 年 32、2028 年 22、2029 年 26、2030 年 27 | I92: —
A93: uns_r | B93: 無擔保票據加權利率 | C93: % | E93: =(32*0.055+22*0.05875+26*0.04875+27*0.1025)/107 -> 0.066238318 | G93: Derived | H93: Carvana 10-Q Q2 2026（2026-07-29） 附註 9 各期利率 | I93: —
A94: re_fin | B94: 不動產售後租回融資 | C94: US$M | E94: 485 | G94: Interested-party | H94: Carvana 10-Q Q2 2026（2026-07-29） 附註 9 | I94: 期限 20–25 年；本版不攤還
A95: re_r | B95: 不動產融資利率 | C95: % | D95: 0.07 | E95: 0.08 | F95: 0.09 | G95: Assumed | H95: 隱含利率：未找到 | I95: —
A96: bi_r | B96: 受益權融資利率 | C96: % | D96: 0.06 | E96: 0.07 | F96: 0.08 | G96: Assumed | H96: 未找到 | I96: —
A97: fleet | B97: 運輸車隊融資 | C97: US$M | E97: 142 | G97: Interested-party | H97: Carvana 10-Q Q3 2026（2026-10-28） 附註 9（Citizens Bank，額度 250） | I97: 本版持平
A98: fleet_r | B98: 運輸車隊融資利率 | C98: % | E98: 0.065 | G98: Derived | H98: SOFR 交換利率約 3.6%＋2.80–2.95%（10-Q 附註 9） | I98: —
A99: finls | B99: 融資租賃負債 | C99: US$M | E99: 118 | G99: Interested-party | H99: Carvana 10-Q Q2 2026（2026-07-29）（XBRL FinanceLeaseLiability） | I99: 本版持平
A100: finls_r | B100: 融資租賃折現率 | C100: % | E100: 0.064 | G100: Interested-party | H100: Carvana 10-Q Q2 2026（2026-07-29）：加權平均折現率 6.4% | I100: —
A101: fp_ratio | B101: 存貨融資（Ally floor plan）÷ 存貨 | C101: % | E101: =71/3456 -> 0.020543981 | G101: Derived | H101: Carvana 10-Q Q3 2026（2026-10-28）：floor plan 71 ÷ 存貨 3,456 | I101: 額度 1.5B 至 2027-04-30
...

Sheet Q
A1: Q — 事實總帳（US$M；台數為輛）。來源：各季股東信（8-K 附件 99.1）、10-Q、10-K、SEC XBRL；carvana/data/carvana_facts_20261029.json
A2: 欄：C–J＝Q4'24、Q1'25、Q2'25、Q3'25、Q4'25、Q1'26、Q2'26、Q3'26；K＝2026 前三季；L＝FY2024；M＝FY2025。核對列應為 0
A3: 項目 | B3: 單位 | C3: Q4'24 | D3: Q1'25 | E3: Q2'25 | F3: Q3'25 | G3: Q4'25 | H3: Q1'26 | I3: Q2'26 | J3: Q3'26 | K3: 2026 前三季 | L3: FY2024 | M3: FY2025
A4: 零售台數 | B4: 輛 | C4: 114379 | D4: 133898 | E4: 143280 | F4: 155941 | G4: 163522 | H4: 187393 | I4: 197325 | J4: 217385 | K4: 602103 | L4: 416348 | M4: 596641
A5: 批發台數 | B5: 輛 | C5: 48770 | D5: 63454 | E5: 72770 | F5: 80369 | G5: 81050 | H5: 83574 | I5: 105052 | J5: 111119 | K5: 299745 | L5: 199780 | M5: 297643
A6: 零售車輛銷售 | B6: US$M | C6: 2552 | D6: 2980 | E6: 3405 | F6: 3996 | G6: 4156 | H6: 4828 | I6: 5507 | J6: 6144 | K6: 16479 | L6: 9681 | M6: 14537
A7: 批發銷售與營收 | B7: US$M | C7: 678 | D7: 863 | E7: 1024 | F7: 1177 | G7: 988 | H7: 1078 | I7: 1343 | J7: 1302 | K7: 3723 | L7: 2841 | M7: 4052
A8: 其他銷售與營收 | B8: US$M | C8: 317 | D8: 389 | E8: 411 | F8: 474 | G8: 459 | H8: 526 | I8: 526 | J8: 594 | K8: 1646 | L8: 1151 | M8: 1733
A9: 合併營收 | B9: US$M | C9: 3547 | D9: 4232 | E9: 4840 | F9: 5647 | G9: 5603 | H9: 6432 | I9: 7376 | J9: 8040 | K9: 21848 | L9: 13673 | M9: 20322
A10: 零售毛利 | B10: US$M | C10: 369 | D10: 429 | E10: 521 | F10: 539 | G10: 489 | H10: 593 | I10: 700 | J10: 773 | K10: 2066 | L10: 1379 | M10: 1978
A11: 批發毛利 | B11: US$M | C11: 77 | D11: 111 | E11: 132 | F11: 135 | G11: 103 | H11: 152 | I11: 158 | J11: 154 | K11: 464 | L11: 346 | M11: 481
A12: SG&A | B12: US$M | C12: 494 | D12: 535 | E12: 551 | F12: 595 | G12: 627 | H12: 690 | I12: 704 | J12: 805 | K12: 2199 | L12: 1874 | M12: 2308
A13: 營業利益 | B13: US$M | C13: 260 | D13: 394 | E13: 511 | F13: 552 | G13: 424 | H13: 581 | I13: 680 | J13: 714 | K13: 1975 | L13: 990 | M13: 1881
A14: 折舊攤銷（銷貨成本＋SG&A） | B14: US$M | C14: 74 | D14: 73 | E14: 68 | F14: 65 | G14: 69 | H14: 69 | I14: 69 | J14: 64 | K14: 202 | L14: 305 | M14: 275
A15: 股份基礎給付 | B15: US$M | C15: 21 | D15: 26 | E15: 26 | F15: 24 | G15: 23 | H15: 27 | I15: 26 | J15: 25 | K15: 78 | L15: 92 | M15: 99
... A20: 利息費用（淨） | B20: US$M | C20: 148 | D20: 139 | E20: 143 | F20: 125 | G20: 98 | H20: 99 | I20: 101 | J20: 98 | K20: 298 | L20: 651 | M20: 505
A21: 其他費用（收益）與清償損失（推得） | B21: US$M | C21: =C13-C20-C22-C23 -> -44 | D21: =D13-D20-D22-D23 -> -120 | E21: =E13-E20-E22-E23 -> 60 | F21: =F13-F20-F22-F23 -> 168 | G21: =G13-G20-G22-G23 -> 2158 | H21: =H13-H20-H22-H23 -> 41 | I21: =I13-I20-I22-I23 -> 0 | J21: =J13-J20-J22-J23 -> 64 | ... M21: =M13-M20-M22-M23 -> 2266
A22: 所得稅（利益） | B22: US$M | C22: -3 | D22: 2 | E22: 0 | F22: -4 | G22: -2783 | H22: 36 | I22: 66 | J22: 69 | K22: 171 | L22: -4 | M22: -2785
A23: 淨利（合併） | B23: US$M | C23: 159 | D23: 373 | E23: 308 | F23: 263 | G23: 951 | H23: 405 | I23: 513 | J23: 483 | K23: 1401 | L23: 404 | M23: 1895
A24: 其他營收中關係人部分（DriveTime 等） | B24: US$M | C24: 59 | D24: 72 | E24: 83 | F24: 93 | G24: 99 | H24: 114 | I24: 117 | J24: 129 | K24: 360 | L24: 200 | M24: 347
A25: 資本支出 | B25: US$M | C25: 24 | D25: 27 | E25: 31 | F25: 38 | G25: 51 | H25: 51 | I25: 51 | J25: 64 | K25: 166 | L25: 91 | M25: 147
A26: 營業活動現金流 | B26: US$M | C26: 60 | D26: 232 | E26: 29 | F26: 345 | G26: 430 | H26: 107 | I26: 238 | J26: 555 | K26: 900 | L26: 918 | M26: 1036
A27: 現金（期末） | B27: US$M | C27: 1716 | D27: 1858 | E27: 1857 | F27: 2142 | G27: 2327 | H27: 2410 | I27: 2630 | J27: 3049 | K27: 3049 | L27: 1716 | M27: 2327
A28: 存貨（期末） | B28: US$M | C28: 1608 | D28: 1503 | E28: 2023 | F28: 2316 | G28: 2408 | H28: 2664 | I28: 3263 | J28: 3456 | K28: 3456 | L28: 1608 | M28: 2408
A29: 待售貸款（期末） | B29: US$M | C29: 612 | D29: 737 | E29: 767 | F29: 724 | G29: 813 | H29: 982 | I29: 921 | J29: 896 | K29: 896 | L29: 612 | M29: 813
A30: 證券化受益權（期末） | B30: US$M | C30: 464 | D30: 475 | E30: 466 | F30: 486 | G30: 486 | H30: 492 | I30: 502 | J30: 557 | K30: 557 | L30: 464 | M30: 486
A31: 債務合計（含融資租賃，期末） | B31: US$M | C31: 5632 | D31: 5641 | E31: 5707 | F31: 5203 | G31: 5115 | H31: 5154 | I31: 5236 | J31: 5228 | K31: 5228 | L31: 5632 | M31: 5115
A32: 股東權益（含非控制權益，期末） | B32: US$M | C32: 1375 | D32: 1773 | E32: 2117 | F32: 2951 | G32: 4203 | H32: 4632 | I32: 5138 | J32: 5653 | K32: 5653 | L32: 1375 | M32: 4203
A33: 公司口徑總流動性資源（期末） | B33: US$M | C33: 5690 | D33: 5861 | E33: 5981 | F33: 6438 | G33: 6739 | H33: 6910 | I33: 7024 | J33: 7503 | K33: 7503 | L33: 5690 | M33: 6739
A34: 其他毛利（＝其他營收） | B34: US$M | C34: =C8 -> 317 | D34: =D8 -> 389 | E34: =E8 -> 411 | F34: =F8 -> 474 | G34: =G8 -> 459 | H34: =H8 -> 526 | I34: =I8 -> 526 | J34: =J8 -> 594 | ... M34: =M8 -> 1733
A35: 毛利合計 | B35: US$M | C35: =C10+C11+C34 -> 763 | D35: =D10+D11+D34 -> 929 | E35: =E10+E11+E34 -> 1064 | F35: =F10+F11+F34 -> 1148 | G35: =G10+G11+G34 -> 1051 | H35: =H10+H11+H34 -> 1271 | I35: =I10+I11+I34 -> 1384 | J35: =J10+J11+J34 -> 1521 | ... M35: =M10+M11+M34 -> 4192
A36: 核對：營收線合計 − 合併營收 | B36: US$M | C36: =C6+C7+C8-C9 -> 0 | D36: =D6+D7+D8-D9 -> 0 | E36: =E6+E7+E8-E9 -> 0 | F36: =F6+F7+F8-F9 -> 0 | G36: =G6+G7+G8-G9 -> 0 | H36: =H6+H7+H8-H9 -> 0 | I36: =I6+I7+I8-I9 -> 0 | J36: =J6+J7+J8-J9 -> 0 | ... M36: =M6+M7+M8-M9 -> 0
A37: 核對：營業利益＋其他營業費用＋折舊＋SBC − 權證 − 調整後 EBITDA | B37: US$M | C37: =C13+C38+C14+C15-C18-C19 -> 0 | D37: =D13+D38+D14+D15-D18-D19 -> 0 | E37: =E13+E38+E14+E15-E18-E19 -> 0 | F37: =F13+F38+F14+F15-F18-F19 -> 0 | G37: =G13+G38+G14+G15-G18-G19 -> 0 | H37: =H13+H38+H14+H15-H18-H19 -> 0 | I37: =I13+I38+I14+I15-I18-I19 -> 0 | J37: =J13+J38+J14+J15-J18-J19 -> 0 | ... M37: =M13+M38+M14+M15-M18-M19 -> 0
A38: 其他營業費用（推得） | B38: US$M | C38: =C35-C12-C13 -> 9 | D38: =D35-D12-D13 -> 0 | E38: =E35-E12-E13 -> 2 | F38: =F35-F12-F13 -> 1 | G38: =G35-G12-G13 -> 0 | H38: =H35-H12-H13 -> 0 | I38: =I35-I12-I13 -> 0 | J38: =J35-J12-J13 -> 2 | ... M38: =M35-M12-M13 -> 3
A39: 貸款出售利得率 | B39: % | C39: =IF(C16>0,C17/C16,"") -> 0.093942054 | D39: =IF(D16>0,D17/D16,"") -> 0.10263158 | E39: =IF(E16>0,E17/E16,"") -> 0.088788075 | F39: =IF(F16>0,F17/F16,"") -> 0.096389051 | G39: =IF(G16>0,G17/G16,"") -> 0.086848635 | H39: =IF(H16>0,H17/H16,"") -> 0.083215797 | I39: =IF(I16>0,I17/I16,"") -> 0.073458219 | J39: =IF(J16>0,J17/J16,"") -> 0.073523736 | ... M39: =IF(M16>0,M17/M16,"") -> 0.093152182
A40: 總毛利／零售台 | B40: US$ | C40: =C35*1000000/C4 -> 6670.805 | D40: =D35*1000000/D4 -> 6938.1171 | E40: =E35*1000000/E4 -> 7426.019 | F40: =F35*1000000/F4 -> 7361.7586 | G40: =G35*1000000/G4 -> 6427.2697 | H40: =H35*1000000/H4 -> 6782.5372 | I40: =I35*1000000/I4 -> 7013.8097 | J40: =J35*1000000/J4 -> 6996.8029 | ... M40: =M35*1000000/M4 -> 7026.0006
A41: 零售毛利／台 | B41: US$ | C41: =C10*1000000/C4 -> 3226.1167 | D41: =D10*1000000/D4 -> 3203.9314 | E41: =E10*1000000/E4 -> 3636.2367 | F41: =F10*1000000/F4 -> 3456.4354 | G41: =G10*1000000/G4 -> 2990.4233 | H41: =H10*1000000/H4 -> 3164.4725 | I41: =I10*1000000/I4 -> 3547.4471 | J41: =J10*1000000/J4 -> 3555.9031 | ... M41: =M10*1000000/M4 -> 3315.2264
A42: 其他毛利／台 | B42: US$ | C42: =C34*1000000/C4 -> 2771.4878 | D42: =D34*1000000/D4 -> 2905.1965 | E42: =E34*1000000/E4 -> 2868.5092 | F42: =F34*1000000/F4 -> 3039.6111 | G42: =G34*1000000/G4 -> 2806.9618 | H42: =H34*1000000/H4 -> 2806.9352 | I42: =I34*1000000/I4 -> 2665.6531 | J42: =J34*1000000/J4 -> 2732.4792 | ... M42: =M34*1000000/M4 -> 2904.5942
A43: SG&A／台 | B43: US$ | C43: =C12*1000000/C4 -> 4318.9746 | D43: =D12*1000000/D4 -> 3995.5787 | E43: =E12*1000000/E4 -> 3845.617 | F43: =F12*1000000/F4 -> 3815.5456 | G43: =G12*1000000/G4 -> 3834.3464 | H43: =H12*1000000/H4 -> 3682.1013 | I43: =I12*1000000/I4 -> 3567.7182 | J43: =J12*1000000/J4 -> 3703.1074 | ... M43: =M12*1000000/M4 -> 3868.3228
A44: 調整後 EBITDA 率 | B44: % | C44: =C19/C9 -> 0.10121229 | D44: =D19/D9 -> 0.11531191 | E44: =E19/E9 -> 0.12417355 | F44: =F19/F9 -> 0.11280326 | G44: =G19/G9 -> 0.091201142 | H44: =H19/H9 -> 0.10447761 | I44: =I19/I9 -> 0.10425705 | J44: =J19/J9 -> 0.099502488 | ... M44: =M19/M9 -> 0.11007775
A45: 出售利得 ÷ 調整後 EBITDA | B45: % | C45: =C17/C19 -> 0.59610028 | D45: =D17/D19 -> 0.55942623 | E45: =E17/E19 -> 0.45590682 | F45: =F17/F19 -> 0.51962323 | G45: =G17/G19 -> 0.61643836 | H45: =H17/H19 -> 0.52678571 | I45: =I17/I19 -> 0.45383615 | J45: =J17/J19 -> 0.47625 | ... M45: =M17/M19 -> 0.53330353
A46: （出售利得＋關係人其他營收）÷ 調整後 EBITDA | B46: % | C46: =IF(C24="","",(C17+C24)/C19) -> 0.76044568 | D46: =IF(D24="","",(D17+D24)/D19) -> 0.70696721 | E46: =IF(E24="","",(E17+E24)/E19) -> 0.59400998 | F46: =IF(F24="","",(F17+F24)/F19) -> 0.66562009 | G46: =IF(G24="","",(G17+G24)/G19) -> 0.81017613 | H46: =IF(H24="","",(H17+H24)/H19) -> 0.69642857 | I46: =IF(I24="","",(I17+I24)/I19) -> 0.60598179 | J46: =IF(J24="","",(J17+J24)/J19) -> 0.6375 | ... M46: =IF(M24="","",(M17+M24)/M19) -> 0.68842199
A47: 調整後 EBITDA 扣除出售利得 | B47: US$M | C47: =C19-C17 -> 145 | D47: =D19-D17 -> 215 | E47: =E19-E17 -> 327 | F47: =F19-F17 -> 306 | G47: =G19-G17 -> 196 | H47: =H19-H17 -> 318 | I47: =I19-I17 -> 420 | J47: =J19-J17 -> 419 | ... M47: =M19-M17 -> 1044
A48: 扣除出售利得的 EBITDA 率 | B48: % | C48: =C47/C9 -> 0.040879617 | D48: =D47/D9 -> 0.050803403 | E48: =E47/E9 -> 0.067561983 | F48: =F47/F9 -> 0.054188064 | G48: =G47/G9 -> 0.03498126 | H48: =H47/H9 -> 0.049440299 | I48: =I47/I9 -> 0.056941432 | J48: =J47/J9 -> 0.052114428 | ... M48: =M47/M9 -> 0.051372896
A50: 近四季（TTM，Q4 2025–Q3 2026）
A51: 調整後 EBITDA（TTM） | B51: US$M | C51: =SUM(G19:J19) -> 2752
A52: 貸款出售利得（TTM） | B52: US$M | C52: =SUM(G17:J17) -> 1399
A53: 利息費用（TTM） | B53: US$M | C53: =SUM(G20:J20) -> 396
A54: 資本支出（TTM） | B54: US$M | C54: =SUM(G25:J25) -> 217
A55: 營業現金流（TTM） | B55: US$M | C55: =SUM(G26:J26) -> 1330
A56: 關係人其他營收（TTM） | B56: US$M | C56: =SUM(G24:J24) -> 459
A57: 債務／調整後 EBITDA（TTM，2026-09-30） | B57: x | C57: =J31/C51 -> 1.8997093
A58: 淨債務／調整後 EBITDA（TTM） | B58: x | C58: =(J31-J27)/C51 -> 0.79178779
A59: 債務／扣除出售利得的 EBITDA（TTM） | B59: x | C59: =J31/(C51-C52) -> 3.8640059
A60: （EBITDA − 資本支出）／利息（TTM） | B60: x | C60: =(C51-C54)/C53 -> 6.4015152
A61: （出售利得＋關係人其他營收）÷ 調整後 EBITDA（TTM） | B61: % | C61: =(C52+C56)/C51 -> 0.67514535

Sheet Thesis
A1: Thesis — 命題模組：零售台數 × 每台單位經濟。其他毛利拆成「貸款出售利得＝每台發放額 × 利得率」與「非貸款部分（VSC、GAP 等）」；2026 年＝上半年實績＋下半年模型
A2: 讀法：Carvana 的利潤約三到四成來自把車貸賣掉的利得；賣得掉、賣得好，取決於消費信用表現與 ABS 市場。情境 C 的利得率由 Credit 頁 S2 的損失與利差假設推導
A4: 情境 A（樂觀：沿公司 300 萬台路徑、利得率維持）
A5: 項目 | B5: 單位 | C5: FY2025A | D5: FY2026E | E5: FY2027E | F5: FY2028E | G5: FY2029E | H5: FY2030E | I5: FY2031E | J5: FY2032E | K5: FY2033E | L5: FY2034E | M5: FY2035E
A6: 零售台數年增（2027 起為輸入；觸及上限後實際年增較低） | B6: % | C6: =Q!M4/Q!L4-1 -> 0.43303438 | D6: =D7/C7-1 -> 0.38078962 | E6: =g27_A -> 0.32 | F6: =g28_A -> 0.28 | G6: =(g28_A+g30_A)/2 -> 0.24 | H6: =g30_A -> 0.2 | I6: =g30_A+(g35_A-g30_A)*1/5 -> 0.176 | J6: =g30_A+(g35_A-g30_A)*2/5 -> 0.152 | K6: =g30_A+(g35_A-g30_A)*3/5 -> 0.128 | L6: =g30_A+(g35_A-g30_A)*4/5 -> 0.104 | M6: =g30_A+(g35_A-g30_A)*5/5 -> 0.08
A7: 零售台數 | B7: 輛 | C7: =fy25_units -> 596641 | D7: =ytd_units+u_q4 -> 823835.7 | E7: =MIN(D7*(1+E6),unit_cap) -> 1087463.1 | F7: =MIN(E7*(1+F6),unit_cap) -> 1391952.8 | G7: =MIN(F7*(1+G6),unit_cap) -> 1726021.5 | H7: =MIN(G7*(1+H6),unit_cap) -> 2071225.8 | I7: =MIN(H7*(1+I6),unit_cap) -> 2435761.5 | J7: =MIN(I7*(1+J6),unit_cap) -> 2805997.2 | K7: =MIN(J7*(1+K6),unit_cap) -> 3000000 | L7: =MIN(K7*(1+L6),unit_cap) -> 3000000 | M7: =MIN(L7*(1+M6),unit_cap) -> 3000000
A8: 零售每台營收 | B8: US$ | C8: =fy25_rev_ret*1000000/C7 -> 24364.735 | D8: =(ytd_rev_ret*1000000+(D7-ytd_units)*asp_q4)/D7 -> 27609.669 | E8: =D8*(1+asp_g) -> 28161.863 | F8: =E8*(1+asp_g) -> 28725.1 | G8: =F8*(1+asp_g) -> 29299.602 | H8: =G8*(1+asp_g) -> 29885.594 | I8: =H8*(1+asp_g) -> 30483.306 | J8: =I8*(1+asp_g) -> 31092.972 | K8: =J8*(1+asp_g) -> 31714.832 | L8: =K8*(1+asp_g) -> 32349.128 | M8: =L8*(1+asp_g) -> 32996.111
A9: 零售車輛銷售 | B9: US$M | C9: =C7*C8/1000000 -> 14537 | D9: =D7*D8/1000000 -> 22745.831 | E9: =E7*E8/1000000 -> 30624.987 | F9: =F7*F8/1000000 -> 39983.983 | G9: =G7*G8/1000000 -> 50571.742 | H9: =H7*H8/1000000 -> 61899.812 | I9: =I7*I8/1000000 -> 74250.063 | J9: =J7*J8/1000000 -> 87246.794 | ... M9: =M7*M8/1000000 -> 98988.332
A10: 批發營收／零售台 | B10: US$ | C10: =fy25_rev_whs*1000000/C7 -> 6791.3536 | D10: =(ytd_rev_whs*1000000+(D7-ytd_units)*whs_pu)/D7 -> 6183.3274 | E10: =D10*(1+asp_g) -> 6306.994 | F10: =E10*(1+asp_g) -> 6433.1339 | G10: =F10*(1+asp_g) -> 6561.7965 | H10: =G10*(1+asp_g) -> 6693.0325 | I10: =H10*(1+asp_g) -> 6826.8931 | J10: =I10*(1+asp_g) -> 6963.431 | K10: =J10*(1+asp_g) -> 7102.6996 | L10: =K10*(1+asp_g) -> 7244.7536 | M10: =L10*(1+asp_g) -> 7389.6487
A11: 批發銷售與營收 | B11: US$M | C11: =C7*C10/1000000 -> 4052 | D11: =D7*D10/1000000 -> 5094.0459 | E11: =E7*E10/1000000 -> 6858.6234 | F11: =F7*F10/1000000 -> 8954.6187 | G11: =G7*G10/1000000 -> 11325.802 | H11: =H7*H10/1000000 -> 13862.781 | I11: =I7*I10/1000000 -> 16628.683 | J11: =J7*J10/1000000 -> 19539.368 | ... M11: =M7*M10/1000000 -> 22168.946
A12: 零售毛利／台 | B12: US$ | C12: =fy25_gp_ret*1000000/C7 -> 3315.2264 | D12: =(ytd_gp_ret*1000000+(D7-ytd_units)*(gpr_q4+q4_adj))/D7 -> 3303.3794 | E12: =gpr27_A -> 3600 | F12: =gpr27_A+(gprLT_A-gpr27_A)/3 -> 3633.3333 | G12: =gpr27_A+(gprLT_A-gpr27_A)*2/3 -> 3666.6667 | H12: =gprLT_A -> 3700 | I12: =gprLT_A -> 3700 | J12: =gprLT_A -> 3700 | K12: =gprLT_A -> 3700 | L12: =gprLT_A -> 3700 | M12: =gprLT_A -> 3700
A13: 批發毛利／零售台 | B13: US$ | C13: =fy25_gp_whs*1000000/C7 -> 806.17993 | D13: =(ytd_gp_whs*1000000+(D7-ytd_units)*gpw_h2)/D7 -> 753.775 | E13: =gpw_h2 -> 708 | F13: =gpw_h2 -> 708 | G13: =gpw_h2 -> 708 | H13: =gpw_h2 -> 708 | I13: =gpw_h2 -> 708 | J13: =gpw_h2 -> 708 | K13: =gpw_h2 -> 708 | L13: =gpw_h2 -> 708 | M13: =gpw_h2 -> 708
A14: 每零售台貸款發放額 | B14: US$ | C14: =fy25_orig*1000000/C7 -> 21465.169 | D14: =(ytd_orig*1000000+(D7-ytd_units)*opu)/D7 -> 23636.558 | E14: =D14*(1+asp_g) -> 24109.289 | F14: =E14*(1+asp_g) -> 24591.475 | G14: =F14*(1+asp_g) -> 25083.304 | H14: =G14*(1+asp_g) -> 25584.97 | I14: =H14*(1+asp_g) -> 26096.67 | J14: =I14*(1+asp_g) -> 26618.603 | K14: =J14*(1+asp_g) -> 27150.975 | L14: =K14*(1+asp_g) -> 27693.994 | M14: =L14*(1+asp_g) -> 28247.874
A15: 貸款發放 | B15: US$M | C15: =C7*C14/1000000 -> 12807 | D15: =D7*D14/1000000 -> 19472.64 | E15: =E7*E14/1000000 -> 26217.962 | F15: =F7*F14/1000000 -> 34230.172 | G15: =G7*G14/1000000 -> 43294.321 | H15: =H7*H14/1000000 -> 52992.249 | I15: =I7*I14/1000000 -> 63565.263 | J15: =J7*J14/1000000 -> 74691.727 | ... M15: =M7*M14/1000000 -> 84743.623
A16: 貸款出售利得率 | B16: % | C16: =fy25_gos/fy25_orig -> 0.093152182 | D16: =(ytd_gos+(D15-ytd_orig)*gos_h2)/D15 -> 0.075625082 | E16: =gos27_A -> 0.08 | F16: =gos27_A+(gosLT_A-gos27_A)/3 -> 0.08 | G16: =gos27_A+(gosLT_A-gos27_A)*2/3 -> 0.08 | H16: =gosLT_A -> 0.08 | I16: =gosLT_A -> 0.08 | J16: =gosLT_A -> 0.08 | K16: =gosLT_A -> 0.08 | L16: =gosLT_A -> 0.08 | M16: =gosLT_A -> 0.08
A17: 貸款出售利得（其他毛利之一） | B17: US$M | C17: =C15*C16 -> 1193 | D17: =D15*D16 -> 1472.62 | E17: =E15*E16 -> 2097.437 | F17: =F15*F16 -> 2738.4137 | G17: =G15*G16 -> 3463.5457 | H17: =H15*H16 -> 4239.3799 | I17: =I15*I16 -> 5085.221 | J17: =J15*J16 -> 5975.3381 | ... M17: =M15*M16 -> 6779.4898
A18: 非貸款其他毛利／台 | B18: US$ | C18: =(Q!M8-fy25_gos)*1000000/C7 -> 905.06687 | D18: =((Q!K8-ytd_gos)*1000000+(D7-ytd_units)*oth_pu)/D7 -> 945.89249 | E18: =D18*(1+oth_g) -> 945.89249 | F18: =E18*(1+oth_g) -> 945.89249 | G18: =F18*(1+oth_g) -> 945.89249 | H18: =G18*(1+oth_g) -> 945.89249 | I18: =H18*(1+oth_g) -> 945.89249 | J18: =I18*(1+oth_g) -> 945.89249 | K18: =J18*(1+oth_g) -> 945.89249 | L18: =K18*(1+oth_g) -> 945.89249 | M18: =L18*(1+oth_g) -> 945.89249
A19: 非貸款其他毛利（VSC、GAP 等） | B19: US$M | C19: =C7*C18/1000000 -> 540 | D19: =D7*D18/1000000 -> 779.26 | E19: =E7*E18/1000000 -> 1028.6232 | F19: =F7*F18/1000000 -> 1316.6377 | G19: =G7*G18/1000000 -> 1632.6307 | H19: =H7*H18/1000000 -> 1959.1569 | I19: =I7*I18/1000000 -> 2303.9685 | J19: =J7*J18/1000000 -> 2654.1717 | ... M19: =M7*M18/1000000 -> 2837.6775
A20: 零售毛利 | B20: US$M | C20: =C7*C12/1000000 -> 1978 | D20: =D7*D12/1000000 -> 2721.4419 | E20: =E7*E12/1000000 -> 3914.8672 | F20: =F7*F12/1000000 -> 5057.4285 | G20: =G7*G12/1000000 -> 6328.7454 | H20: =H7*H12/1000000 -> 7663.5353 | I20: =I7*I12/1000000 -> 9012.3175 | J20: =J7*J12/1000000 -> 10382.19 | ... M20: =M7*M12/1000000 -> 11100
A21: 批發毛利 | B21: US$M | C21: =C7*C13/1000000 -> 481 | D21: =D7*D13/1000000 -> 620.98675 | E21: =E7*E13/1000000 -> 769.92389 | F21: =F7*F13/1000000 -> 985.50258 | G21: =G7*G13/1000000 -> 1222.0232 | H21: =H7*H13/1000000 -> 1466.4278 | I21: =I7*I13/1000000 -> 1724.5191 | J21: =J7*J13/1000000 -> 1986.6461 | ... M21: =M7*M13/1000000 -> 2124
A22: 其他毛利（＝其他營收） | B22: US$M | C22: =C17+C19 -> 1733 | D22: =D17+D19 -> 2251.88 | E22: =E17+E19 -> 3126.0602 | F22: =F17+F19 -> 4055.0514 | G22: =G17+G19 -> 5096.1764 | H22: =H17+H19 -> 6198.5368 | I22: =I17+I19 -> 7389.1895 | J22: =J17+J19 -> 8629.5098 | ... M22: =M17+M19 -> 9617.1673
A23: 總毛利／台 | B23: US$ | C23: =(C20+C21+C22)*1000000/C7 -> 7026.0006 | D23: =(D20+D21+D22)*1000000/D7 -> 6790.5635 | E23: =(E20+E21+E22)*1000000/E7 -> 7182.6356 | F23: =(F20+F21+F22)*1000000/F7 -> 7254.5438 | G23: =(G20+G21+G22)*1000000/G7 -> 7327.2235 | H23: =(H20+H21+H22)*1000000/H7 -> 7400.6901 | I23: =(I20+I21+I22)*1000000/I7 -> 7441.6261 | J23: =(J20+J21+J22)*1000000/J7 -> 7483.3807 | ... M23: =(M20+M21+M22)*1000000/M7 -> 7613.7224
A24: SG&A | B24: US$M | C24: =Q!M12 -> 2308 | D24: =ytd_sga+sga_fix+(D7-ytd_units)*sga_var/1000000 -> 2989.8516 | E24: =4*sga_fix*(1+infl)^1+E7*sga_var*(1-eff_A)^1/1000000 -> 3653.9498 | F24: =4*sga_fix*(1+infl)^2+F7*sga_var*(1-eff_A)^2/1000000 -> 4388.5395 | G24: =4*sga_fix*(1+infl)^3+G7*sga_var*(1-eff_A)^3/1000000 -> 5153.8753 | H24: =4*sga_fix*(1+infl)^4+H7*sga_var*(1-eff_A)^4/1000000 -> 5899.5416 | I24: =4*sga_fix*(1+infl)^5+I7*sga_var*(1-eff_A)^5/1000000 -> 6644.9859 | J24: =4*sga_fix*(1+infl)^6+J7*sga_var*(1-eff_A)^6/1000000 -> 7356.4436 | K24: =4*sga_fix*(1+infl)^7+K7*sga_var*(1-eff_A)^7/1000000 -> 7623.3701 | L24: =4*sga_fix*(1+infl)^8+L7*sga_var*(1-eff_A)^8/1000000 -> 7444.8479 | M24: =4*sga_fix*(1+infl)^9+M7*sga_var*(1-eff_A)^9/1000000 -> 7273.1867
A25: SG&A／台 | B25: US$ | C25: =C24*1000000/C7 -> 3868.3228 | D25: =D24*1000000/D7 -> 3629.1843 | E25: =E24*1000000/E7 -> 3360.0678 | F25: =F24*1000000/F7 -> 3152.7933 | G25: =G24*1000000/G7 -> 2985.9856 | H25: =H24*1000000/H7 -> 2848.3334 | I25: =I24*1000000/I7 -> 2728.0938 | J25: =J24*1000000/J7 -> 2621.686 | ... M25: =M24*1000000/M7 -> 2424.3956
A26: 變動 SG&A／台 | B26: US$ | D26: =sga_var -> 2800 | E26: =sga_var*(1-eff_A)^1 -> 2716 | F26: =sga_var*(1-eff_A)^2 -> 2634.52 | G26: =sga_var*(1-eff_A)^3 -> 2555.4844 | H26: =sga_var*(1-eff_A)^4 -> 2478.8199 | I26: =sga_var*(1-eff_A)^5 -> 2404.4553 | J26: =sga_var*(1-eff_A)^6 -> 2332.3216 | K26: =sga_var*(1-eff_A)^7 -> 2262.352 | L26: =sga_var*(1-eff_A)^8 -> 2194.4814 | M26: =sga_var*(1-eff_A)^9 -> 2128.647
A27: 年產能（期末，足以支應次年台數） | B27: 輛 | D27: =MAX(cap_0,E7/util) -> 1500000 | E27: =MAX(D27,MIN(F7,unit_cap)/util) -> 1637591.5 | F27: =MAX(E27,MIN(G7,unit_cap)/util) -> 2030613.5 | G27: =MAX(F27,MIN(H7,unit_cap)/util) -> 2436736.2 | H27: =MAX(G27,MIN(I7,unit_cap)/util) -> 2865601.8 | I27: =MAX(H27,MIN(J7,unit_cap)/util) -> 3301173.2 | J27: =MAX(I27,MIN(K7,unit_cap)/util) -> 3529411.8 | K27: =MAX(J27,MIN(L7,unit_cap)/util) -> 3529411.8 | L27: =MAX(K27,MIN(M7,unit_cap)/util) -> 3529411.8 | M27: =MAX(L27,MIN(M7*(1+M6),unit_cap)/util) -> 3529411.8
A28: 成長性資本支出（新增產能 × 每台成本） | B28: US$M | D28: =0 -> 0 | E28: =(E27-D27)*capcost/1000000 -> 82.554917 | F28: =(F27-E27)*capcost/1000000 -> 235.81318 | G28: =(G27-F27)*capcost/1000000 -> 243.67362 | H28: =(H27-G27)*capcost/1000000 -> 257.31934 | I28: =(I27-H27)*capcost/1000000 -> 261.34288 | J28: =(J27-I27)*capcost/1000000 -> 136.94312 | K28: =(K27-J27)*capcost/1000000 -> 0 | L28: =(L27-K27)*capcost/1000000 -> 0 | M28: =(M27-L27)*capcost/1000000 -> 0
A31: 情境 B（基準：成長放緩、利得率小降）
A32: 項目 | B32: 單位 | C32: FY2025A | D32: FY2026E | E32: FY2027E | F32: FY2028E | G32: FY2029E | H32: FY2030E | I32: FY2031E | J32: FY2032E | K32: FY2033E | L32: FY2034E | M32: FY2035E
A33: 零售台數年增（2027 起為輸入；觸及上限後實際年增較低） | B33: % | C33: =Q!M4/Q!L4-1 -> 0.43303438 | D33: =D34/C34-1 -> 0.38078962 | E33: =g27_B -> 0.25 | F33: =g28_B -> 0.2 | G33: =(g28_B+g30_B)/2 -> 0.165 | H33: =g30_B -> 0.13 | I33: =g30_B+(g35_B-g30_B)*1/5 -> 0.114 | J33: =g30_B+(g35_B-g30_B)*2/5 -> 0.098 | K33: =g30_B+(g35_B-g30_B)*3/5 -> 0.082 | L33: =g30_B+(g35_B-g30_B)*4/5 -> 0.066 | M33: =g30_B+(g35_B-g30_B)*5/5 -> 0.05
A34: 零售台數 | B34: 輛 | C34: =fy25_units -> 596641 | D34: =ytd_units+u_q4 -> 823835.7 | E34: =MIN(D34*(1+E33),unit_cap) -> 1029794.6 | F34: =MIN(E34*(1+F33),unit_cap) -> 1235753.6 | G34: =MIN(F34*(1+G33),unit_cap) -> 1439652.9 | H34: =MIN(G34*(1+H33),unit_cap) -> 1626807.8 | I34: =MIN(H34*(1+I33),unit_cap) -> 1812263.8 | J34: =MIN(I34*(1+J33),unit_cap) -> 1989865.7 | K34: =MIN(J34*(1+K33),unit_cap) -> 2153034.7 | L34: =MIN(K34*(1+L33),unit_cap) -> 2295135 | M34: =MIN(L34*(1+M33),unit_cap) -> 2409891.7
A35: 零售每台營收 | B35: US$ | C35: =fy25_rev_ret*1000000/C34 -> 24364.735 | D35: =(ytd_rev_ret*1000000+(D34-ytd_units)*asp_q4)/D34 -> 27609.669 | E35: =D35*(1+asp_g) -> 28161.863 | F35: =E35*(1+asp_g) -> 28725.1 | G35: =F35*(1+asp_g) -> 29299.602 | H35: =G35*(1+asp_g) -> 29885.594 | I35: =H35*(1+asp_g) -> 30483.306 | J35: =I35*(1+asp_g) -> 31092.972 | K35: =J35*(1+asp_g) -> 31714.832 | L35: =K35*(1+asp_g) -> 32349.128 | M35: =L35*(1+asp_g) -> 32996.111
A36: 零售車輛銷售 | B36: US$M | C36: =C34*C35/1000000 -> 14537 | D36: =D34*D35/1000000 -> 22745.831 | E36: =E34*E35/1000000 -> 29000.935 | F36: =F34*F35/1000000 -> 35497.144 | G36: =G34*G35/1000000 -> 42181.257 | H36: =H34*H35/1000000 -> 48618.116 | I36: =I34*I35/1000000 -> 55243.793 | J36: =J34*J35/1000000 -> 61870.839 | ... M36: =M34*M35/1000000 -> 79517.054
A37: 批發營收／零售台 | B37: US$ | C37: =fy25_rev_whs*1000000/C34 -> 6791.3536 | D37: =(ytd_rev_whs*1000000+(D34-ytd_units)*whs_pu)/D34 -> 6183.3274 | E37: =D37*(1+asp_g) -> 6306.994 | F37: =E37*(1+asp_g) -> 6433.1339 | G37: =F37*(1+asp_g) -> 6561.7965 | H37: =G37*(1+asp_g) -> 6693.0325 | I37: =H37*(1+asp_g) -> 6826.8931 | J37: =I37*(1+asp_g) -> 6963.431 | K37: =J37*(1+asp_g) -> 7102.6996 | L37: =K37*(1+asp_g) -> 7244.7536 | M37: =L37*(1+asp_g) -> 7389.6487
A38: 批發銷售與營收 | B38: US$M | C38: =C34*C37/1000000 -> 4052 | D38: =D34*D37/1000000 -> 5094.0459 | E38: =E34*E37/1000000 -> 6494.9085 | F38: =F34*F37/1000000 -> 7949.768 | G38: =G34*G37/1000000 -> 9446.7093 | H38: =H34*H37/1000000 -> 10888.277 | I38: =I34*I37/1000000 -> 12372.132 | J38: =J34*J37/1000000 -> 13856.292 | ... M38: =M34*M37/1000000 -> 17808.253
A39: 零售毛利／台 | B39: US$ | C39: =fy25_gp_ret*1000000/C34 -> 3315.2264 | D39: =(ytd_gp_ret*1000000+(D34-ytd_units)*(gpr_q4+q4_adj))/D34 -> 3303.3794 | E39: =gpr27_B -> 3450 | F39: =gpr27_B+(gprLT_B-gpr27_B)/3 -> 3416.6667 | G39: =gpr27_B+(gprLT_B-gpr27_B)*2/3 -> 3383.3333 | H39: =gprLT_B -> 3350 | I39: =gprLT_B -> 3350 | J39: =gprLT_B -> 3350 | K39: =gprLT_B -> 3350 | L39: =gprLT_B -> 3350 | M39: =gprLT_B -> 3350
A40: 批發毛利／零售台 | B40: US$ | C40: =fy25_gp_whs*1000000/C34 -> 806.17993 | D40: =(ytd_gp_whs*1000000+(D34-ytd_units)*gpw_h2)/D34 -> 753.775 | E40: =gpw_h2 -> 708 | F40: =gpw_h2 -> 708 | G40: =gpw_h2 -> 708 | H40: =gpw_h2 -> 708 | I40: =gpw_h2 -> 708 | J40: =gpw_h2 -> 708 | K40: =gpw_h2 -> 708 | L40: =gpw_h2 -> 708 | M40: =gpw_h2 -> 708
A41: 每零售台貸款發放額 | B41: US$ | C41: =fy25_orig*1000000/C34 -> 21465.169 | D41: =(ytd_orig*1000000+(D34-ytd_units)*opu)/D34 -> 23636.558 | E41: =D41*(1+asp_g) -> 24109.289 | F41: =E41*(1+asp_g) -> 24591.475 | G41: =F41*(1+asp_g) -> 25083.304 | H41: =G41*(1+asp_g) -> 25584.97 | I41: =H41*(1+asp_g) -> 26096.67 | J41: =I41*(1+asp_g) -> 26618.603 | K41: =J41*(1+asp_g) -> 27150.975 | L41: =K41*(1+asp_g) -> 27693.994 | M41: =L41*(1+asp_g) -> 28247.874
A42: 貸款發放 | B42: US$M | C42: =C34*C41/1000000 -> 12807 | D42: =D34*D41/1000000 -> 19472.64 | E42: =E34*E41/1000000 -> 24827.616 | F42: =F34*F41/1000000 -> 30389.002 | G42: =G34*G41/1000000 -> 36111.251 | H42: =H34*H41/1000000 -> 41621.828 | I42: =I34*I41/1000000 -> 47294.051 | J42: =J34*J41/1000000 -> 52967.445 | ... M42: =M34*M41/1000000 -> 68074.319
A43: 貸款出售利得率 | B43: % | C43: =fy25_gos/fy25_orig -> 0.093152182 | D43: =(ytd_gos+(D42-ytd_orig)*gos_h2)/D42 -> 0.075625082 | E43: =gos27_B -> 0.072 | F43: =gos27_B+(gosLT_B-gos27_B)/3 -> 0.071333333 | G43: =gos27_B+(gosLT_B-gos27_B)*2/3 -> 0.070666667 | H43: =gosLT_B -> 0.07 | I43: =gosLT_B -> 0.07 | J43: =gosLT_B -> 0.07 | K43: =gosLT_B -> 0.07 | L43: =gosLT_B -> 0.07 | M43: =gosLT_B -> 0.07
A44: 貸款出售利得（其他毛利之一） | B44: US$M | C44: =C42*C43 -> 1193 | D44: =D42*D43 -> 1472.62 | E44: =E42*E43 -> 1787.5884 | F44: =F42*F43 -> 2167.7488 | G44: =G42*G43 -> 2551.8617 | H44: =H42*H43 -> 2913.528 | I44: =I42*I43 -> 3310.5835 | J44: =J42*J43 -> 3707.7212 | ... M44: =M42*M43 -> 4765.2023
A45: 非貸款其他毛利／台 | B45: US$ | C45: =(Q!M8-fy25_gos)*1000000/C34 -> 905.06687 | D45: =((Q!K8-ytd_gos)*1000000+(D34-ytd_units)*oth_pu)/D34 -> 945.89249 | E45: =D45*(1+oth_g) -> 945.89249 | F45: =E45*(1+oth_g) -> 945.89249 | G45: =F45*(1+oth_g) -> 945.89249 | H45: =G45*(1+oth_g) -> 945.89249 | I45: =H45*(1+oth_g) -> 945.89249 | J45: =I45*(1+oth_g) -> 945.89249 | K45: =J45*(1+oth_g) -> 945.89249 | L45: =K45*(1+oth_g) -> 945.89249 | M45: =L45*(1+oth_g) -> 945.89249
A46: 非貸款其他毛利（VSC、GAP 等） | B46: US$M | C46: =C34*C45/1000000 -> 540 | D46: =D34*D45/1000000 -> 779.26 | E46: =E34*E45/1000000 -> 974.075 | F46: =F34*F45/1000000 -> 1168.89 | G46: =G34*G45/1000000 -> 1361.7568 | H46: =H34*H45/1000000 -> 1538.7852 | I46: =I34*I45/1000000 -> 1714.2068 | J46: =J34*J45/1000000 -> 1882.199 | ... M46: =M34*M45/1000000 -> 2279.4985
A47: 零售毛利 | B47: US$M | C47: =C34*C39/1000000 -> 1978 | D47: =D34*D39/1000000 -> 2721.4419 | E47: =E34*E39/1000000 -> 3552.7915 | F47: =F34*F39/1000000 -> 4222.158 | G47: =G34*G39/1000000 -> 4870.8256 | H47: =H34*H39/1000000 -> 5449.806 | I47: =I34*I39/1000000 -> 6071.0839 | J47: =J34*J39/1000000 -> 6666.0501 | ... M47: =M34*M39/1000000 -> 8073.1373
A48: 批發毛利 | B48: US$M | C48: =C34*C40/1000000 -> 481 | D48: =D34*D40/1000000 -> 620.98675 | E48: =E34*E40/1000000 -> 729.09459 | F48: =F34*F40/1000000 -> 874.91351 | G48: =G34*G40/1000000 -> 1019.2742 | H48: =H34*H40/1000000 -> 1151.7799 | I48: =I34*I40/1000000 -> 1283.0828 | J48: =J34*J40/1000000 -> 1408.8249 | ... M48: =M34*M40/1000000 -> 1706.2033
A49: 其他毛利（＝其他營收） | B49: US$M | C49: =C44+C46 -> 1733 | D49: =D44+D46 -> 2251.88 | E49: =E44+E46 -> 2761.6634 | F49: =F44+F46 -> 3336.6388 | G49: =G44+G46 -> 3913.6186 | H49: =H44+H46 -> 4452.3132 | I49: =I44+I46 -> 5024.7903 | J49: =J44+J46 -> 5589.9202 | ... M49: =M44+M46 -> 7044.7008
A50: 總毛利／台 | B50: US$ | C50: =(C47+C48+C49)*1000000/C34 -> 7026.0006 | D50: =(D47+D48+D49)*1000000/D34 -> 6790.5635 | E50: =(E47+E48+E49)*1000000/E34 -> 6839.7613 | F50: =(F47+F48+F49)*1000000/F34 -> 6824.751 | G50: =(G47+G48+G49)*1000000/G34 -> 6809.7793 | H50: =(H47+H48+H49)*1000000/H34 -> 6794.8404 | I50: =(I47+I48+I49)*1000000/I34 -> 6830.6594 | J50: =(J47+J48+J49)*1000000/J34 -> 6867.1947 | ... M50: =(M47+M48+M49)*1000000/M34 -> 6981.2437
A51: SG&A | B51: US$M | C51: =Q!M12 -> 2308 | D51: =ytd_sga+sga_fix+(D34-ytd_units)*sga_var/1000000 -> 2989.8516 | E51: =4*sga_fix*(1+infl)^1+E34*sga_var*(1-eff_B)^1/1000000 -> 3540.5736 | F51: =4*sga_fix*(1+infl)^2+F34*sga_var*(1-eff_B)^2/1000000 -> 4078.4972 | G51: =4*sga_fix*(1+infl)^3+G34*sga_var*(1-eff_B)^3/1000000 -> 4595.3935 | H51: =4*sga_fix*(1+infl)^4+H34*sga_var*(1-eff_B)^4/1000000 -> 5053.1921 | I51: =4*sga_fix*(1+infl)^5+I34*sga_var*(1-eff_B)^5/1000000 -> 5493.317 | J51: =4*sga_fix*(1+infl)^6+J34*sga_var*(1-eff_B)^6/1000000 -> 5900.5657 | K51: =4*sga_fix*(1+infl)^7+K34*sga_var*(1-eff_B)^7/1000000 -> 6259.6023 | L51: =4*sga_fix*(1+infl)^8+L34*sga_var*(1-eff_B)^8/1000000 -> 6555.9103 | M51: =4*sga_fix*(1+infl)^9+M34*sga_var*(1-eff_B)^9/1000000 -> 6776.7893
A52: SG&A／台 | B52: US$ | C52: =C51*1000000/C34 -> 3868.3228 | D52: =D51*1000000/D34 -> 3629.1843 | E52: =E51*1000000/E34 -> 3438.1356 | F52: =F51*1000000/F34 -> 3300.4131 | G52: =G51*1000000/G34 -> 3192.0149 | H52: =H51*1000000/H34 -> 3106.2011 | I52: =I51*1000000/I34 -> 3031.1905 | J52: =J51*1000000/J34 -> 2965.3085 | ... M52: =M51*1000000/M34 -> 2812.0721
A53: 變動 SG&A／台 | B53: US$ | D53: =sga_var -> 2800 | E53: =sga_var*(1-eff_B)^1 -> 2758 | F53: =sga_var*(1-eff_B)^2 -> 2716.63 | G53: =sga_var*(1-eff_B)^3 -> 2675.8805 | H53: =sga_var*(1-eff_B)^4 -> 2635.7423 | I53: =sga_var*(1-eff_B)^5 -> 2596.2062 | J53: =sga_var*(1-eff_B)^6 -> 2557.2631 | K53: =sga_var*(1-eff_B)^7 -> 2518.9042 | L53: =sga_var*(1-eff_B)^8 -> 2481.1206 | M53: =sga_var*(1-eff_B)^9 -> 2443.9038
A54: 年產能（期末，足以支應次年台數） | B54: 輛 | D54: =MAX(cap_0,E34/util) -> 1500000 | E54: =MAX(D54,MIN(F34,unit_cap)/util) -> 1500000 | F54: =MAX(E54,MIN(G34,unit_cap)/util) -> 1693709.3 | G54: =MAX(F54,MIN(H34,unit_cap)/util) -> 1913891.5 | H54: =MAX(G54,MIN(I34,unit_cap)/util) -> 2132075.1 | I54: =MAX(H54,MIN(J34,unit_cap)/util) -> 2341018.5 | J54: =MAX(I54,MIN(K34,unit_cap)/util) -> 2532982 | K54: =MAX(J54,MIN(L34,unit_cap)/util) -> 2700158.8 | L54: =MAX(K54,MIN(M34,unit_cap)/util) -> 2835166.7 | M54: =MAX(L54,MIN(M34*(1+M33),unit_cap)/util) -> 2976925.1
A55: 成長性資本支出（新增產能 × 每台成本） | B55: US$M | D55: =0 -> 0 | E55: =(E54-D54)*capcost/1000000 -> 0 | F55: =(F54-E54)*capcost/1000000 -> 116.22557 | G55: =(G54-F54)*capcost/1000000 -> 132.10932 | H55: =(H54-G54)*capcost/1000000 -> 130.91018 | I55: =(I54-H54)*capcost/1000000 -> 125.36602 | J55: =(J54-I54)*capcost/1000000 -> 115.17811 | K55: =(K54-J54)*capcost/1000000 -> 100.30609 | L55: =(L54-K54)*capcost/1000000 -> 81.004764 | M55: =(M54-L54)*capcost/1000000 -> 85.055002
A58: 情境 C（信用壓力：2027 年次級車貸循環＋二手車價下跌）
A59: 項目 | B59: 單位 | C59: FY2025A | D59: FY2026E | E59: FY2027E | F59: FY2028E | G59: FY2029E | H59: FY2030E | I59: FY2031E | J59: FY2032E | K59: FY2033E | L59: FY2034E | M59: FY2035E
A60: 零售台數年增（2027 起為輸入；觸及上限後實際年增較低） | B60: % | C60: =Q!M4/Q!L4-1 -> 0.43303438 | D60: =D61/C61-1 -> 0.38078962 | E60: =g27_C -> -0.1 | F60: =g28_C -> 0.05 | G60: =(g28_C+g30_C)/2 -> 0.075 | H60: =g30_C -> 0.1 | I60: =g30_C+(g35_C-g30_C)*1/5 -> 0.088 | J60: =g30_C+(g35_C-g30_C)*2/5 -> 0.076 | K60: =g30_C+(g35_C-g30_C)*3/5 -> 0.064 | L60: =g30_C+(g35_C-g30_C)*4/5 -> 0.052 | M60: =g30_C+(g35_C-g30_C)*5/5 -> 0.04
A61: 零售台數 | B61: 輛 | C61: =fy25_units -> 596641 | D61: =ytd_units+u_q4 -> 823835.7 | E61: =MIN(D61*(1+E60),unit_cap) -> 741452.13 | F61: =MIN(E61*(1+F60),unit_cap) -> 778524.74 | G61: =MIN(F61*(1+G60),unit_cap) -> 836914.09 | H61: =MIN(G61*(1+H60),unit_cap) -> 920605.5 | I61: =MIN(H61*(1+I60),unit_cap) -> 1001618.8 | J61: =MIN(I61*(1+J60),unit_cap) -> 1077741.8 | K61: =MIN(J61*(1+K60),unit_cap) -> 1146717.3 | L61: =MIN(K61*(1+L60),unit_cap) -> 1206346.6 | M61: =MIN(L61*(1+M60),unit_cap) -> 1254600.5
A62: 零售每台營收 | B62: US$ | C62: =fy25_rev_ret*1000000/C61 -> 24364.735 | D62: =(ytd_rev_ret*1000000+(D61-ytd_units)*asp_q4)/D61 -> 27609.669 | E62: =D62*(1+asp_g) -> 28161.863 | F62: =E62*(1+asp_g) -> 28725.1 | G62: =F62*(1+asp_g) -> 29299.602 | H62: =G62*(1+asp_g) -> 29885.594 | I62: =H62*(1+asp_g) -> 30483.306 | J62: =I62*(1+asp_g) -> 31092.972 | K62: =J62*(1+asp_g) -> 31714.832 | L62: =K62*(1+asp_g) -> 32349.128 | M62: =L62*(1+asp_g) -> 32996.111
A63: 零售車輛銷售 | B63: US$M | C63: =C61*C62/1000000 -> 14537 | D63: =D61*D62/1000000 -> 22745.831 | E63: =E61*E62/1000000 -> 20880.673 | F63: =F61*F62/1000000 -> 22363.201 | G63: =G61*G62/1000000 -> 24521.25 | H63: =H61*H62/1000000 -> 27512.842 | I63: =I61*I62/1000000 -> 30532.652 | J63: =J61*J62/1000000 -> 33510.196 | ... M63: =M61*M62/1000000 -> 41396.935
A64: 批發營收／零售台 | B64: US$ | C64: =fy25_rev_whs*1000000/C61 -> 6791.3536 | D64: =(ytd_rev_whs*1000000+(D61-ytd_units)*whs_pu)/D61 -> 6183.3274 | E64: =D64*(1+asp_g) -> 6306.994 | F64: =E64*(1+asp_g) -> 6433.1339 | G64: =F64*(1+asp_g) -> 6561.7965 | H64: =G64*(1+asp_g) -> 6693.0325 | I64: =H64*(1+asp_g) -> 6826.8931 | J64: =I64*(1+asp_g) -> 6963.431 | K64: =J64*(1+asp_g) -> 7102.6996 | L64: =K64*(1+asp_g) -> 7244.7536 | M64: =L64*(1+asp_g) -> 7389.6487
A65: 批發銷售與營收 | B65: US$M | C65: =C61*C64/1000000 -> 4052 | D65: =D61*D64/1000000 -> 5094.0459 | E65: =E61*E64/1000000 -> 4676.3341 | F65: =F61*F64/1000000 -> 5008.3538 | G65: =G61*G64/1000000 -> 5491.66 | H65: =H61*H64/1000000 -> 6161.6425 | I65: =I61*I64/1000000 -> 6837.9444 | J65: =J61*J64/1000000 -> 7504.7807 | ... M65: =M61*M64/1000000 -> 9271.0566
A66: 零售毛利／台 | B66: US$ | C66: =fy25_gp_ret*1000000/C61 -> 3315.2264 | D66: =(ytd_gp_ret*1000000+(D61-ytd_units)*(gpr_q4+q4_adj))/D61 -> 3303.3794 | E66: =gpr27_C -> 2700 | F66: =gpr27_C+(gprLT_C-gpr27_C)/3 -> 2833.3333 | G66: =gpr27_C+(gprLT_C-gpr27_C)*2/3 -> 2966.6667 | H66: =gprLT_C -> 3100 | I66: =gprLT_C -> 3100 | J66: =gprLT_C -> 3100 | K66: =gprLT_C -> 3100 | L66: =gprLT_C -> 3100 | M66: =gprLT_C -> 3100
A67: 批發毛利／零售台 | B67: US$ | C67: =fy25_gp_whs*1000000/C61 -> 806.17993 | D67: =(ytd_gp_whs*1000000+(D61-ytd_units)*gpw_h2)/D61 -> 753.775 | E67: =gpw27_C -> 650 | F67: =gpw27_C+(gpw_h2-gpw27_C)/3 -> 669.33333 | G67: =gpw27_C+(gpw_h2-gpw27_C)*2/3 -> 688.66667 | H67: =gpw_h2 -> 708 | I67: =gpw_h2 -> 708 | J67: =gpw_h2 -> 708 | K67: =gpw_h2 -> 708 | L67: =gpw_h2 -> 708 | M67: =gpw_h2 -> 708
A68: 每零售台貸款發放額 | B68: US$ | C68: =fy25_orig*1000000/C61 -> 21465.169 | D68: =(ytd_orig*1000000+(D61-ytd_units)*opu)/D61 -> 23636.558 | E68: =D68*(1+asp_g) -> 24109.289 | F68: =E68*(1+asp_g) -> 24591.475 | G68: =F68*(1+asp_g) -> 25083.304 | H68: =G68*(1+asp_g) -> 25584.97 | I68: =H68*(1+asp_g) -> 26096.67 | J68: =I68*(1+asp_g) -> 26618.603 | K68: =J68*(1+asp_g) -> 27150.975 | L68: =K68*(1+asp_g) -> 27693.994 | M68: =L68*(1+asp_g) -> 28247.874
A69: 貸款發放 | B69: US$M | C69: =C61*C68/1000000 -> 12807 | D69: =D61*D68/1000000 -> 19472.64 | E69: =E61*E68/1000000 -> 17875.884 | F69: =F61*F68/1000000 -> 19145.071 | G69: =G61*G68/1000000 -> 20992.571 | H69: =H61*H68/1000000 -> 23553.664 | I69: =I61*I68/1000000 -> 26138.914 | J69: =J61*J68/1000000 -> 28687.981 | ... M69: =M61*M68/1000000 -> 35439.796
A70: 貸款出售利得率 | B70: % | C70: =fy25_gos/fy25_orig -> 0.093152182 | D70: =(ytd_gos+(D69-ytd_orig)*gos_h2)/D69 -> 0.075625082 | E70: =gos27_C -> 0.034 | F70: =gos27_C+(gosLT_C-gos27_C)/3 -> 0.042666667 | G70: =gos27_C+(gosLT_C-gos27_C)*2/3 -> 0.051333333 | H70: =gosLT_C -> 0.06 | I70: =gosLT_C -> 0.06 | J70: =gosLT_C -> 0.06 | K70: =gosLT_C -> 0.06 | L70: =gosLT_C -> 0.06 | M70: =gosLT_C -> 0.06
A71: 貸款出售利得（其他毛利之一） | B71: US$M | C71: =C69*C70 -> 1193 | D71: =D69*D70 -> 1472.62 | E71: =E69*E70 -> 607.78004 | F71: =F69*F70 -> 816.85637 | G71: =G69*G70 -> 1077.6186 | H71: =H69*H70 -> 1413.2199 | I71: =I69*I70 -> 1568.3349 | J71: =J69*J70 -> 1721.2789 | ... M71: =M69*M70 -> 2126.3878
A72: 非貸款其他毛利／台 | B72: US$ | C72: =(Q!M8-fy25_gos)*1000000/C61 -> 905.06687 | D72: =((Q!K8-ytd_gos)*1000000+(D61-ytd_units)*oth_pu)/D61 -> 945.89249 | E72: =D72*(1+oth_g) -> 945.89249 | F72: =E72*(1+oth_g) -> 945.89249 | G72: =F72*(1+oth_g) -> 945.89249 | H72: =G72*(1+oth_g) -> 945.89249 | I72: =H72*(1+oth_g) -> 945.89249 | J72: =I72*(1+oth_g) -> 945.89249 | K72: =J72*(1+oth_g) -> 945.89249 | L72: =K72*(1+oth_g) -> 945.89249 | M72: =L72*(1+oth_g) -> 945.89249
A73: 非貸款其他毛利（VSC、GAP 等） | B73: US$M | C73: =C61*C72/1000000 -> 540 | D73: =D61*D72/1000000 -> 779.26 | E73: =E61*E72/1000000 -> 701.334 | F73: =F61*F72/1000000 -> 736.4007 | G73: =G61*G72/1000000 -> 791.63075 | H73: =H61*H72/1000000 -> 870.79383 | I73: =I61*I72/1000000 -> 947.42368 | J73: =J61*J72/1000000 -> 1019.4279 | ... M73: =M61*M72/1000000 -> 1186.7171
A74: 零售毛利 | B74: US$M | C74: =C61*C66/1000000 -> 1978 | D74: =D61*D66/1000000 -> 2721.4419 | E74: =E61*E66/1000000 -> 2001.9208 | F74: =F61*F66/1000000 -> 2205.8201 | G74: =G61*G66/1000000 -> 2482.8451 | H74: =H61*H66/1000000 -> 2853.8771 | I74: =I61*I66/1000000 -> 3105.0182 | J74: =J61*J66/1000000 -> 3340.9996 | ... M74: =M61*M66/1000000 -> 3889.2614
A75: 批發毛利 | B75: US$M | C75: =C61*C67/1000000 -> 481 | D75: =D61*D67/1000000 -> 620.98675 | E75: =E61*E67/1000000 -> 481.94388 | F75: =F61*F67/1000000 -> 521.09256 | G75: =G61*G67/1000000 -> 576.35484 | H75: =H61*H67/1000000 -> 651.78869 | I75: =I61*I67/1000000 -> 709.1461 | J75: =J61*J67/1000000 -> 763.0412 | ... M75: =M61*M67/1000000 -> 888.25712
A76: 其他毛利（＝其他營收） | B76: US$M | C76: =C71+C73 -> 1733 | D76: =D71+D73 -> 2251.88 | E76: =E71+E73 -> 1309.114 | F76: =F71+F73 -> 1553.2571 | G76: =G71+G73 -> 1869.2494 | H76: =H71+H73 -> 2284.0137 | I76: =I71+I73 -> 2515.7586 | J76: =J71+J73 -> 2740.7068 | ... M76: =M71+M73 -> 3313.1049
A77: 總毛利／台 | B77: US$ | C77: =(C74+C75+C76)*1000000/C61 -> 7026.0006 | D77: =(D74+D75+D76)*1000000/D61 -> 6790.5635 | E77: =(E74+E75+E76)*1000000/E61 -> 5115.6083 | F77: =(F74+F75+F76)*1000000/F61 -> 5497.7954 | G77: =(G74+G75+G76)*1000000/G61 -> 5888.8354 | H77: =(H74+H75+H76)*1000000/H61 -> 6288.9907 | I77: =(I74+I75+I76)*1000000/I61 -> 6319.6927 | J77: =(J74+J75+J76)*1000000/J61 -> 6351.0087 | ... M77: =(M74+M75+M76)*1000000/M61 -> 6448.765
A78: SG&A | B78: US$M | C78: =Q!M12 -> 2308 | D78: =ytd_sga+sga_fix+(D61-ytd_units)*sga_var/1000000 -> 2989.8516 | E78: =4*sga_fix*(1+infl)^1+E61*sga_var*(1-eff_C)^1/1000000 -> 2776.466 | F78: =4*sga_fix*(1+infl)^2+F61*sga_var*(1-eff_C)^2/1000000 -> 2901.2813 | G78: =4*sga_fix*(1+infl)^3+G61*sga_var*(1-eff_C)^3/1000000 -> 3086.4138 | H78: =4*sga_fix*(1+infl)^4+H61*sga_var*(1-eff_C)^4/1000000 -> 3343.0414 | I78: =4*sga_fix*(1+infl)^5+I61*sga_var*(1-eff_C)^5/1000000 -> 3592.839 | J78: =4*sga_fix*(1+infl)^6+J61*sga_var*(1-eff_C)^6/1000000 -> 3829.6326 | K78: =4*sga_fix*(1+infl)^7+K61*sga_var*(1-eff_C)^7/1000000 -> 4047.1226 | L78: =4*sga_fix*(1+infl)^8+L61*sga_var*(1-eff_C)^8/1000000 -> 4239.1741 | M78: =4*sga_fix*(1+infl)^9+M61*sga_var*(1-eff_C)^9/1000000 -> 4400.127
A79: SG&A／台 | B79: US$ | C79: =C78*1000000/C61 -> 3868.3228 | D79: =D78*1000000/D61 -> 3629.1843 | E79: =E78*1000000/E61 -> 3744.6328 | F79: =F78*1000000/F61 -> 3726.6398 | G79: =G78*1000000/G61 -> 3687.8502 | H79: =H78*1000000/H61 -> 3631.3507 | I79: =I78*1000000/I61 -> 3587.0323 | J79: =J78*1000000/J61 -> 3553.386 | ... M79: =M78*1000000/M61 -> 3507.1939
A80: 變動 SG&A／台 | B80: US$ | D80: =sga_var -> 2800 | E80: =sga_var*(1-eff_C)^1 -> 2800 | F80: =sga_var*(1-eff_C)^2 -> 2800 | G80: =sga_var*(1-eff_C)^3 -> 2800 | H80: =sga_var*(1-eff_C)^4 -> 2800 | I80: =sga_var*(1-eff_C)^5 -> 2800 | J80: =sga_var*(1-eff_C)^6 -> 2800 | K80: =sga_var*(1-eff_C)^7 -> 2800 | L80: =sga_var*(1-eff_C)^8 -> 2800 | M80: =sga_var*(1-eff_C)^9 -> 2800
A81: 年產能（期末，足以支應次年台數） | B81: 輛 | D81: =MAX(cap_0,E61/util) -> 1500000 | E81: =MAX(D81,MIN(F61,unit_cap)/util) -> 1500000 | F81: =MAX(E81,MIN(G61,unit_cap)/util) -> 1500000 | G81: =MAX(F81,MIN(H61,unit_cap)/util) -> 1500000 | H81: =MAX(G81,MIN(I61,unit_cap)/util) -> 1500000 | I81: =MAX(H81,MIN(J61,unit_cap)/util) -> 1500000 | J81: =MAX(I81,MIN(K61,unit_cap)/util) -> 1500000 | K81: =MAX(J81,MIN(L61,unit_cap)/util) -> 1500000 | L81: =MAX(K81,MIN(M61,unit_cap)/util) -> 1500000 | M81: =MAX(L81,MIN(M61*(1+M60),unit_cap)/util) -> 1535040.6
A82: 成長性資本支出（新增產能 × 每台成本） | B82: US$M | D82: =0 -> 0 | E82: =(E81-D81)*capcost/1000000 -> 0 | F82: =(F81-E81)*capcost/1000000 -> 0 | G82: =(G81-F81)*capcost/1000000 -> 0 | H82: =(H81-G81)*capcost/1000000 -> 0 | I82: =(I81-H81)*capcost/1000000 -> 0 | J82: =(J81-I81)*capcost/1000000 -> 0 | K82: =(K81-J81)*capcost/1000000 -> 0 | L82: =(L81-K81)*capcost/1000000 -> 0 | M82: =(M81-L81)*capcost/1000000 -> 21.024331
A85: 三情境假設對照：輸入（藍字在 In 頁）與推導量
A86: 項目 | B86: 單位 | C86: 情境 A（樂觀） | D86: 情境 B（基準） | E86: 情境 C（信用壓力） | F86: 標記
A87: 2027 年零售台數年增 | B87: % | C87: =g27_A -> 0.32 | D87: =g27_B -> 0.25 | E87: =g27_C -> -0.1 | F87: Assumed
A88: 2028 年零售台數年增 | B88: % | C88: =g28_A -> 0.28 | D88: =g28_B -> 0.2 | E88: =g28_C -> 0.05 | F88: Assumed
A89: 2030 年零售台數年增 | B89: % | C89: =g30_A -> 0.2 | D89: =g30_B -> 0.13 | E89: =g30_C -> 0.1 | F89: Assumed
A90: 2035 年零售台數年增 | B90: % | C90: =g35_A -> 0.08 | D90: =g35_B -> 0.05 | E90: =g35_C -> 0.04 | F90: Assumed
A91: 2027 年零售毛利／台 | B91: US$ | C91: =gpr27_A -> 3600 | D91: =gpr27_B -> 3450 | E91: =gpr27_C -> 2700 | F91: Assumed
A92: 2030 年起零售毛利／台 | B92: US$ | C92: =gprLT_A -> 3700 | D92: =gprLT_B -> 3350 | E92: =gprLT_C -> 3100 | F92: Assumed
A93: 2027 年批發毛利／零售台 | B93: US$ | C93: =gpw_h2 -> 708 | D93: =gpw_h2 -> 708 | E93: =gpw27_C -> 650 | F93: Assumed
A94: 2027 年貸款出售利得率 | B94: % | C94: =gos27_A -> 0.08 | D94: =gos27_B -> 0.072 | E94: =gos27_C -> 0.034 | F94: Assumed；C 為 Derived
A95: 2030 年起貸款出售利得率 | B95: % | C95: =gosLT_A -> 0.08 | D95: =gosLT_B -> 0.07 | E95: =gosLT_C -> 0.06 | F95: Assumed
A96: 變動 SG&A／台每年下降 | B96: % | C96: =eff_A -> 0.03 | D96: =eff_B -> 0.015 | E96: =eff_C -> 0 | F96: Assumed
A97: 2027 年存貨天數 | B97: 天 | C97: =inv_d -> 60 | D97: =inv_d -> 60 | E97: =inv_d_C -> 70 | F97: Assumed
A98: 推導量
A99: 2027 年零售台數 | B99: 輛 | C99: =E7 -> 1087463.1 | D99: =E34 -> 1029794.6 | E99: =E61 -> 741452.13 | F99: Derived
A100: 2030 年零售台數 | B100: 輛 | C100: =H7 -> 2071225.8 | D100: =H34 -> 1626807.8 | E100: =H61 -> 920605.5 | F100: Derived
A101: 2035 年零售台數 | B101: 輛 | C101: =M7 -> 3000000 | D101: =M34 -> 2409891.7 | E101: =M61 -> 1254600.5 | F101: Derived
A102: 2027 年總毛利／台 | B102: US$ | C102: =E23 -> 7182.6356 | D102: =E50 -> 6839.7613 | E102: =E77 -> 5115.6083 | F102: Derived
A103: 2027 年貸款出售利得 | B103: US$M | C103: =E17 -> 2097.437 | D103: =E44 -> 1787.5884 | E103: =E71 -> 607.78004 | F103: Derived
A104: 2027 年 SG&A／台 | B104: US$ | C104: =E25 -> 3360.0678 | D104: =E52 -> 3438.1356 | E104: =E79 -> 3744.6328 | F104: Derived
A105: 2027 年調整後 EBITDA | B105: US$M | C105: =PL!E33 -> 4515.9715 | D105: =PL!E62 -> 3862.0458 | E105: =PL!E91 -> 1375.5827 | F105: Derived
A106: 2030 年調整後 EBITDA | B106: US$M | C106: =PL!H33 -> 9860.7406 | D106: =PL!H62 -> 6411.5754 | E106: =PL!H91 -> 2840.9508 | F106: Derived
A107: 2030 年調整後 EBITDA 率 | B107: % | C107: =PL!H34 -> 0.12030996 | D107: =PL!H63 -> 0.10024555 | E107: =PL!H92 -> 0.07900638 | F107: Derived

Sheet PL
A1: PL — 損益表。Carvana 只有一個應報導部門（10-Q 附註 2：CODM 看合併淨利）；營收列採公司固定揭露的三條營收線，「其他銷售與營收」下拆命題子列（貸款出售利得／非貸款）
A2: FY2025A 為實績（含第四季釋放評價備抵的稅務利益 2,785 與 TRA 重估等其他費用 2,250）；FY2026E＝上半年實績＋下半年模型
A3: 項目 | B3: 單位 | C3: FY2025A | D3: FY2026E | E3: FY2027E | F3: FY2028E | G3: FY2029E | H3: FY2030E | I3: FY2031E | J3: FY2032E | K3: FY2033E | L3: FY2034E | M3: FY2035E
A4: 核對列（三情境合計絕對差，應為 0）
A5: 核對：營收線合計 − 合併營收 | C5: =ABS(C9+C10+C11-C14)+ABS(C38+C39+C40-C43)+ABS(C67+C68+C69-C72) -> 0 | D5: =ABS(D9+D10+D11-D14)+ABS(D38+D39+D40-D43)+ABS(D67+D68+D69-D72) -> 0 | E5: =ABS(E9+E10+E11-E14)+ABS(E38+E39+E40-E43)+ABS(E67+E68+E69-E72) -> 0 | F5: =ABS(F9+F10+F11-F14)+ABS(F38+F39+F40-F43)+ABS(F67+F68+F69-F72) -> 0 | G5: =ABS(G9+G10+G11-G14)+ABS(G38+G39+G40-G43)+ABS(G67+G68+G69-G72) -> 0 | H5: =ABS(H9+H10+H11-H14)+ABS(H38+H39+H40-H43)+ABS(H67+H68+H69-H72) -> 0 | I5: =ABS(I9+I10+I11-I14)+ABS(I38+I39+I40-I43)+ABS(I67+I68+I69-I72) -> 0 | J5: =ABS(J9+J10+J11-J14)+ABS(J38+J39+J40-J43)+ABS(J67+J68+J69-J72) -> 0 | ... M5: =ABS(M9+M10+M11-M14)+ABS(M38+M39+M40-M43)+ABS(M67+M68+M69-M72) -> 0
A6: 核對：其他營收子列合計 − 其他營收 | C6: =ABS(C12+C13-C11)+ABS(C41+C42-C40)+ABS(C70+C71-C69) -> 0 | D6: =ABS(D12+D13-D11)+ABS(D41+D42-D40)+ABS(D70+D71-D69) -> 0 | E6: =ABS(E12+E13-E11)+ABS(E41+E42-E40)+ABS(E70+E71-E69) -> 0 | F6: =ABS(F12+F13-F11)+ABS(F41+F42-F40)+ABS(F70+F71-F69) -> 0 | G6: =ABS(G12+G13-G11)+ABS(G41+G42-G40)+ABS(G70+G71-G69) -> 0 | H6: =ABS(H12+H13-H11)+ABS(H41+H42-H40)+ABS(H70+H71-H69) -> 0 | I6: =ABS(I12+I13-I11)+ABS(I41+I42-I40)+ABS(I70+I71-I69) -> 0 | J6: =ABS(J12+J13-J11)+ABS(J41+J42-J40)+ABS(J70+J71-J69) -> 0 | ... M6: =ABS(M12+M13-M11)+ABS(M41+M42-M40)+ABS(M70+M71-M69) -> 0
A8: 情境 A（樂觀：沿公司 300 萬台路徑、利得率維持）
A9: 零售車輛銷售 | B9: US$M | C9: =Thesis!C9 -> 14537 | D9: =Thesis!D9 -> 22745.831 | E9: =Thesis!E9 -> 30624.987 | F9: =Thesis!F9 -> 39983.983 | G9: =Thesis!G9 -> 50571.742 | H9: =Thesis!H9 -> 61899.812 | I9: =Thesis!I9 -> 74250.063 | J9: =Thesis!J9 -> 87246.794 | ... M9: =Thesis!M9 -> 98988.332
A10: 批發銷售與營收 | B10: US$M | C10: =Thesis!C11 -> 4052 | D10: =Thesis!D11 -> 5094.0459 | E10: =Thesis!E11 -> 6858.6234 | F10: =Thesis!F11 -> 8954.6187 | G10: =Thesis!G11 -> 11325.802 | H10: =Thesis!H11 -> 13862.781 | I10: =Thesis!I11 -> 16628.683 | J10: =Thesis!J11 -> 19539.368 | ... M10: =Thesis!M11 -> 22168.946
A11: 其他銷售與營收 | B11: US$M | C11: =Q!M8 -> 1733 | D11: =Thesis!D22 -> 2251.88 | E11: =Thesis!E22 -> 3126.0602 | F11: =Thesis!F22 -> 4055.0514 | G11: =Thesis!G22 -> 5096.1764 | H11: =Thesis!H22 -> 6198.5368 | I11: =Thesis!I22 -> 7389.1895 | J11: =Thesis!J22 -> 8629.5098 | K11: =Thesis!K22 -> 9353.9115 | ... M11: =Thesis!M22 -> 9617.1673
A12: 其中：貸款出售利得（命題子列） | B12: US$M | C12: =Thesis!C17 -> 1193 | D12: =Thesis!D17 -> 1472.62 | E12: =Thesis!E17 -> 2097.437 | F12: =Thesis!F17 -> 2738.4137 | G12: =Thesis!G17 -> 3463.5457 | H12: =Thesis!H17 -> 4239.3799 | I12: =Thesis!I17 -> 5085.221 | J12: =Thesis!J17 -> 5975.3381 | ... M12: =Thesis!M17 -> 6779.4898
A13: 其中：VSC、GAP 等非貸款（命題子列） | B13: US$M | C13: =C11-C12 -> 540 | D13: =D11-D12 -> 779.26 | E13: =E11-E12 -> 1028.6232 | F13: =F11-F12 -> 1316.6377 | G13: =G11-G12 -> 1632.6307 | H13: =H11-H12 -> 1959.1569 | I13: =I11-I12 -> 2303.9685 | J13: =J11-J12 -> 2654.1717 | ... M13: =M11-M12 -> 2837.6775
A14: 合併營收 | B14: US$M | C14: =Q!M9 -> 20322 | D14: =D9+D10+D11 -> 30091.757 | E14: =E9+E10+E11 -> 40609.671 | F14: =F9+F10+F11 -> 52993.654 | G14: =G9+G10+G11 -> 66993.72 | H14: =H9+H10+H11 -> 81961.131 | I14: =I9+I10+I11 -> 98267.936 | J14: =J9+J10+J11 -> 115415.67 | K14: =K9+K10+K11 -> 125806.5 | ... M14: =M9+M10+M11 -> 130774.45
A15: 營收年增 | B15: % | D15: =D14/C14-1 -> 0.48074782 | E15: =E14/D14-1 -> 0.34952806 | F15: =F14/E14-1 -> 0.30495156 | G15: =G14/F14-1 -> 0.26418384 | H15: =H14/G14-1 -> 0.22341512 | I15: =I14/H14-1 -> 0.19895779 | J15: =J14/I14-1 -> 0.17449981 | K15: =K14/J14-1 -> 0.090029652 | ... M15: =M14/L14-1 -> 0.019557532
A16: 零售毛利 | B16: US$M | C16: =Thesis!C20 -> 1978 | D16: =Thesis!D20 -> 2721.4419 | E16: =Thesis!E20 -> 3914.8672 | F16: =Thesis!F20 -> 5057.4285 | G16: =Thesis!G20 -> 6328.7454 | H16: =Thesis!H20 -> 7663.5353 | I16: =Thesis!I20 -> 9012.3175 | J16: =Thesis!J20 -> 10382.19 | ... M16: =Thesis!M20 -> 11100
A17: 批發毛利 | B17: US$M | C17: =Thesis!C21 -> 481 | D17: =Thesis!D21 -> 620.98675 | E17: =Thesis!E21 -> 769.92389 | F17: =Thesis!F21 -> 985.50258 | G17: =Thesis!G21 -> 1222.0232 | H17: =Thesis!H21 -> 1466.4278 | I17: =Thesis!I21 -> 1724.5191 | J17: =Thesis!J21 -> 1986.6461 | ... M17: =Thesis!M21 -> 2124
A18: 其他毛利 | B18: US$M | C18: =C11 -> 1733 | D18: =D11 -> 2251.88 | E18: =E11 -> 3126.0602 | F18: =F11 -> 4055.0514 | G18: =G11 -> 5096.1764 | H18: =H11 -> 6198.5368 | I18: =I11 -> 7389.1895 | J18: =J11 -> 8629.5098 | ... M18: =M11 -> 9617.1673
A19: 毛利合計 | B19: US$M | C19: =C16+C17+C18 -> 4192 | D19: =D16+D17+D18 -> 5594.3086 | E19: =E16+E17+E18 -> 7810.8513 | F19: =F16+F17+F18 -> 10097.983 | G19: =G16+G17+G18 -> 12646.945 | H19: =H16+H17+H18 -> 15328.5 | I19: =I16+I17+I18 -> 18126.026 | J19: =J16+J17+J18 -> 20998.346 | ... M19: =M16+M17+M18 -> 22841.167
A20: SG&A | B20: US$M | C20: =Thesis!C24 -> 2308 | D20: =Thesis!D24 -> 2989.8516 | E20: =Thesis!E24 -> 3653.9498 | F20: =Thesis!F24 -> 4388.5395 | G20: =Thesis!G24 -> 5153.8753 | H20: =Thesis!H24 -> 5899.5416 | I20: =Thesis!I24 -> 6644.9859 | J20: =Thesis!J24 -> 7356.4436 | ... M20: =Thesis!M24 -> 7273.1867
A21: 營業利益 | B21: US$M | C21: =fy25_oi -> 1881 | D21: =D19-D20 -> 2604.4571 | E21: =E19-E20 -> 4156.9015 | F21: =F19-F20 -> 5709.443 | G21: =G19-G20 -> 7493.0697 | H21: =H19-H20 -> 9428.9584 | I21: =I19-I20 -> 11481.04 | J21: =J19-J20 -> 13641.902 | K21: =K19-K20 -> 14954.541 | ... M21: =M19-M20 -> 15567.981
A22: 營業利益率 | B22: % | C22: =C21/C14 -> 0.092559787 | D22: =D21/D14 -> 0.086550514 | E22: =E21/E14 -> 0.10236235 | F22: =F21/F14 -> 0.10773824 | G22: =G21/G14 -> 0.11184734 | H22: =H21/H14 -> 0.11504183 | I22: =I21/I14 -> 0.11683404 | J22: =J21/J14 -> 0.118198 | ... M22: =M21/M14 -> 0.11904452
A23: 利息費用（淨；CF 頁債務表） | B23: US$M | C23: =fy25_int -> 505 | D23: =CF!D47 -> 390.40787 | E23: =CF!E47 -> 366.15625 | F23: =CF!F47 -> 344.03167 | G23: =CF!G47 -> 353.52801 | H23: =CF!H47 -> 401.82942 | I23: =CF!I47 -> 454.36382 | J23: =CF!J47 -> 512.22067 | K23: =CF!K47 -> 554.93371 | ... M23: =CF!M47 -> 484.86877
A24: 其他費用（收益） | B24: US$M | C24: =Q!M21 -> 2266 | D24: =ytd_oth_exp -> 105 | E24: =0 -> 0 | F24: =0 -> 0 | G24: =0 -> 0 | H24: =0 -> 0 | I24: =0 -> 0 | J24: =0 -> 0 | K24: =0 -> 0 | L24: =0 -> 0 | M24: =0 -> 0
A25: 稅前淨利 | B25: US$M | C25: =C21-C23-C24 -> -890 | D25: =D21-D23-D24 -> 2109.0492 | E25: =E21-E23-E24 -> 3790.7452 | F25: =F21-F23-F24 -> 5365.4114 | G25: =G21-G23-G24 -> 7139.5417 | H25: =H21-H23-H24 -> 9027.129 | I25: =I21-I23-I24 -> 11026.676 | J25: =J21-J23-J24 -> 13129.681 | ... M25: =M21-M23-M24 -> 15083.112
A26: 所得稅 | B26: US$M | C26: =fy25_tax -> -2785 | D26: =ytd_tax+(D25-(ytd_oi-ytd_int-ytd_oth_exp))*etr_26 -> 229.41947 | E26: =E25*etr_27 -> 454.88943 | F26: =F25*(etr_27+(etr_30-etr_27)/3) -> 751.15759 | G26: =G25*(etr_27+(etr_30-etr_27)*2/3) -> 1142.3267 | H26: =H25*etr_30 -> 1624.8832 | I26: =I25*etr_30 -> 1984.8018 | J26: =J25*etr_30 -> 2363.3427 | K26: =K25*etr_30 -> 2591.9294 | L26: =L25*etr_30 -> 2661.7372 | M26: =M25*etr_30 -> 2714.9601
A27: 淨利（合併，含非控制權益） | B27: US$M | C27: =C25-C26 -> 1895 | D27: =D25-D26 -> 1879.6297 | E27: =E25-E26 -> 3335.8558 | F27: =F25-F26 -> 4614.2538 | G27: =G25-G26 -> 5997.2151 | H27: =H25-H26 -> 7402.2458 | I27: =I25-I26 -> 9041.8747 | J27: =J25-J26 -> 10766.339 | ... M27: =M25-M26 -> 12368.152
A28: 淨利率 | B28: % | C28: =C27/C14 -> 0.093248696 | D28: =D27/D14 -> 0.062463275 | E28: =E27/E14 -> 0.08214437 | F28: =F27/F14 -> 0.087071818 | G28: =G27/G14 -> 0.089519063 | H28: =H27/H14 -> 0.090314101 | I28: =I27/I14 -> 0.092012462 | J28: =J27/J14 -> 0.093283162 | ... M28: =M27/M14 -> 0.094576213
A29: 每股盈餘（完全轉換股數） | B29: US$ | D29: =D27/sh_fx -> 1.667817 | E29: =E27/sh_fx -> 2.9599431 | F29: =F27/sh_fx -> 4.0942802 | G29: =G27/sh_fx -> 5.3213976 | H29: =H27/sh_fx -> 6.5680974 | I29: =I27/sh_fx -> 8.0229589 | J29: =J27/sh_fx -> 9.5530956 | K29: =K27/sh_fx -> 10.477088 | ... M29: =M27/sh_fx -> 10.974403
A30: 折舊攤銷 | B30: US$M | C30: =fy25_da -> 275 | D30: =ytd_da+da_q4 -> 266 | E30: =(ytd_da+da_q4)*(1+infl) -> 273.98 | F30: =(ytd_da+da_q4)*(1+infl)^2+SUM(Thesis!E28:E28)/life -> 287.70306 | G30: =(ytd_da+da_q4)*(1+infl)^3+SUM(Thesis!E28:F28)/life -> 311.88992 | H30: =(ytd_da+da_q4)*(1+infl)^4+SUM(Thesis!E28:G28)/life -> 336.85479 | I30: =(ytd_da+da_q4)*(1+infl)^5+SUM(Thesis!E28:H28)/life -> 362.99097 | J30: =(ytd_da+da_q4)*(1+infl)^6+SUM(Thesis!E28:I28)/life -> 389.66484 | K30: =(ytd_da+da_q4)*(1+infl)^7+SUM(Thesis!E28:J28)/life -> 408.32292 | L30: =(ytd_da+da_q4)*(1+infl)^8+SUM(Thesis!E28:K28)/life -> 418.13731 | M30: =(ytd_da+da_q4)*(1+infl)^9+SUM(Thesis!E28:L28)/life -> 428.24614
A31: 股份基礎給付 | B31: US$M | C31: =fy25_sbc -> 99 | D31: =ytd_sbc+sbc_q4 -> 103 | E31: =(ytd_sbc+sbc_q4)*(1+infl)^1 -> 106.09 | F31: =(ytd_sbc+sbc_q4)*(1+infl)^2 -> 109.2727 | G31: =(ytd_sbc+sbc_q4)*(1+infl)^3 -> 112.55088 | H31: =(ytd_sbc+sbc_q4)*(1+infl)^4 -> 115.92741 | I31: =(ytd_sbc+sbc_q4)*(1+infl)^5 -> 119.40523 | J31: =(ytd_sbc+sbc_q4)*(1+infl)^6 -> 122.98739 | K31: =(ytd_sbc+sbc_q4)*(1+infl)^7 -> 126.67701 | L31: =(ytd_sbc+sbc_q4)*(1+infl)^8 -> 130.47732 | M31: =(ytd_sbc+sbc_q4)*(1+infl)^9 -> 134.39164
A32: 權證營收（扣除） | B32: US$M | C32: =fy25_warrant -> 21 | D32: =ytd_warrant+warr/4 -> 21.25 | E32: =warr -> 21 | F32: =warr -> 21 | G32: =warr -> 21 | H32: =warr -> 21 | I32: =warr -> 21 | J32: =warr -> 21 | K32: =warr -> 21 | L32: =warr -> 21 | M32: =warr -> 21
A33: 調整後 EBITDA | B33: US$M | C33: =Q!M19 -> 2237 | D33: =D21+D30+D31-D32 -> 2952.2071 | E33: =E21+E30+E31-E32 -> 4515.9715 | F33: =F21+F30+F31-F32 -> 6085.4188 | G33: =G21+G30+G31-G32 -> 7896.5105 | H33: =H21+H30+H31-H32 -> 9860.7406 | I33: =I21+I30+I31-I32 -> 11942.436 | J33: =J21+J30+J31-J32 -> 14133.554 | K33: =K21+K30+K31-K32 -> 15468.541 | ... M33: =M21+M30+M31-M32 -> 16109.618
A34: 調整後 EBITDA 率 | B34: % | C34: =C33/C14 -> 0.11007775 | D34: =D33/D14 -> 0.098106835 | E34: =E33/E14 -> 0.11120434 | F34: =F33/F14 -> 0.11483297 | G34: =G33/G14 -> 0.11786941 | H34: =H33/H14 -> 0.12030996 | I34: =I33/I14 -> 0.12152933 | J34: =J33/J14 -> 0.12245784 | ... M34: =M33/M14 -> 0.12318629
A35: 貸款出售利得 ÷ 調整後 EBITDA | B35: % | C35: =C12/C33 -> 0.53330353 | D35: =D12/D33 -> 0.49882003 | E35: =E12/E33 -> 0.46444868 | F35: =F12/F33 -> 0.44999594 | G35: =G12/G33 -> 0.43861725 | H35: =H12/H33 -> 0.4299251 | I35: =I12/I33 -> 0.42581102 | J35: =J12/J33 -> 0.42277675 | ... M35: =M12/M33 -> 0.42083491
A37: 情境 B（基準：成長放緩、利得率小降）
A38: 零售車輛銷售 | B38: US$M | C38: =Thesis!C36 -> 14537 | D38: =Thesis!D36 -> 22745.831 | E38: =Thesis!E36 -> 29000.935 | F38: =Thesis!F36 -> 35497.144 | G38: =Thesis!G36 -> 42181.257 | H38: =Thesis!H36 -> 48618.116 | I38: =Thesis!I36 -> 55243.793 | J38: =Thesis!J36 -> 61870.839 | ... M38: =Thesis!M36 -> 79517.054
A39: 批發銷售與營收 | B39: US$M | C39: =Thesis!C38 -> 4052 | D39: =Thesis!D38 -> 5094.0459 | E39: =Thesis!E38 -> 6494.9085 | F39: =Thesis!F38 -> 7949.768 | G39: =Thesis!G38 -> 9446.7093 | H39: =Thesis!H38 -> 10888.277 | I39: =Thesis!I38 -> 12372.132 | J39: =Thesis!J38 -> 13856.292 | ... M39: =Thesis!M38 -> 17808.253
A40: 其他銷售與營收 | B40: US$M | C40: =Q!M8 -> 1733 | D40: =Thesis!D49 -> 2251.88 | E40: =Thesis!E49 -> 2761.6634 | F40: =Thesis!F49 -> 3336.6388 | G40: =Thesis!G49 -> 3913.6186 | H40: =Thesis!H49 -> 4452.3132 | I40: =Thesis!I49 -> 5024.7903 | J40: =Thesis!J49 -> 5589.9202 | K40: =Thesis!K49 -> 6128.5287 | ... M40: =Thesis!M49 -> 7044.7008
A41: 其中：貸款出售利得（命題子列） | B41: US$M | C41: =Thesis!C44 -> 1193 | D41: =Thesis!D44 -> 1472.62 | E41: =Thesis!E44 -> 1787.5884 | F41: =Thesis!F44 -> 2167.7488 | G41: =Thesis!G44 -> 2551.8617 | H41: =Thesis!H44 -> 2913.528 | I41: =Thesis!I44 -> 3310.5835 | J41: =Thesis!J44 -> 3707.7212 | ... M41: =Thesis!M44 -> 4765.2023
A42: 其中：VSC、GAP 等非貸款（命題子列） | B42: US$M | C42: =C40-C41 -> 540 | D42: =D40-D41 -> 779.26 | E42: =E40-E41 -> 974.075 | F42: =F40-F41 -> 1168.89 | G42: =G40-G41 -> 1361.7568 | H42: =H40-H41 -> 1538.7852 | I42: =I40-I41 -> 1714.2068 | J42: =J40-J41 -> 1882.199 | ... M42: =M40-M41 -> 2279.4985
A43: 合併營收 | B43: US$M | C43: =Q!M9 -> 20322 | D43: =D38+D39+D40 -> 30091.757 | E43: =E38+E39+E40 -> 38257.507 | F43: =F38+F39+F40 -> 46783.551 | G43: =G38+G39+G40 -> 55541.585 | H43: =H38+H39+H40 -> 63958.707 | I43: =I38+I39+I40 -> 72640.715 | J43: =J38+J39+J40 -> 81317.051 | K43: =K38+K39+K40 -> 89704.02 | ... M43: =M38+M39+M40 -> 104370.01
A44: 營收年增 | B44: % | D44: =D43/C43-1 -> 0.48074782 | E44: =E43/D43-1 -> 0.27136167 | F44: =F43/E43-1 -> 0.22285938 | G44: =G43/F43-1 -> 0.18720326 | H44: =H43/G43-1 -> 0.15154631 | I44: =I43/H43-1 -> 0.13574396 | J44: =J43/I43-1 -> 0.11944178 | K44: =K43/J43-1 -> 0.10313911 | ... M44: =M43/L43-1 -> 0.07053238
A45: 零售毛利 | B45: US$M | C45: =Thesis!C47 -> 1978 | D45: =Thesis!D47 -> 2721.4419 | E45: =Thesis!E47 -> 3552.7915 | F45: =Thesis!F47 -> 4222.158 | G45: =Thesis!G47 -> 4870.8256 | H45: =Thesis!H47 -> 5449.806 | I45: =Thesis!I47 -> 6071.0839 | J45: =Thesis!J47 -> 6666.0501 | ... M45: =Thesis!M47 -> 8073.1373
A46: 批發毛利 | B46: US$M | C46: =Thesis!C48 -> 481 | D46: =Thesis!D48 -> 620.98675 | E46: =Thesis!E48 -> 729.09459 | F46: =Thesis!F48 -> 874.91351 | G46: =Thesis!G48 -> 1019.2742 | H46: =Thesis!H48 -> 1151.7799 | I46: =Thesis!I48 -> 1283.0828 | J46: =Thesis!J48 -> 1408.8249 | ... M46: =Thesis!M48 -> 1706.2033
A47: 其他毛利 | B47: US$M | C47: =C40 -> 1733 | D47: =D40 -> 2251.88 | E47: =E40 -> 2761.6634 | F47: =F40 -> 3336.6388 | G47: =G40 -> 3913.6186 | H47: =H40 -> 4452.3132 | I47: =I40 -> 5024.7903 | J47: =J40 -> 5589.9202 | ... M47: =M40 -> 7044.7008
A48: 毛利合計 | B48: US$M | C48: =C45+C46+C47 -> 4192 | D48: =D45+D46+D47 -> 5594.3086 | E48: =E45+E46+E47 -> 7043.5494 | F48: =F45+F46+F47 -> 8433.7103 | G48: =G45+G46+G47 -> 9803.7184 | H48: =H45+H46+H47 -> 11053.899 | I48: =I45+I46+I47 -> 12378.957 | J48: =J45+J46+J47 -> 13664.795 | ... M48: =M45+M46+M47 -> 16824.041
A49: SG&A | B49: US$M | C49: =Thesis!C51 -> 2308 | D49: =Thesis!D51 -> 2989.8516 | E49: =Thesis!E51 -> 3540.5736 | F49: =Thesis!F51 -> 4078.4972 | G49: =Thesis!G51 -> 4595.3935 | H49: =Thesis!H51 -> 5053.1921 | I49: =Thesis!I51 -> 5493.317 | J49: =Thesis!J51 -> 5900.5657 | ... M49: =Thesis!M51 -> 6776.7893
A50: 營業利益 | B50: US$M | C50: =fy25_oi -> 1881 | D50: =D48-D49 -> 2604.4571 | E50: =E48-E49 -> 3502.9758 | F50: =F48-F49 -> 4355.2131 | G50: =G48-G49 -> 5208.3249 | H50: =H48-H49 -> 6000.707 | I50: =I48-I49 -> 6885.64 | J50: =J48-J49 -> 7764.2295 | K50: =K48-K49 -> 8605.9412 | ... M50: =M48-M49 -> 10047.252
A51: 營業利益率 | B51: % | C51: =C50/C43 -> 0.092559787 | D51: =D50/D43 -> 0.086550514 | E51: =E50/E43 -> 0.091563098 | F51: =F50/F43 -> 0.093092829 | G51: =G50/G43 -> 0.09377343 | H51: =H50/H43 -> 0.093821581 | I51: =I50/I43 -> 0.094790366 | J51: =J50/J43 -> 0.095480952 | ... M51: =M50/M43 -> 0.096265702
A52: 利息費用（淨；CF 頁債務表） | B52: US$M | C52: =fy25_int -> 505 | D52: =CF!D85 -> 390.40787 | E52: =CF!E85 -> 361.03247 | F52: =CF!F85 -> 327.55262 | G52: =CF!G85 -> 320.61295 | H52: =CF!H85 -> 347.86122 | I52: =CF!I85 -> 375.28742 | J52: =CF!J85 -> 404.77647 | K52: =CF!K85 -> 433.59394 | ... M52: =CF!M85 -> 390.5672
A53: 其他費用（收益） | B53: US$M | C53: =Q!M21 -> 2266 | D53: =ytd_oth_exp -> 105 | E53: =0 -> 0 | F53: =0 -> 0 | G53: =0 -> 0 | H53: =0 -> 0 | I53: =0 -> 0 | J53: =0 -> 0 | K53: =0 -> 0 | L53: =0 -> 0 | M53: =0 -> 0
A54: 稅前淨利 | B54: US$M | C54: =C50-C52-C53 -> -890 | D54: =D50-D52-D53 -> 2109.0492 | E54: =E50-E52-E53 -> 3141.9434 | F54: =F50-F52-F53 -> 4027.6605 | G54: =G50-G52-G53 -> 4887.712 | H54: =H50-H52-H53 -> 5652.8458 | I54: =I50-I52-I53 -> 6510.3526 | J54: =J50-J52-J53 -> 7359.453 | ... M54: =M50-M52-M53 -> 9656.6849
A55: 所得稅 | B55: US$M | C55: =fy25_tax -> -2785 | D55: =ytd_tax+(D54-(ytd_oi-ytd_int-ytd_oth_exp))*etr_26 -> 229.41947 | E55: =E54*etr_27 -> 377.0332 | F55: =F54*(etr_27+(etr_30-etr_27)/3) -> 563.87247 | G55: =G54*(etr_27+(etr_30-etr_27)*2/3) -> 782.03391 | H55: =H54*etr_30 -> 1017.5122 | I55: =I54*etr_30 -> 1171.8635 | J55: =J54*etr_30 -> 1324.7015 | K55: =K54*etr_30 -> 1471.0225 | L55: =L54*etr_30 -> 1622.2899 | M55: =M54*etr_30 -> 1738.2033
A56: 淨利（合併，含非控制權益） | B56: US$M | C56: =C54-C55 -> 1895 | D56: =D54-D55 -> 1879.6297 | E56: =E54-E55 -> 2764.9102 | F56: =F54-F55 -> 3463.788 | G56: =G54-G55 -> 4105.678 | H56: =H54-H55 -> 4635.3335 | I56: =I54-I55 -> 5338.4891 | J56: =J54-J55 -> 6034.7515 | ... M56: =M54-M55 -> 7918.4816
A57: 淨利率 | B57: % | C57: =C56/C43 -> 0.093248696 | D57: =D56/D43 -> 0.062463275 | E57: =E56/E43 -> 0.072271049 | F57: =F56/F43 -> 0.074038587 | G57: =G56/G43 -> 0.073920794 | H57: =H56/H43 -> 0.072473847 | I57: =I56/I43 -> 0.073491692 | J57: =J56/J43 -> 0.07421262 | ... M57: =M56/M43 -> 0.075869321
A58: 每股盈餘（完全轉換股數） | B58: US$ | D58: =D56/sh_fx -> 1.667817 | E58: =E56/sh_fx -> 2.4533364 | F58: =F56/sh_fx -> 3.0734588 | G58: =G56/sh_fx -> 3.6430151 | H58: =H56/sh_fx -> 4.1129845 | I58: =I56/sh_fx -> 4.7369025 | J58: =J56/sh_fx -> 5.354704 | K58: =K56/sh_fx -> 5.9461622 | ... M58: =M56/sh_fx -> 7.0261594
A59: 折舊攤銷 | B59: US$M | C59: =fy25_da -> 275 | D59: =ytd_da+da_q4 -> 266 | E59: =(ytd_da+da_q4)*(1+infl) -> 273.98 | F59: =(ytd_da+da_q4)*(1+infl)^2+SUM(Thesis!E55:E55)/life -> 282.1994 | G59: =(ytd_da+da_q4)*(1+infl)^3+SUM(Thesis!E55:F55)/life -> 298.41375 | H59: =(ytd_da+da_q4)*(1+infl)^4+SUM(Thesis!E55:G55)/life -> 315.941 | I59: =(ytd_da+da_q4)*(1+infl)^5+SUM(Thesis!E55:H55)/life -> 333.64991 | J59: =(ytd_da+da_q4)*(1+infl)^6+SUM(Thesis!E55:I55)/life -> 351.25865 | K59: =(ytd_da+da_q4)*(1+infl)^7+SUM(Thesis!E55:J55)/life -> 368.46573 | L59: =(ytd_da+da_q4)*(1+infl)^8+SUM(Thesis!E55:K55)/life -> 384.96719 | M59: =(ytd_da+da_q4)*(1+infl)^9+SUM(Thesis!E55:L55)/life -> 400.47634
A60: 股份基礎給付 | B60: US$M | C60: =fy25_sbc -> 99 | D60: =ytd_sbc+sbc_q4 -> 103 | E60: =(ytd_sbc+sbc_q4)*(1+infl)^1 -> 106.09 | F60: =(ytd_sbc+sbc_q4)*(1+infl)^2 -> 109.2727 | G60: =(ytd_sbc+sbc_q4)*(1+infl)^3 -> 112.55088 | H60: =(ytd_sbc+sbc_q4)*(1+infl)^4 -> 115.92741 | I60: =(ytd_sbc+sbc_q4)*(1+infl)^5 -> 119.40523 | J60: =(ytd_sbc+sbc_q4)*(1+infl)^6 -> 122.98739 | K60: =(ytd_sbc+sbc_q4)*(1+infl)^7 -> 126.67701 | L60: =(ytd_sbc+sbc_q4)*(1+infl)^8 -> 130.47732 | M60: =(ytd_sbc+sbc_q4)*(1+infl)^9 -> 134.39164
A61: 權證營收（扣除） | B61: US$M | C61: =fy25_warrant -> 21 | D61: =ytd_warrant+warr/4 -> 21.25 | E61: =warr -> 21 | F61: =warr -> 21 | G61: =warr -> 21 | H61: =warr -> 21 | I61: =warr -> 21 | J61: =warr -> 21 | K61: =warr -> 21 | L61: =warr -> 21 | M61: =warr -> 21
A62: 調整後 EBITDA | B62: US$M | C62: =Q!M19 -> 2237 | D62: =D50+D59+D60-D61 -> 2952.2071 | E62: =E50+E59+E60-E61 -> 3862.0458 | F62: =F50+F59+F60-F61 -> 4725.6852 | G62: =G50+G59+G60-G61 -> 5598.2895 | H62: =H50+H59+H60-H61 -> 6411.5754 | I62: =I50+I59+I60-I61 -> 7317.6951 | J62: =J50+J59+J60-J61 -> 8217.4755 | K62: =K50+K59+K60-K61 -> 9080.0839 | ... M62: =M50+M59+M60-M61 -> 10561.12
A63: 調整後 EBITDA 率 | B63: % | C63: =C62/C43 -> 0.11007775 | D63: =D62/D43 -> 0.098106835 | E63: =E62/E43 -> 0.10094871 | F63: =F62/F43 -> 0.10101168 | G63: =G62/G43 -> 0.10079456 | H63: =H62/H43 -> 0.10024555 | I63: =I62/I43 -> 0.1007382 | J63: =J62/J43 -> 0.10105476 | ... M63: =M62/M43 -> 0.10118922
A64: 貸款出售利得 ÷ 調整後 EBITDA | B64: % | C64: =C41/C62 -> 0.53330353 | D64: =D41/D62 -> 0.49882003 | E64: =E41/E62 -> 0.46286047 | F64: =F41/F62 -> 0.45871629 | G64: =G41/G62 -> 0.45582882 | H64: =H41/H62 -> 0.45441686 | I64: =I41/I62 -> 0.45240796 | J64: =J41/J62 -> 0.45119954 | ... M64: =M41/M62 -> 0.45120236
A66: 情境 C（信用壓力：2027 年次級車貸循環＋二手車價下跌）
A67: 零售車輛銷售 | B67: US$M | C67: =Thesis!C63 -> 14537 | D67: =Thesis!D63 -> 22745.831 | E67: =Thesis!E63 -> 20880.673 | F67: =Thesis!F63 -> 22363.201 | G67: =Thesis!G63 -> 24521.25 | H67: =Thesis!H63 -> 27512.842 | I67: =Thesis!I63 -> 30532.652 | J67: =Thesis!J63 -> 33510.196 | ... M67: =Thesis!M63 -> 41396.935
A68: 批發銷售與營收 | B68: US$M | C68: =Thesis!C65 -> 4052 | D68: =Thesis!D65 -> 5094.0459 | E68: =Thesis!E65 -> 4676.3341 | F68: =Thesis!F65 -> 5008.3538 | G68: =Thesis!G65 -> 5491.66 | H68: =Thesis!H65 -> 6161.6425 | I68: =Thesis!I65 -> 6837.9444 | J68: =Thesis!J65 -> 7504.7807 | ... M68: =Thesis!M65 -> 9271.0566
A69: 其他銷售與營收 | B69: US$M | C69: =Q!M8 -> 1733 | D69: =Thesis!D76 -> 2251.88 | E69: =Thesis!E76 -> 1309.114 | F69: =Thesis!F76 -> 1553.2571 | G69: =Thesis!G76 -> 1869.2494 | H69: =Thesis!H76 -> 2284.0137 | I69: =Thesis!I76 -> 2515.7586 | J69: =Thesis!J76 -> 2740.7068 | K69: =Thesis!K76 -> 2952.7408 | ... M69: =Thesis!M76 -> 3313.1049
A70: 其中：貸款出售利得（命題子列） | B70: US$M | C70: =Thesis!C71 -> 1193 | D70: =Thesis!D71 -> 1472.62 | E70: =Thesis!E71 -> 607.78004 | F70: =Thesis!F71 -> 816.85637 | G70: =Thesis!G71 -> 1077.6186 | H70: =Thesis!H71 -> 1413.2199 | I70: =Thesis!I71 -> 1568.3349 | J70: =Thesis!J71 -> 1721.2789 | ... M70: =Thesis!M71 -> 2126.3878
A71: 其中：VSC、GAP 等非貸款（命題子列） | B71: US$M | C71: =C69-C70 -> 540 | D71: =D69-D70 -> 779.26 | E71: =E69-E70 -> 701.334 | F71: =F69-F70 -> 736.4007 | G71: =G69-G70 -> 791.63075 | H71: =H69-H70 -> 870.79383 | I71: =I69-I70 -> 947.42368 | J71: =J69-J70 -> 1019.4279 | ... M71: =M69-M70 -> 1186.7171
A72: 合併營收 | B72: US$M | C72: =Q!M9 -> 20322 | D72: =D67+D68+D69 -> 30091.757 | E72: =E67+E68+E69 -> 26866.121 | F72: =F67+F68+F69 -> 28924.812 | G72: =G67+G68+G69 -> 31882.159 | H72: =H67+H68+H69 -> 35958.498 | I72: =I67+I68+I69 -> 39886.355 | J72: =J67+J68+J69 -> 43755.684 | K72: =K67+K68+K69 -> 47465.475 | ... M72: =M67+M68+M69 -> 53981.097
A73: 營收年增 | B73: % | D73: =D72/C72-1 -> 0.48074782 | E73: =E72/D72-1 -> -0.10719334 | F73: =F72/E72-1 -> 0.076627755 | G73: =G72/F72-1 -> 0.10224258 | H73: =H72/G72-1 -> 0.12785644 | I73: =I72/H72-1 -> 0.10923305 | J73: =J72/I72-1 -> 0.097008834 | K73: =K72/J72-1 -> 0.084784215 | ... M73: =M72/L72-1 -> 0.060333794
A74: 零售毛利 | B74: US$M | C74: =Thesis!C74 -> 1978 | D74: =Thesis!D74 -> 2721.4419 | E74: =Thesis!E74 -> 2001.9208 | F74: =Thesis!F74 -> 2205.8201 | G74: =Thesis!G74 -> 2482.8451 | H74: =Thesis!H74 -> 2853.8771 | I74: =Thesis!I74 -> 3105.0182 | J74: =Thesis!J74 -> 3340.9996 | ... M74: =Thesis!M74 -> 3889.2614
A75: 批發毛利 | B75: US$M | C75: =Thesis!C75 -> 481 | D75: =Thesis!D75 -> 620.98675 | E75: =Thesis!E75 -> 481.94388 | F75: =Thesis!F75 -> 521.09256 | G75: =Thesis!G75 -> 576.35484 | H75: =Thesis!H75 -> 651.78869 | I75: =Thesis!I75 -> 709.1461 | J75: =Thesis!J75 -> 763.0412 | ... M75: =Thesis!M75 -> 888.25712
A76: 其他毛利 | B76: US$M | C76: =C69 -> 1733 | D76: =D69 -> 2251.88 | E76: =E69 -> 1309.114 | F76: =F69 -> 1553.2571 | G76: =G69 -> 1869.2494 | H76: =H69 -> 2284.0137 | I76: =I69 -> 2515.7586 | J76: =J69 -> 2740.7068 | ... M76: =M69 -> 3313.1049
A77: 毛利合計 | B77: US$M | C77: =C74+C75+C76 -> 4192 | D77: =D74+D75+D76 -> 5594.3086 | E77: =E74+E75+E76 -> 3792.9787 | F77: =F74+F75+F76 -> 4280.1697 | G77: =G74+G75+G76 -> 4928.4494 | H77: =H74+H75+H76 -> 5789.6794 | I77: =I74+I75+I76 -> 6329.9229 | J77: =J74+J75+J76 -> 6844.7476 | ... M77: =M74+M75+M76 -> 8090.6234
A78: SG&A | B78: US$M | C78: =Thesis!C78 -> 2308 | D78: =Thesis!D78 -> 2989.8516 | E78: =Thesis!E78 -> 2776.466 | F78: =Thesis!F78 -> 2901.2813 | G78: =Thesis!G78 -> 3086.4138 | H78: =Thesis!H78 -> 3343.0414 | I78: =Thesis!I78 -> 3592.839 | J78: =Thesis!J78 -> 3829.6326 | ... M78: =Thesis!M78 -> 4400.127
A79: 營業利益 | B79: US$M | C79: =fy25_oi -> 1881 | D79: =D77-D78 -> 2604.4571 | E79: =E77-E78 -> 1016.5127 | F79: =F77-F78 -> 1378.8885 | G79: =G77-G78 -> 1842.0355 | H79: =H77-H78 -> 2446.638 | I79: =I77-I78 -> 2737.0839 | J79: =J77-J78 -> 3015.115 | K79: =K77-K78 -> 3272.3176 | ... M79: =M77-M78 -> 3690.4964
A80: 營業利益率 | B80: % | C80: =C79/C72 -> 0.092559787 | D80: =D79/D72 -> 0.086550514 | E80: =E79/E72 -> 0.037836229 | F80: =F79/F72 -> 0.047671475 | G80: =G79/G72 -> 0.057776374 | H80: =H79/H72 -> 0.068040606 | I80: =I79/I72 -> 0.068622062 | J80: =J79/J72 -> 0.068907961 | ... M80: =M79/M72 -> 0.068366458
A81: 利息費用（淨；CF 頁債務表） | B81: US$M | C81: =fy25_int -> 505 | D81: =CF!D123 -> 390.40787 | E81: =CF!E123 -> 335.41358 | F81: =CF!F123 -> 321.78433 | G81: =CF!G123 -> 298.86332 | H81: =CF!H123 -> 308.41956 | I81: =CF!I123 -> 318.53018 | J81: =CF!J123 -> 330.6199 | K81: =CF!K123 -> 342.93386 | ... M81: =CF!M123 -> 270.38025
A82: 其他費用（收益） | B82: US$M | C82: =Q!M21 -> 2266 | D82: =ytd_oth_exp -> 105 | E82: =0 -> 0 | F82: =0 -> 0 | G82: =0 -> 0 | H82: =0 -> 0 | I82: =0 -> 0 | J82: =0 -> 0 | K82: =0 -> 0 | L82: =0 -> 0 | M82: =0 -> 0
A83: 稅前淨利 | B83: US$M | C83: =C79-C81-C82 -> -890 | D83: =D79-D81-D82 -> 2109.0492 | E83: =E79-E81-E82 -> 681.09913 | F83: =F79-F81-F82 -> 1057.1041 | G83: =G79-G81-G82 -> 1543.1722 | H83: =H79-H81-H82 -> 2138.2185 | I83: =I79-I81-I82 -> 2418.5537 | J83: =J79-J81-J82 -> 2684.4951 | ... M83: =M79-M81-M82 -> 3420.1161
A84: 所得稅 | B84: US$M | C84: =fy25_tax -> -2785 | D84: =ytd_tax+(D83-(ytd_oi-ytd_int-ytd_oth_exp))*etr_26 -> 229.41947 | E84: =E83*etr_27 -> 81.731896 | F84: =F83*(etr_27+(etr_30-etr_27)/3) -> 147.99458 | G84: =G83*(etr_27+(etr_30-etr_27)*2/3) -> 246.90756 | H84: =H83*etr_30 -> 384.87933 | I84: =I83*etr_30 -> 435.33967 | J84: =J83*etr_30 -> 483.20911 | K84: =K83*etr_30 -> 527.28908 | L84: =L83*etr_30 -> 583.40661 | M84: =M83*etr_30 -> 615.6209
A85: 淨利（合併，含非控制權益） | B85: US$M | C85: =C83-C84 -> 1895 | D85: =D83-D84 -> 1879.6297 | E85: =E83-E84 -> 599.36724 | F85: =F83-F84 -> 909.10955 | G85: =G83-G84 -> 1296.2647 | H85: =H83-H84 -> 1753.3392 | I85: =I83-I84 -> 1983.2141 | J85: =J83-J84 -> 2201.2859 | ... M85: =M83-M84 -> 2804.4952
A86: 淨利率 | B86: % | C86: =C85/C72 -> 0.093248696 | D86: =D85/D72 -> 0.062463275 | E86: =E85/E72 -> 0.022309407 | F86: =F85/F72 -> 0.031430094 | G86: =G85/G72 -> 0.040657995 | H86: =H85/H72 -> 0.048760077 | I86: =I85/I72 -> 0.049721617 | J86: =J85/J72 -> 0.050308572 | ... M86: =M85/M72 -> 0.051953284
A87: 每股盈餘（完全轉換股數） | B87: US$ | D87: =D85/sh_fx -> 1.667817 | E87: =E85/sh_fx -> 0.53182541 | F87: =F85/sh_fx -> 0.80666331 | G87: =G85/sh_fx -> 1.1501905 | H87: =H85/sh_fx -> 1.5557579 | I87: =I85/sh_fx -> 1.7597285 | J87: =J85/sh_fx -> 1.9532262 | K87: =K85/sh_fx -> 2.1314061 | ... M87: =M85/sh_fx -> 2.4884607
A88: 折舊攤銷 | B88: US$M | C88: =fy25_da -> 275 | D88: =ytd_da+da_q4 -> 266 | E88: =(ytd_da+da_q4)*(1+infl) -> 273.98 | F88: =(ytd_da+da_q4)*(1+infl)^2+SUM(Thesis!E82:E82)/life -> 282.1994 | G88: =(ytd_da+da_q4)*(1+infl)^3+SUM(Thesis!E82:F82)/life -> 290.66538 | H88: =(ytd_da+da_q4)*(1+infl)^4+SUM(Thesis!E82:G82)/life -> 299.38534 | I88: =(ytd_da+da_q4)*(1+infl)^5+SUM(Thesis!E82:H82)/life -> 308.3669 | J88: =(ytd_da+da_q4)*(1+infl)^6+SUM(Thesis!E82:I82)/life -> 317.61791 | K88: =(ytd_da+da_q4)*(1+infl)^7+SUM(Thesis!E82:J82)/life -> 327.14645 | L88: =(ytd_da+da_q4)*(1+infl)^8+SUM(Thesis!E82:K82)/life -> 336.96084 | M88: =(ytd_da+da_q4)*(1+infl)^9+SUM(Thesis!E82:L82)/life -> 347.06967
A89: 股份基礎給付 | B89: US$M | C89: =fy25_sbc -> 99 | D89: =ytd_sbc+sbc_q4 -> 103 | E89: =(ytd_sbc+sbc_q4)*(1+infl)^1 -> 106.09 | F89: =(ytd_sbc+sbc_q4)*(1+infl)^2 -> 109.2727 | G89: =(ytd_sbc+sbc_q4)*(1+infl)^3 -> 112.55088 | H89: =(ytd_sbc+sbc_q4)*(1+infl)^4 -> 115.92741 | I89: =(ytd_sbc+sbc_q4)*(1+infl)^5 -> 119.40523 | J89: =(ytd_sbc+sbc_q4)*(1+infl)^6 -> 122.98739 | K89: =(ytd_sbc+sbc_q4)*(1+infl)^7 -> 126.67701 | L89: =(ytd_sbc+sbc_q4)*(1+infl)^8 -> 130.47732 | M89: =(ytd_sbc+sbc_q4)*(1+infl)^9 -> 134.39164
A90: 權證營收（扣除） | B90: US$M | C90: =fy25_warrant -> 21 | D90: =ytd_warrant+warr/4 -> 21.25 | E90: =warr -> 21 | F90: =warr -> 21 | G90: =warr -> 21 | H90: =warr -> 21 | I90: =warr -> 21 | J90: =warr -> 21 | K90: =warr -> 21 | L90: =warr -> 21 | M90: =warr -> 21
A91: 調整後 EBITDA | B91: US$M | C91: =Q!M19 -> 2237 | D91: =D79+D88+D89-D90 -> 2952.2071 | E91: =E79+E88+E89-E90 -> 1375.5827 | F91: =F79+F88+F89-F90 -> 1749.3606 | G91: =G79+G88+G89-G90 -> 2224.2518 | H91: =H79+H88+H89-H90 -> 2840.9508 | I91: =I79+I88+I89-I90 -> 3143.856 | J91: =J79+J88+J89-J90 -> 3434.7202 | K91: =K79+K88+K89-K90 -> 3705.1411 | ... M91: =M79+M88+M89-M90 -> 4150.9577
A92: 調整後 EBITDA 率 | B92: % | C92: =C91/C72 -> 0.11007775 | D92: =D91/D72 -> 0.098106835 | E92: =E91/E72 -> 0.051201388 | F92: =F91/F72 -> 0.060479583 | G92: =G91/G72 -> 0.069764779 | H92: =H91/H72 -> 0.07900638 | I92: =I91/I72 -> 0.07882034 | J92: =J91/J72 -> 0.078497694 | ... M92: =M91/M72 -> 0.076896505
A93: 貸款出售利得 ÷ 調整後 EBITDA | B93: % | C93: =C70/C91 -> 0.53330353 | D93: =D70/D91 -> 0.49882003 | E93: =E70/E91 -> 0.4418346 | F93: =F70/F91 -> 0.46694569 | G93: =G70/G91 -> 0.4844859 | H93: =H70/H91 -> 0.49744609 | I93: =I70/I91 -> 0.49885709 | J93: =J70/J91 -> 0.50114092 | ... M93: =M70/M91 -> 0.51226438

Sheet CF
A1: CF — 收支模組。收支關卡＝自由現金流 − TRA 付款 − 代 NCI 繳稅 − 排定到期本金 − 贖回溢價；期末現金低於最低營運現金時以新增外部融資補足（利息自次年計）。FY2026＝全年（上半年實績＋下半年模型）
A2: 利息以期初餘額 × 各工具利率計（避免循環參照）；「其他利息與費用」以 Q2 2026 實績校準，並隨貸款發放量縮放
A3: 收支摘要 | B3: 單位 | C3: 情境 A | D3: 情境 B | E3: 情境 C
A4: 收支關卡：FY2027–FY2031 合計（A／B／C 於 C、D、E 欄） | C4: =SUM(E30:I30) -> 23175.187 | D4: =SUM(E68:I68) -> 16038.47 | E4: =SUM(E106:I106) -> 5947.1788
A5: 新增外部融資需求：FY2027–FY2031 合計 | C5: =SUM(E32:I32) -> 0 | D5: =SUM(E70:I70) -> 0 | E5: =SUM(E108:I108) -> 0
A6: FY2027–FY2031 期末現金最低值 | C6: =MIN(E34:I34) -> 5000 | D6: =MIN(E72:I72) -> 5000 | E6: =MIN(E110:I110) -> 4225.3682
A7: FY2027–FY2031 超額現金（高於現金上限，可回饋股東或提前還債）合計 | C7: =SUM(E33:I33) -> 22029.433 | D7: =SUM(E71:I71) -> 14892.716 | E7: =SUM(E109:I109) -> 4801.4242
A9: 其他利息與費用校準（年化，以 2026-09-30 結構；扣除 Q3 中 2030 年票據 1.5 個月的高利率） | B9: US$M | C9: =4*(int_lq-tlb*(ssn_r-swap_fix-tlb_sp)*1.5/12)-tlb*(swap_fix+tlb_sp)-ssn_31*ssn_r-uns*uns_r-re_fin*re_r-bi_adv*lq_bi*bi_r-fleet*fleet_r-finls*finls_r-fp_ratio*lq_inv*fp_r+lq_cash*cash_y -> 71.7616
A12: 情境 A（樂觀：沿公司 300 萬台路徑、利得率維持）
A13: 項目 | B13: 單位 | C13: FY2025A | D13: FY2026E | E13: FY2027E | F13: FY2028E | G13: FY2029E | H13: FY2030E | I13: FY2031E | J13: FY2032E | K13: FY2033E | L13: FY2034E | M13: FY2035E
A14: 存貨（期末） | B14: US$M | C14: =d25_inv -> 2408 | D14: =inv_d*(PL!D9-PL!D16)/365 -> 3291.6805 | E14: =inv_d*(PL!E9-PL!E16)/365 -> 4390.7047 | F14: =inv_d*(PL!F9-PL!F16)/365 -> 5741.3515 | G14: =inv_d*(PL!G9-PL!G16)/365 -> 7272.8214 | H14: =inv_d*(PL!H9-PL!H16)/365 -> 8915.5524 | I14: =inv_d*(PL!I9-PL!I16)/365 -> 10724.013 | J14: =inv_d*(PL!J9-PL!J16)/365 -> 12635.277 | K14: =inv_d*(PL!K9-PL!K16)/365 -> 13815.533 | ... M14: =inv_d*(PL!M9-PL!M16)/365 -> 14447.397
A15: 待售貸款（期末） | B15: US$M | C15: =d25_frhfs -> 813 | D15: =fr_d*Thesis!D15/365 -> 853.59518 | E15: =fr_d*Thesis!E15/365 -> 1149.2805 | F15: =fr_d*Thesis!F15/365 -> 1500.5007 | G15: =fr_d*Thesis!G15/365 -> 1897.8333 | H15: =fr_d*Thesis!H15/365 -> 2322.9479 | I15: =fr_d*Thesis!I15/365 -> 2786.4225 | J15: =fr_d*Thesis!J15/365 -> 3274.1579 | K15: =fr_d*Thesis!K15/365 -> 3570.5392 | ... M15: =fr_d*Thesis!M15/365 -> 3714.789
A16: 應付與應計（期末） | B16: US$M | C16: 1100 | D16: =ap_pct*(PL!D14-PL!D19+PL!D20) -> 1484.3142 | E16: =ap_pct*(PL!E14-PL!E19+PL!E20) -> 1968.4495 | F16: =ap_pct*(PL!F14-PL!F19+PL!F20) -> 2553.3474 | G16: =ap_pct*(PL!G14-PL!G19+PL!G20) -> 3213.0351 | H16: =ap_pct*(PL!H14-PL!H19+PL!H20) -> 3916.7373 | I16: =ap_pct*(PL!I14-PL!I19+PL!I20) -> 4686.4924 | J16: =ap_pct*(PL!J14-PL!J19+PL!J20) -> 5495.7836 | K16: =ap_pct*(PL!K14-PL!K19+PL!K20) -> 5986.006 | ... M16: =ap_pct*(PL!M14-PL!M19+PL!M20) -> 6221.1491
A17: 證券化受益權（期末，隨發放量縮放） | B17: US$M | C17: =d25_bi -> 486 | D17: =lq_bi*Thesis!D15/Thesis!D15 -> 557 | E17: =lq_bi*Thesis!E15/Thesis!D15 -> 749.9448 | F17: =lq_bi*Thesis!F15/Thesis!D15 -> 979.12793 | G17: =lq_bi*Thesis!G15/Thesis!D15 -> 1238.401 | H17: =lq_bi*Thesis!H15/Thesis!D15 -> 1515.8028 | I17: =lq_bi*Thesis!I15/Thesis!D15 -> 1818.2358 | J17: =lq_bi*Thesis!J15/Thesis!D15 -> 2136.4998 | K17: =lq_bi*Thesis!K15/Thesis!D15 -> 2329.8987 | L17: =lq_bi*Thesis!L15/Thesis!D15 -> 2376.4967 | M17: =lq_bi*Thesis!M15/Thesis!D15 -> 2424.0266
A18: 淨利 | B18: US$M | D18: =PL!D27 -> 1879.6297 | E18: =PL!E27 -> 3335.8558 | F18: =PL!F27 -> 4614.2538 | G18: =PL!G27 -> 5997.2151 | H18: =PL!H27 -> 7402.2458 | I18: =PL!I27 -> 9041.8747 | J18: =PL!J27 -> 10766.339 | K18: =PL!K27 -> 11807.678 | ... M18: =PL!M27 -> 12368.152
A19: ＋折舊攤銷＋SBC | B19: US$M | D19: =PL!D30+PL!D31 -> 369 | E19: =PL!E30+PL!E31 -> 380.07 | F19: =PL!F30+PL!F31 -> 396.97576 | G19: =PL!G30+PL!G31 -> 424.4408 | H19: =PL!H30+PL!H31 -> 452.7822 | I19: =PL!I30+PL!I31 -> 482.3962 | J19: =PL!J30+PL!J31 -> 512.65223 | K19: =PL!K30+PL!K31 -> 534.99993 | ... M19: =PL!M30+PL!M31 -> 562.63778
A20: ＋帳面稅與現金稅差額（遞延所得稅資產抵用） | B20: US$M | D20: =PL!D26-MAX(0,PL!D25)*ctr -> 166.148 | E20: =PL!E26-MAX(0,PL!E25)*ctr -> 341.16707 | F20: =PL!F26-MAX(0,PL!F25)*ctr -> 590.19525 | G20: =0 -> 0 | H20: =0 -> 0 | I20: =0 -> 0 | J20: =0 -> 0 | K20: =0 -> 0 | L20: =0 -> 0 | M20: =0 -> 0
A21: −營運資金增加（存貨＋待售貸款 − 應付） | B21: US$M | D21: =-((D14-C14)+(D15-C15)-(D16-C16)) -> -539.96143 | E21: =-((E14-D14)+(E15-D15)-(E16-D16)) -> -910.57424 | F21: =-((F14-E14)+(F15-E15)-(F16-E16)) -> -1116.9691 | G21: =-((G14-F14)+(G15-F15)-(G16-F16)) -> -1269.1147 | H21: =-((H14-G14)+(H15-G15)-(H16-G16)) -> -1364.1435 | I21: =-((I14-H14)+(I15-H15)-(I16-H16)) -> -1502.18 | J21: =-((J14-I14)+(J15-I15)-(J16-I16)) -> -1589.7086 | K21: =-((K14-J14)+(K15-J15)-(K16-J16)) -> -986.41479 | ... M21: =-((M14-L14)+(M15-L15)-(M16-L16)) -> -272.88442
A22: −風險自留淨現金（受益權增加 ×（1 − 融資成數）） | B22: US$M | D22: =-(D17-C17)*(1-bi_adv) -> -16.570916 | E22: =-(E17-D17)*(1-bi_adv) -> -45.032 | F22: =-(F17-E17)*(1-bi_adv) -> -53.489779 | G22: =-(G17-F17)*(1-bi_adv) -> -60.512567 | H22: =-(H17-G17)*(1-bi_adv) -> -64.743694 | I22: =-(I17-H17)*(1-bi_adv) -> -70.585795 | J22: =-(J17-I17)*(1-bi_adv) -> -74.280646 | K22: =-(K17-J17)*(1-bi_adv) -> -45.137988 | ... M22: =-(M17-L17)*(1-bi_adv) -> -11.093162
A23: 營業現金流（模型口徑） | B23: US$M | D23: =D18+D19+D20+D21+D22 -> 1858.2454 | E23: =E18+E19+E20+E21+E22 -> 3101.4867 | F23: =F18+F19+F20+F21+F22 -> 4430.9659 | G23: =G18+G19+G20+G21+G22 -> 5092.0286 | H23: =H18+H19+H20+H21+H22 -> 6426.1408 | I23: =I18+I19+I20+I21+I22 -> 7951.5051 | J23: =J18+J19+J20+J21+J22 -> 9615.0017 | K23: =K18+K19+K20+K21+K22 -> 11311.125 | ... M23: =M18+M19+M20+M21+M22 -> 12646.812
A24: 資本支出（維護＋成長） | B24: US$M | D24: =ytd_capex+capex_q4 -> 236 | E24: =PL!E14*mcx+Thesis!E28 -> 285.60327 | F24: =PL!F14*mcx+Thesis!F28 -> 500.78145 | G24: =PL!G14*mcx+Thesis!G28 -> 578.64222 | H24: =PL!H14*mcx+Thesis!H28 -> 667.12499 | I24: =PL!I14*mcx+Thesis!I28 -> 752.68256 | J24: =PL!J14*mcx+Thesis!J28 -> 714.02148 | K24: =PL!K14*mcx+Thesis!K28 -> 629.03252 | L24: =PL!L14*mcx+Thesis!L28 -> 641.32941 | M24: =PL!M14*mcx+Thesis!M28 -> 653.87223
A25: 自由現金流 | B25: US$M | D25: =D23-D24 -> 1622.2454 | E25: =E23-E24 -> 2815.8834 | F25: =F23-F24 -> 3930.1844 | G25: =G23-G24 -> 4513.3864 | H25: =H23-H24 -> 5759.0158 | I25: =I23-I24 -> 7198.8225 | J25: =J23-J24 -> 8900.9803 | K25: =K23-K24 -> 10682.093 | ... M25: =M23-M24 -> 11992.94
A26: TRA 付款 | B26: US$M | D26: =37+tra_q4 -> 37 | E26: =MIN(tra_0-tra_q4,tra_0/tra_yrs) -> 142 | F26: =MIN(tra_0-tra_q4-SUM(E26:E26),tra_0/tra_yrs) -> 142 | G26: =MIN(tra_0-tra_q4-SUM(E26:F26),tra_0/tra_yrs) -> 142 | H26: =MIN(tra_0-tra_q4-SUM(E26:G26),tra_0/tra_yrs) -> 142 | I26: =MIN(tra_0-tra_q4-SUM(E26:H26),tra_0/tra_yrs) -> 142 | J26: =MIN(tra_0-tra_q4-SUM(E26:I26),tra_0/tra_yrs) -> 142 | K26: =MIN(tra_0-tra_q4-SUM(E26:J26),tra_0/tra_yrs) -> 142 | L26: =MIN(tra_0-tra_q4-SUM(E26:K26),tra_0/tra_yrs) -> 142 | M26: =MIN(tra_0-tra_q4-SUM(E26:L26),tra_0/tra_yrs) -> 142
A27: 代非控制權益繳稅 | B27: US$M | D27: =ncitax -> 8 | E27: =ncitax -> 8 | F27: =ncitax -> 8 | G27: =ncitax -> 8 | H27: =ncitax -> 8 | I27: =ncitax -> 8 | J27: =ncitax -> 8 | K27: =ncitax -> 8 | ... M27: =ncitax -> 8
A28: 排定到期本金（定期貸款攤還、無擔保票據） | B28: US$M | D28: =0 -> 0 | E28: =tlb*0.01+32 -> 48.6 | F28: =tlb*0.01+22 -> 38.6 | G28: =tlb*0.01+26 -> 42.6 | H28: =tlb*0.01+27 -> 43.6 | I28: =tlb*0.01 -> 16.6 | J28: =tlb*0.01 -> 16.6 | K28: =tlb-tlb*0.01*6 -> 1560.4 | L28: =0 -> 0 | M28: =0 -> 0
A29: 贖回溢價與費用 | B29: US$M | D29: =redeem_cost -> 50 | E29: =IF(2027=refi_yr,ssn_31*refi_prem,0) -> 0 | F29: =IF(2028=refi_yr,ssn_31*refi_prem,0) -> 102.105 | G29: =IF(2029=refi_yr,ssn_31*refi_prem,0) -> 0 | H29: =IF(2030=refi_yr,ssn_31*refi_prem,0) -> 0 | I29: =IF(2031=refi_yr,ssn_31*refi_prem,0) -> 0 | J29: =IF(2032=refi_yr,ssn_31*refi_prem,0) -> 0 | K29: =IF(2033=refi_yr,ssn_31*refi_prem,0) -> 0 | L29: =IF(2034=refi_yr,ssn_31*refi_prem,0) -> 0 | M29: =IF(2035=refi_yr,ssn_31*refi_prem,0) -> 0
A30: 收支關卡：自由現金流扣 TRA 與到期本金 | B30: US$M | D30: =D25-D26-D27-D28-D29 -> 1527.2454 | E30: =E25-E26-E27-E28-E29 -> 2617.2834 | F30: =F25-F26-F27-F28-F29 -> 3639.4794 | G30: =G25-G26-G27-G28-G29 -> 4320.7864 | H30: =H25-H26-H27-H28-H29 -> 5565.4158 | I30: =I25-I26-I27-I28-I29 -> 7032.2225 | J30: =J25-J26-J27-J28-J29 -> 8734.3803 | K30: =K25-K26-K27-K28-K29 -> 8971.6929 | ... M30: =M25-M26-M27-M28-M29 -> 11842.94
A31: 期末現金（融資與分配前） | B31: US$M | D31: =C34+D30 -> 3854.2454 | E31: =D34+E30 -> 6471.5287 | F31: =E34+F30 -> 8639.4794 | G31: =F34+G30 -> 9320.7864 | H31: =G34+H30 -> 10565.416 | I31: =H34+I30 -> 12032.222 | J31: =I34+J30 -> 13734.38 | K31: =J34+K30 -> 13971.693 | ... M31: =L34+M30 -> 16842.94
A32: 新增外部融資（補足至最低營運現金） | B32: US$M | D32: =MAX(0,min_cash-D31) -> 0 | E32: =MAX(0,min_cash-E31) -> 0 | F32: =MAX(0,min_cash-F31) -> 0 | G32: =MAX(0,min_cash-G31) -> 0 | H32: =MAX(0,min_cash-H31) -> 0 | I32: =MAX(0,min_cash-I31) -> 0 | J32: =MAX(0,min_cash-J31) -> 0 | K32: =MAX(0,min_cash-K31) -> 0 | ... M32: =MAX(0,min_cash-M31) -> 0
A33: 超額現金（高於現金上限；視為回饋股東或提前還債，不再計息） | B33: US$M | D33: =MAX(0,D31-cash_cap) -> 0 | E33: =MAX(0,E31-cash_cap) -> 1471.5287 | F33: =MAX(0,F31-cash_cap) -> 3639.4794 | G33: =MAX(0,G31-cash_cap) -> 4320.7864 | H33: =MAX(0,H31-cash_cap) -> 5565.4158 | I33: =MAX(0,I31-cash_cap) -> 7032.2225 | J33: =MAX(0,J31-cash_cap) -> 8734.3803 | K33: =MAX(0,K31-cash_cap) -> 8971.6929 | ... M33: =MAX(0,M31-cash_cap) -> 11842.94
A34: 期末現金 | B34: US$M | C34: =d25_cash -> 2327 | D34: =D31+D32-D33 -> 3854.2454 | E34: =E31+E32-E33 -> 5000 | F34: =F31+F32-F33 -> 5000 | G34: =G31+G32-G33 -> 5000 | H34: =H31+H32-H33 -> 5000 | I34: =I31+I32-I33 -> 5000 | J34: =J31+J32-J33 -> 5000 | K34: =K31+K32-K33 -> 5000 | ... M34: =M31+M32-M33 -> 5000
A35: 債務（期末）
A36: 定期貸款 B（2026 年起；取代 2030 年擔保票據） | B36: US$M | C36: =0 -> 0 | D36: =tlb -> 1660 | E36: =tlb-tlb*0.01*1 -> 1643.4 | F36: =tlb-tlb*0.01*2 -> 1626.8 | G36: =tlb-tlb*0.01*3 -> 1610.2 | H36: =tlb-tlb*0.01*4 -> 1593.6 | I36: =tlb-tlb*0.01*5 -> 1577 | J36: =tlb-tlb*0.01*6 -> 1560.4 | K36: =0 -> 0 | L36: =0 -> 0 | M36: =0 -> 0
A37: 2030 年擔保票據 | B37: US$M | C37: =tlb_old -> 1660 | D37: =0 -> 0 | E37: =0 -> 0 | F37: =0 -> 0 | G37: =0 -> 0 | H37: =0 -> 0 | I37: =0 -> 0 | J37: =0 -> 0 | K37: =0 -> 0 | ... M37: =0 -> 0
A38: 2031 年擔保票據 | B38: US$M | C38: =IF(2025<refi_yr,ssn_31,0) -> 2269 | D38: =IF(2026<refi_yr,ssn_31,0) -> 2269 | E38: =IF(2027<refi_yr,ssn_31,0) -> 2269 | F38: =IF(2028<refi_yr,ssn_31,0) -> 0 | G38: =IF(2029<refi_yr,ssn_31,0) -> 0 | H38: =IF(2030<refi_yr,ssn_31,0) -> 0 | I38: =IF(2031<refi_yr,ssn_31,0) -> 0 | J38: =IF(2032<refi_yr,ssn_31,0) -> 0 | K38: =IF(2033<refi_yr,ssn_31,0) -> 0 | L38: =IF(2034<refi_yr,ssn_31,0) -> 0 | M38: =IF(2035<refi_yr,ssn_31,0) -> 0
A39: 2031 年票據再融資貸款 | B39: US$M | C39: =IF(2025>=refi_yr,ssn_31*(1+0),0) -> 0 | D39: =IF(2026>=refi_yr,ssn_31*(1+0),0) -> 0 | E39: =IF(2027>=refi_yr,ssn_31*(1+0),0) -> 0 | F39: =IF(2028>=refi_yr,ssn_31*(1+0),0) -> 2269 | G39: =IF(2029>=refi_yr,ssn_31*(1+0),0) -> 2269 | H39: =IF(2030>=refi_yr,ssn_31*(1+0),0) -> 2269 | I39: =IF(2031>=refi_yr,ssn_31*(1+0),0) -> 2269 | J39: =IF(2032>=refi_yr,ssn_31*(1+0),0) -> 2269 | K39: =IF(2033>=refi_yr,ssn_31*(1+0),0) -> 2269 | L39: =IF(2034>=refi_yr,ssn_31*(1+0),0) -> 2269 | M39: =IF(2035>=refi_yr,ssn_31*(1+0),0) -> 2269
A40: 無擔保票據 | B40: US$M | C40: =uns -> 107 | D40: =uns -> 107 | E40: =uns-32 -> 75 | F40: =uns-32-22 -> 53 | G40: =uns-32-22-26 -> 27 | H40: =0 -> 0 | I40: =0 -> 0 | J40: =0 -> 0 | K40: =0 -> 0 | L40: =0 -> 0 | M40: =0 -> 0
A41: 不動產售後租回融資 | B41: US$M | C41: =re_fin -> 485 | D41: =re_fin -> 485 | E41: =re_fin -> 485 | F41: =re_fin -> 485 | G41: =re_fin -> 485 | H41: =re_fin -> 485 | I41: =re_fin -> 485 | J41: =re_fin -> 485 | ... M41: =re_fin -> 485
A42: 受益權融資 | B42: US$M | C42: =bi_adv*C17 -> 372.57092 | D42: =bi_adv*D17 -> 427 | E42: =bi_adv*E17 -> 574.9128 | F42: =bi_adv*F17 -> 750.60615 | G42: =bi_adv*G17 -> 949.36666 | H42: =bi_adv*H17 -> 1162.0248 | I42: =bi_adv*I17 -> 1393.872 | J42: =bi_adv*J17 -> 1637.8553 | ... M42: =bi_adv*M17 -> 1858.2754
A43: 車隊融資＋融資租賃 | B43: US$M | C43: =fleet+finls -> 260 | D43: =fleet+finls -> 260 | E43: =fleet+finls -> 260 | F43: =fleet+finls -> 260 | G43: =fleet+finls -> 260 | H43: =fleet+finls -> 260 | I43: =fleet+finls -> 260 | J43: =fleet+finls -> 260 | ... M43: =fleet+finls -> 260
A44: 存貨融資（floor plan） | B44: US$M | C44: =fp_ratio*C14 -> 49.469907 | D44: =fp_ratio*D14 -> 67.624222 | E44: =fp_ratio*E14 -> 90.202555 | F44: =fp_ratio*F14 -> 117.95022 | G44: =fp_ratio*G14 -> 149.41271 | H44: =fp_ratio*H14 -> 183.16094 | I44: =fp_ratio*I14 -> 220.31392 | J44: =fp_ratio*J14 -> 259.5789 | ... M44: =fp_ratio*M14 -> 296.80706
A45: 新增外部融資（累計） | B45: US$M | C45: =0 -> 0 | D45: =C45+D32 -> 0 | E45: =D45+E32 -> 0 | F45: =E45+F32 -> 0 | G45: =F45+G32 -> 0 | H45: =G45+H32 -> 0 | I45: =H45+I32 -> 0 | J45: =I45+J32 -> 0 | K45: =J45+K32 -> 0 | ... M45: =L45+M32 -> 0
A46: 債務合計 | B46: US$M | C46: =SUM(C36:C45) -> 5203.0408 | D46: =SUM(D36:D45) -> 5275.6242 | E46: =SUM(E36:E45) -> 5397.5154 | F46: =SUM(F36:F45) -> 5562.3564 | G46: =SUM(G36:G45) -> 5749.9794 | H46: =SUM(H36:H45) -> 5952.7857 | I46: =SUM(I36:I45) -> 6205.1859 | J46: =SUM(J36:J45) -> 6471.8342 | ... M46: =SUM(M36:M45) -> 5169.0824
A47: 利息費用（淨） | B47: US$M | D47: =ytd_int+int_lq-tlb*(ssn_r-swap_fix-tlb_sp)*1.5/12 -> 390.40787 | E47: =D36*(IF(2027<=2028,swap_fix,sofr)+tlb_sp)+IF(2027=refi_yr,ssn_31*(ssn_r*7.5/12+(sofr+refi_sp)*(12-7.5)/12),D38*ssn_r+D39*(sofr+refi_sp))+D40*uns_r+D41*re_r+D42*bi_r+fleet*fleet_r+finls*finls_r+D44*fp_r+D45*(sofr+new_r_sp)+int_cal*Thesis!E15/Thesis!D15-D34*cash_y -> 366.15625 | F47: =E36*(IF(2028<=2028,swap_fix,sofr)+tlb_sp)+IF(2028=refi_yr,ssn_31*(ssn_r*7.5/12+(sofr+refi_sp)*(12-7.5)/12),E38*ssn_r+E39*(sofr+refi_sp))+E40*uns_r+E41*re_r+E42*bi_r+fleet*fleet_r+finls*finls_r+E44*fp_r+E45*(sofr+new_r_sp)+int_cal*Thesis!F15/Thesis!D15-E34*cash_y -> 344.03167 | G47: =F36*(IF(2029<=2028,swap_fix,sofr)+tlb_sp)+IF(2029=refi_yr,ssn_31*(ssn_r*7.5/12+(sofr+refi_sp)*(12-7.5)/12),F38*ssn_r+F39*(sofr+refi_sp))+F40*uns_r+F41*re_r+F42*bi_r+fleet*fleet_r+finls*finls_r+F44*fp_r+F45*(sofr+new_r_sp)+int_cal*Thesis!G15/Thesis!D15-F34*cash_y -> 353.52801 | H47: =G36*(IF(2030<=2028,swap_fix,sofr)+tlb_sp)+IF(2030=refi_yr,ssn_31*(ssn_r*7.5/12+(sofr+refi_sp)*(12-7.5)/12),G38*ssn_r+G39*(sofr+refi_sp))+G40*uns_r+G41*re_r+G42*bi_r+fleet*fleet_r+finls*finls_r+G44*fp_r+G45*(sofr+new_r_sp)+int_cal*Thesis!H15/Thesis!D15-G34*cash_y -> 401.82942 | I47: =H36*(IF(2031<=2028,swap_fix,sofr)+tlb_sp)+IF(2031=refi_yr,ssn_31*(ssn_r*7.5/12+(sofr+refi_sp)*(12-7.5)/12),H38*ssn_r+H39*(sofr+refi_sp))+H40*uns_r+H41*re_r+H42*bi_r+fleet*fleet_r+finls*finls_r+H44*fp_r+H45*(sofr+new_r_sp)+int_cal*Thesis!I15/Thesis!D15-H34*cash_y -> 454.36382 | J47: =I36*(IF(2032<=2028,swap_fix,sofr)+tlb_sp)+IF(2032=refi_yr,ssn_31*(ssn_r*7.5/12+(sofr+refi_sp)*(12-7.5)/12),I38*ssn_r+I39*(sofr+refi_sp))+I40*uns_r+I41*re_r+I42*bi_r+fleet*fleet_r+finls*finls_r+I44*fp_r+I45*(sofr+new_r_sp)+int_cal*Thesis!J15/Thesis!D15-I34*cash_y -> 512.22067 | K47: =J36*(IF(2033<=2028,swap_fix,sofr)+tlb_sp)+IF(2033=refi_yr,ssn_31*(ssn_r*7.5/12+(sofr+refi_sp)*(12-7.5)/12),J38*ssn_r+J39*(sofr+refi_sp))+J40*uns_r+J41*re_r+J42*bi_r+fleet*fleet_r+finls*finls_r+J44*fp_r+J45*(sofr+new_r_sp)+int_cal*Thesis!K15/Thesis!D15-J34*cash_y -> 554.93371 | L47: =K36*(IF(2034<=2028,swap_fix,sofr)+tlb_sp)+IF(2034=refi_yr,ssn_31*(ssn_r*7.5/12+(sofr+refi_sp)*(12-7.5)/12),K38*ssn_r+K39*(sofr+refi_sp))+K40*uns_r+K41*re_r+K42*bi_r+fleet*fleet_r+finls*finls_r+K44*fp_r+K45*(sofr+new_r_sp)+int_cal*Thesis!L15/Thesis!D15-K34*cash_y -> 475.95932 | M47: =L36*(IF(2035<=2028,swap_fix,sofr)+tlb_sp)+IF(2035=refi_yr,ssn_31*(ssn_r*7.5/12+(sofr+refi_sp)*(12-7.5)/12),L38*ssn_r+L39*(sofr+refi_sp))+L40*uns_r+L41*re_r+L42*bi_r+fleet*fleet_r+finls*finls_r+L44*fp_r+L45*(sofr+new_r_sp)+int_cal*Thesis!M15/Thesis!D15-L34*cash_y -> 484.86877
A50: 情境 B（基準：成長放緩、利得率小降）
A51: 項目 | B51: 單位 | C51: FY2025A | D51: FY2026E | E51: FY2027E | F51: FY2028E | G51: FY2029E | H51: FY2030E | I51: FY2031E | J51: FY2032E | K51: FY2033E | L51: FY2034E | M51: FY2035E
A52: 存貨（期末） | B52: US$M | C52: =d25_inv -> 2408 | D52: =inv_d*(PL!D38-PL!D45)/365 -> 3291.6805 | E52: =inv_d*(PL!E38-PL!E45)/365 -> 4183.2565 | F52: =inv_d*(PL!F38-PL!F45)/365 -> 5141.0936 | G52: =inv_d*(PL!G38-PL!G45)/365 -> 6133.2215 | H52: =inv_d*(PL!H38-PL!H45)/365 -> 7096.1606 | I52: =inv_d*(PL!I38-PL!I45)/365 -> 8083.1851 | J52: =inv_d*(PL!J38-PL!J45)/365 -> 9074.7598 | K52: =inv_d*(PL!K38-PL!K45)/365 -> 10038.981 | ... M52: =inv_d*(PL!M38-PL!M45)/365 -> 11744.206
A53: 待售貸款（期末） | B53: US$M | C53: =d25_frhfs -> 813 | D53: =fr_d*Thesis!D42/365 -> 853.59518 | E53: =fr_d*Thesis!E42/365 -> 1088.3339 | F53: =fr_d*Thesis!F42/365 -> 1332.1206 | G53: =fr_d*Thesis!G42/365 -> 1582.959 | H53: =fr_d*Thesis!H42/365 -> 1824.5185 | I53: =fr_d*Thesis!I42/365 -> 2073.1639 | J53: =fr_d*Thesis!J42/365 -> 2321.8606 | K53: =fr_d*Thesis!K42/365 -> 2562.4982 | ... M53: =fr_d*Thesis!M42/365 -> 2984.0797
A54: 應付與應計（期末） | B54: US$M | C54: 1100 | D54: =ap_pct*(PL!D43-PL!D48+PL!D49) -> 1484.3142 | E54: =ap_pct*(PL!E43-PL!E48+PL!E49) -> 1876.7447 | F54: =ap_pct*(PL!F43-PL!F48+PL!F49) -> 2291.1303 | G54: =ap_pct*(PL!G43-PL!G48+PL!G49) -> 2717.996 | H54: =ap_pct*(PL!H43-PL!H48+PL!H49) -> 3129.732 | I54: =ap_pct*(PL!I43-PL!I48+PL!I49) -> 3550.7741 | J54: =ap_pct*(PL!J43-PL!J48+PL!J49) -> 3971.8524 | K54: =ap_pct*(PL!K43-PL!K48+PL!K49) -> 4379.2962 | ... M54: =ap_pct*(PL!M43-PL!M48+PL!M49) -> 5093.4288
A55: 證券化受益權（期末，隨發放量縮放） | B55: US$M | C55: =d25_bi -> 486 | D55: =lq_bi*Thesis!D42/Thesis!D42 -> 557 | E55: =lq_bi*Thesis!E42/Thesis!D42 -> 710.175 | F55: =lq_bi*Thesis!F42/Thesis!D42 -> 869.2542 | G55: =lq_bi*Thesis!G42/Thesis!D42 -> 1032.9348 | H55: =lq_bi*Thesis!H42/Thesis!D42 -> 1190.5606 | I55: =lq_bi*Thesis!I42/Thesis!D42 -> 1352.8102 | J55: =lq_bi*Thesis!J42/Thesis!D42 -> 1515.0933 | K55: =lq_bi*Thesis!K42/Thesis!D42 -> 1672.1176 | L55: =lq_bi*Thesis!L42/Thesis!D42 -> 1818.1269 | M55: =lq_bi*Thesis!M42/Thesis!D42 -> 1947.2139
A56: 淨利 | B56: US$M | D56: =PL!D56 -> 1879.6297 | E56: =PL!E56 -> 2764.9102 | F56: =PL!F56 -> 3463.788 | G56: =PL!G56 -> 4105.678 | H56: =PL!H56 -> 4635.3335 | I56: =PL!I56 -> 5338.4891 | J56: =PL!J56 -> 6034.7515 | K56: =PL!K56 -> 6701.3248 | ... M56: =PL!M56 -> 7918.4816
A57: ＋折舊攤銷＋SBC | B57: US$M | D57: =PL!D59+PL!D60 -> 369 | E57: =PL!E59+PL!E60 -> 380.07 | F57: =PL!F59+PL!F60 -> 391.4721 | G57: =PL!G59+PL!G60 -> 410.96463 | H57: =PL!H59+PL!H60 -> 431.86841 | I57: =PL!I59+PL!I60 -> 453.05514 | J57: =PL!J59+PL!J60 -> 474.24604 | K57: =PL!K59+PL!K60 -> 495.14274 | ... M57: =PL!M59+PL!M60 -> 534.86797
A58: ＋帳面稅與現金稅差額（遞延所得稅資產抵用） | B58: US$M | D58: =PL!D55-MAX(0,PL!D54)*ctr -> 166.148 | E58: =PL!E55-MAX(0,PL!E54)*ctr -> 282.7749 | F58: =PL!F55-MAX(0,PL!F54)*ctr -> 443.04266 | G58: =0 -> 0 | H58: =0 -> 0 | I58: =0 -> 0 | J58: =0 -> 0 | K58: =0 -> 0 | L58: =0 -> 0 | M58: =0 -> 0
A59: −營運資金增加（存貨＋待售貸款 − 應付） | B59: US$M | D59: =-((D52-C52)+(D53-C53)-(D54-C54)) -> -539.96143 | E59: =-((E52-D52)+(E53-D53)-(E54-D54)) -> -733.88421 | F59: =-((F52-E52)+(F53-E53)-(F54-E54)) -> -787.23839 | G59: =-((G52-F52)+(G53-F53)-(G54-F54)) -> -816.10044 | H59: =-((H52-G52)+(H53-G53)-(H54-G54)) -> -792.76264 | I59: =-((I52-H52)+(I53-H53)-(I54-H54)) -> -814.6278 | J59: =-((J52-I52)+(J53-I53)-(J54-I54)) -> -819.19308 | K59: =-((K52-J52)+(K53-J53)-(K54-J54)) -> -797.41475 | ... M59: =-((M52-L52)+(M53-L53)-(M54-L54)) -> -665.97837
A60: −風險自留淨現金（受益權增加 ×（1 − 融資成數）） | B60: US$M | D60: =-(D55-C55)*(1-bi_adv) -> -16.570916 | E60: =-(E55-D55)*(1-bi_adv) -> -35.75 | F60: =-(F55-E55)*(1-bi_adv) -> -37.128 | G60: =-(G55-F55)*(1-bi_adv) -> -38.201927 | H60: =-(H55-G55)*(1-bi_adv) -> -36.788797 | I60: =-(I55-H55)*(1-bi_adv) -> -37.86795 | J60: =-(J55-I55)*(1-bi_adv) -> -37.875771 | K60: =-(K55-J55)*(1-bi_adv) -> -36.648394 | ... M60: =-(M55-L55)*(1-bi_adv) -> -30.128028
A61: 營業現金流（模型口徑） | B61: US$M | D61: =D56+D57+D58+D59+D60 -> 1858.2454 | E61: =E56+E57+E58+E59+E60 -> 2658.1208 | F61: =F56+F57+F58+F59+F60 -> 3473.9364 | G61: =G56+G57+G58+G59+G60 -> 3662.3403 | H61: =H56+H57+H58+H59+H60 -> 4237.6505 | I61: =I56+I57+I58+I59+I60 -> 4939.0485 | J61: =J56+J57+J58+J59+J60 -> 5651.9286 | K61: =K56+K57+K58+K59+K60 -> 6362.4044 | ... M61: =M56+M57+M58+M59+M60 -> 7757.2432
A62: 資本支出（維護＋成長） | B62: US$M | D62: =ytd_capex+capex_q4 -> 236 | E62: =PL!E43*mcx+Thesis!E55 -> 191.28753 | F62: =PL!F43*mcx+Thesis!F55 -> 350.14332 | G62: =PL!G43*mcx+Thesis!G55 -> 409.81725 | H62: =PL!H43*mcx+Thesis!H55 -> 450.70371 | I62: =PL!I43*mcx+Thesis!I55 -> 488.56959 | J62: =PL!J43*mcx+Thesis!J55 -> 521.76337 | K62: =PL!K43*mcx+Thesis!K55 -> 548.82619 | L62: =PL!L43*mcx+Thesis!L55 -> 568.47254 | M62: =PL!M43*mcx+Thesis!M55 -> 606.90504
A63: 自由現金流 | B63: US$M | D63: =D61-D62 -> 1622.2454 | E63: =E61-E62 -> 2466.8333 | F63: =F61-F62 -> 3123.7931 | G63: =G61-G62 -> 3252.5231 | H63: =H61-H62 -> 3786.9468 | I63: =I61-I62 -> 4450.4789 | J63: =J61-J62 -> 5130.1653 | K63: =K61-K62 -> 5813.5782 | ... M63: =M61-M62 -> 7150.3382
A64: TRA 付款 | B64: US$M | D64: =37+tra_q4 -> 37 | E64: =MIN(tra_0-tra_q4,tra_0/tra_yrs) -> 142 | F64: =MIN(tra_0-tra_q4-SUM(E64:E64),tra_0/tra_yrs) -> 142 | G64: =MIN(tra_0-tra_q4-SUM(E64:F64),tra_0/tra_yrs) -> 142 | H64: =MIN(tra_0-tra_q4-SUM(E64:G64),tra_0/tra_yrs) -> 142 | I64: =MIN(tra_0-tra_q4-SUM(E64:H64),tra_0/tra_yrs) -> 142 | J64: =MIN(tra_0-tra_q4-SUM(E64:I64),tra_0/tra_yrs) -> 142 | K64: =MIN(tra_0-tra_q4-SUM(E64:J64),tra_0/tra_yrs) -> 142 | L64: =MIN(tra_0-tra_q4-SUM(E64:K64),tra_0/tra_yrs) -> 142 | M64: =MIN(tra_0-tra_q4-SUM(E64:L64),tra_0/tra_yrs) -> 142
A65: 代非控制權益繳稅 | B65: US$M | D65: =ncitax -> 8 | E65: =ncitax -> 8 | F65: =ncitax -> 8 | G65: =ncitax -> 8 | H65: =ncitax -> 8 | I65: =ncitax -> 8 | J65: =ncitax -> 8 | K65: =ncitax -> 8 | ... M65: =ncitax -> 8
A66: 排定到期本金（定期貸款攤還、無擔保票據） | B66: US$M | D66: =0 -> 0 | E66: =tlb*0.01+32 -> 48.6 | F66: =tlb*0.01+22 -> 38.6 | G66: =tlb*0.01+26 -> 42.6 | H66: =tlb*0.01+27 -> 43.6 | I66: =tlb*0.01 -> 16.6 | J66: =tlb*0.01 -> 16.6 | K66: =tlb-tlb*0.01*6 -> 1560.4 | L66: =0 -> 0 | M66: =0 -> 0
A67: 贖回溢價與費用 | B67: US$M | D67: =redeem_cost -> 50 | E67: =IF(2027=refi_yr,ssn_31*refi_prem,0) -> 0 | F67: =IF(2028=refi_yr,ssn_31*refi_prem,0) -> 102.105 | G67: =IF(2029=refi_yr,ssn_31*refi_prem,0) -> 0 | H67: =IF(2030=refi_yr,ssn_31*refi_prem,0) -> 0 | I67: =IF(2031=refi_yr,ssn_31*refi_prem,0) -> 0 | J67: =IF(2032=refi_yr,ssn_31*refi_prem,0) -> 0 | K67: =IF(2033=refi_yr,ssn_31*refi_prem,0) -> 0 | L67: =IF(2034=refi_yr,ssn_31*refi_prem,0) -> 0 | M67: =IF(2035=refi_yr,ssn_31*refi_prem,0) -> 0
A68: 收支關卡：自由現金流扣 TRA 與到期本金 | B68: US$M | D68: =D63-D64-D65-D66-D67 -> 1527.2454 | E68: =E63-E64-E65-E66-E67 -> 2268.2333 | F68: =F63-F64-F65-F66-F67 -> 2833.0881 | G68: =G63-G64-G65-G66-G67 -> 3059.9231 | H68: =H63-H64-H65-H66-H67 -> 3593.3468 | I68: =I63-I64-I65-I66-I67 -> 4283.8789 | J68: =J63-J64-J65-J66-J67 -> 4963.5653 | K68: =K63-K64-K65-K66-K67 -> 4103.1782 | ... M68: =M63-M64-M65-M66-M67 -> 7000.3382
A69: 期末現金（融資與分配前） | B69: US$M | D69: =C72+D68 -> 3854.2454 | E69: =D72+E68 -> 6122.4787 | F69: =E72+F68 -> 7833.0881 | G69: =F72+G68 -> 8059.9231 | H69: =G72+H68 -> 8593.3468 | I69: =H72+I68 -> 9283.8789 | J69: =I72+J68 -> 9963.5653 | K69: =J72+K68 -> 9103.1782 | ... M69: =L72+M68 -> 12000.338
A70: 新增外部融資（補足至最低營運現金） | B70: US$M | D70: =MAX(0,min_cash-D69) -> 0 | E70: =MAX(0,min_cash-E69) -> 0 | F70: =MAX(0,min_cash-F69) -> 0 | G70: =MAX(0,min_cash-G69) -> 0 | H70: =MAX(0,min_cash-H69) -> 0 | I70: =MAX(0,min_cash-I69) -> 0 | J70: =MAX(0,min_cash-J69) -> 0 | K70: =MAX(0,min_cash-K69) -> 0 | ... M70: =MAX(0,min_cash-M69) -> 0
A71: 超額現金（高於現金上限；視為回饋股東或提前還債，不再計息） | B71: US$M | D71: =MAX(0,D69-cash_cap) -> 0 | E71: =MAX(0,E69-cash_cap) -> 1122.4787 | F71: =MAX(0,F69-cash_cap) -> 2833.0881 | G71: =MAX(0,G69-cash_cap) -> 3059.9231 | H71: =MAX(0,H69-cash_cap) -> 3593.3468 | I71: =MAX(0,I69-cash_cap) -> 4283.8789 | J71: =MAX(0,J69-cash_cap) -> 4963.5653 | K71: =MAX(0,K69-cash_cap) -> 4103.1782 | ... M71: =MAX(0,M69-cash_cap) -> 7000.3382
A72: 期末現金 | B72: US$M | C72: =d25_cash -> 2327 | D72: =D69+D70-D71 -> 3854.2454 | E72: =E69+E70-E71 -> 5000 | F72: =F69+F70-F71 -> 5000 | G72: =G69+G70-G71 -> 5000 | H72: =H69+H70-H71 -> 5000 | I72: =I69+I70-I71 -> 5000 | J72: =J69+J70-J71 -> 5000 | K72: =K69+K70-K71 -> 5000 | ... M72: =M69+M70-M71 -> 5000
A73: 債務（期末）
A74: 定期貸款 B（2026 年起；取代 2030 年擔保票據） | B74: US$M | C74: =0 -> 0 | D74: =tlb -> 1660 | E74: =tlb-tlb*0.01*1 -> 1643.4 | F74: =tlb-tlb*0.01*2 -> 1626.8 | G74: =tlb-tlb*0.01*3 -> 1610.2 | H74: =tlb-tlb*0.01*4 -> 1593.6 | I74: =tlb-tlb*0.01*5 -> 1577 | J74: =tlb-tlb*0.01*6 -> 1560.4 | K74: =0 -> 0 | L74: =0 -> 0 | M74: =0 -> 0
A75: 2030 年擔保票據 | B75: US$M | C75: =tlb_old -> 1660 | D75: =0 -> 0 | E75: =0 -> 0 | F75: =0 -> 0 | G75: =0 -> 0 | H75: =0 -> 0 | I75: =0 -> 0 | J75: =0 -> 0 | K75: =0 -> 0 | ... M75: =0 -> 0
A76: 2031 年擔保票據 | B76: US$M | C76: =IF(2025<refi_yr,ssn_31,0) -> 2269 | D76: =IF(2026<refi_yr,ssn_31,0) -> 2269 | E76: =IF(2027<refi_yr,ssn_31,0) -> 2269 | F76: =IF(2028<refi_yr,ssn_31,0) -> 0 | G76: =IF(2029<refi_yr,ssn_31,0) -> 0 | H76: =IF(2030<refi_yr,ssn_31,0) -> 0 | I76: =IF(2031<refi_yr,ssn_31,0) -> 0 | J76: =IF(2032<refi_yr,ssn_31,0) -> 0 | K76: =IF(2033<refi_yr,ssn_31,0) -> 0 | L76: =IF(2034<refi_yr,ssn_31,0) -> 0 | M76: =IF(2035<refi_yr,ssn_31,0) -> 0
A77: 2031 年票據再融資貸款 | B77: US$M | C77: =IF(2025>=refi_yr,ssn_31*(1+0),0) -> 0 | D77: =IF(2026>=refi_yr,ssn_31*(1+0),0) -> 0 | E77: =IF(2027>=refi_yr,ssn_31*(1+0),0) -> 0 | F77: =IF(2028>=refi_yr,ssn_31*(1+0),0) -> 2269 | G77: =IF(2029>=refi_yr,ssn_31*(1+0),0) -> 2269 | H77: =IF(2030>=refi_yr,ssn_31*(1+0),0) -> 2269 | I77: =IF(2031>=refi_yr,ssn_31*(1+0),0) -> 2269 | J77: =IF(2032>=refi_yr,ssn_31*(1+0),0) -> 2269 | K77: =IF(2033>=refi_yr,ssn_31*(1+0),0) -> 2269 | L77: =IF(2034>=refi_yr,ssn_31*(1+0),0) -> 2269 | M77: =IF(2035>=refi_yr,ssn_31*(1+0),0) -> 2269
A78: 無擔保票據 | B78: US$M | C78: =uns -> 107 | D78: =uns -> 107 | E78: =uns-32 -> 75 | F78: =uns-32-22 -> 53 | G78: =uns-32-22-26 -> 27 | H78: =0 -> 0 | I78: =0 -> 0 | J78: =0 -> 0 | K78: =0 -> 0 | L78: =0 -> 0 | M78: =0 -> 0
A79: 不動產售後租回融資 | B79: US$M | C79: =re_fin -> 485 | D79: =re_fin -> 485 | E79: =re_fin -> 485 | F79: =re_fin -> 485 | G79: =re_fin -> 485 | H79: =re_fin -> 485 | I79: =re_fin -> 485 | J79: =re_fin -> 485 | ... M79: =re_fin -> 485
A80: 受益權融資 | B80: US$M | C80: =bi_adv*C55 -> 372.57092 | D80: =bi_adv*D55 -> 427 | E80: =bi_adv*E55 -> 544.425 | F80: =bi_adv*F55 -> 666.3762 | G80: =bi_adv*G55 -> 791.85484 | H80: =bi_adv*H55 -> 912.69189 | I80: =bi_adv*I55 -> 1037.0735 | J80: =bi_adv*J55 -> 1161.4809 | ... M80: =bi_adv*M55 -> 1492.7475
A81: 車隊融資＋融資租賃 | B81: US$M | C81: =fleet+finls -> 260 | D81: =fleet+finls -> 260 | E81: =fleet+finls -> 260 | F81: =fleet+finls -> 260 | G81: =fleet+finls -> 260 | H81: =fleet+finls -> 260 | I81: =fleet+finls -> 260 | J81: =fleet+finls -> 260 | ... M81: =fleet+finls -> 260
A82: 存貨融資（floor plan） | B82: US$M | C82: =fp_ratio*C52 -> 49.469907 | D82: =fp_ratio*D52 -> 67.624222 | E82: =fp_ratio*E52 -> 85.940743 | F82: =fp_ratio*F52 -> 105.61853 | G82: =fp_ratio*G52 -> 126.00079 | H82: =fp_ratio*H52 -> 145.78339 | I82: =fp_ratio*I52 -> 166.06081 | J82: =fp_ratio*J52 -> 186.4317 | ... M82: =fp_ratio*M52 -> 241.27274
A83: 新增外部融資（累計） | B83: US$M | C83: =0 -> 0 | D83: =C83+D70 -> 0 | E83: =D83+E70 -> 0 | F83: =E83+F70 -> 0 | G83: =F83+G70 -> 0 | H83: =G83+H70 -> 0 | I83: =H83+I70 -> 0 | J83: =I83+J70 -> 0 | K83: =J83+K70 -> 0 | ... M83: =L83+M70 -> 0
A84: 債務合計 | B84: US$M | C84: =SUM(C74:C83) -> 5203.0408 | D84: =SUM(D74:D83) -> 5275.6242 | E84: =SUM(E74:E83) -> 5362.7657 | F84: =SUM(F74:F83) -> 5465.7947 | G84: =SUM(G74:G83) -> 5569.0556 | H84: =SUM(H74:H83) -> 5666.0753 | I84: =SUM(I74:I83) -> 5794.1343 | J84: =SUM(J74:J83) -> 5922.3126 | ... M84: =SUM(M74:M83) -> 4748.0202
A85: 利息費用（淨） | B85: US$M | D85: =ytd_int+int_lq-tlb*(ssn_r-swap_fix-tlb_sp)*1.5/12 -> 390.40787 | E85: =D74*(IF(2027<=2028,swap_fix,sofr)+tlb_sp)+IF(2027=refi_yr,ssn_31*(ssn_r*7.5/12+(sofr+refi_sp)*(12-7.5)/12),D76*ssn_r+D77*(sofr+refi_sp))+D78*uns_r+D79*re_r+D80*bi_r+fleet*fleet_r+finls*finls_r+D82*fp_r+D83*(sofr+new_r_sp)+int_cal*Thesis!E42/Thesis!D42-D72*cash_y -> 361.03247 | F85: =E74*(IF(2028<=2028,swap_fix,sofr)+tlb_sp)+IF(2028=refi_yr,ssn_31*(ssn_r*7.5/12+(sofr+refi_sp)*(12-7.5)/12),E76*ssn_r+E77*(sofr+refi_sp))+E78*uns_r+E79*re_r+E80*bi_r+fleet*fleet_r+finls*finls_r+E82*fp_r+E83*(sofr+new_r_sp)+int_cal*Thesis!F42/Thesis!D42-E72*cash_y -> 327.55262 | G85: =F74*(IF(2029<=2028,swap_fix,sofr)+tlb_sp)+IF(2029=refi_yr,ssn_31*(ssn_r*7.5/12+(sofr+refi_sp)*(12-7.5)/12),F76*ssn_r+F77*(sofr+refi_sp))+F78*uns_r+F79*re_r+F80*bi_r+fleet*fleet_r+finls*finls_r+F82*fp_r+F83*(sofr+new_r_sp)+int_cal*Thesis!G42/Thesis!D42-F72*cash_y -> 320.61295 | H85: =G74*(IF(2030<=2028,swap_fix,sofr)+tlb_sp)+IF(2030=refi_yr,ssn_31*(ssn_r*7.5/12+(sofr+refi_sp)*(12-7.5)/12),G76*ssn_r+G77*(sofr+refi_sp))+G78*uns_r+G79*re_r+G80*bi_r+fleet*fleet_r+finls*finls_r+G82*fp_r+G83*(sofr+new_r_sp)+int_cal*Thesis!H42/Thesis!D42-G72*cash_y -> 347.86122 | I85: =H74*(IF(2031<=2028,swap_fix,sofr)+tlb_sp)+IF(2031=refi_yr,ssn_31*(ssn_r*7.5/12+(sofr+refi_sp)*(12-7.5)/12),H76*ssn_r+H77*(sofr+refi_sp))+H78*uns_r+H79*re_r+H80*bi_r+fleet*fleet_r+finls*finls_r+H82*fp_r+H83*(sofr+new_r_sp)+int_cal*Thesis!I42/Thesis!D42-H72*cash_y -> 375.28742 | J85: =I74*(IF(2032<=2028,swap_fix,sofr)+tlb_sp)+IF(2032=refi_yr,ssn_31*(ssn_r*7.5/12+(sofr+refi_sp)*(12-7.5)/12),I76*ssn_r+I77*(sofr+refi_sp))+I78*uns_r+I79*re_r+I80*bi_r+fleet*fleet_r+finls*finls_r+I82*fp_r+I83*(sofr+new_r_sp)+int_cal*Thesis!J42/Thesis!D42-I72*cash_y -> 404.77647 | K85: =J74*(IF(2033<=2028,swap_fix,sofr)+tlb_sp)+IF(2033=refi_yr,ssn_31*(ssn_r*7.5/12+(sofr+refi_sp)*(12-7.5)/12),J76*ssn_r+J77*(sofr+refi_sp))+J78*uns_r+J79*re_r+J80*bi_r+fleet*fleet_r+finls*finls_r+J82*fp_r+J83*(sofr+new_r_sp)+int_cal*Thesis!K42/Thesis!D42-J72*cash_y -> 433.59394 | L85: =K74*(IF(2034<=2028,swap_fix,sofr)+tlb_sp)+IF(2034=refi_yr,ssn_31*(ssn_r*7.5/12+(sofr+refi_sp)*(12-7.5)/12),K76*ssn_r+K77*(sofr+refi_sp))+K78*uns_r+K79*re_r+K80*bi_r+fleet*fleet_r+finls*finls_r+K82*fp_r+K83*(sofr+new_r_sp)+int_cal*Thesis!L42/Thesis!D42-K72*cash_y -> 365.27829 | M85: =L74*(IF(2035<=2028,swap_fix,sofr)+tlb_sp)+IF(2035=refi_yr,ssn_31*(ssn_r*7.5/12+(sofr+refi_sp)*(12-7.5)/12),L76*ssn_r+L77*(sofr+refi_sp))+L78*uns_r+L79*re_r+L80*bi_r+fleet*fleet_r+finls*finls_r+L82*fp_r+L83*(sofr+new_r_sp)+int_cal*Thesis!M42/Thesis!D42-L72*cash_y -> 390.5672
A88: 情境 C（信用壓力：2027 年次級車貸循環＋二手車價下跌）
A89: 項目 | B89: 單位 | C89: FY2025A | D89: FY2026E | E89: FY2027E | F89: FY2028E | G89: FY2029E | H89: FY2030E | I89: FY2031E | J89: FY2032E | K89: FY2033E | L89: FY2034E | M89: FY2035E
A90: 存貨（期末） | B90: US$M | C90: =d25_inv -> 2408 | D90: =inv_d*(PL!D67-PL!D74)/365 -> 3291.6805 | E90: =inv_d_C*(PL!E67-PL!E74)/365 -> 3620.5826 | F90: =inv_d_C28*(PL!F67-PL!F74)/365 -> 3589.6706 | G90: =inv_d*(PL!G67-PL!G74)/365 -> 3622.7515 | H90: =inv_d*(PL!H67-PL!H74)/365 -> 4053.5285 | I90: =inv_d*(PL!I67-PL!I74)/365 -> 4508.6521 | J90: =inv_d*(PL!J67-PL!J74)/365 -> 4959.32 | K90: =inv_d*(PL!K67-PL!K74)/365 -> 5393.9379 | L90: =inv_d*(PL!L67-PL!L74)/365 -> 5800.2059 | M90: =inv_d*(PL!M67-PL!M74)/365 -> 6165.645
A91: 待售貸款（期末） | B91: US$M | C91: =d25_frhfs -> 813 | D91: =fr_d*Thesis!D69/365 -> 853.59518 | E91: =fr_d*Thesis!E69/365 -> 783.60037 | F91: =fr_d*Thesis!F69/365 -> 839.236 | G91: =fr_d*Thesis!G69/365 -> 920.22227 | H91: =fr_d*Thesis!H69/365 -> 1032.4894 | I91: =fr_d*Thesis!I69/365 -> 1145.8154 | J91: =fr_d*Thesis!J69/365 -> 1257.5553 | K91: =fr_d*Thesis!K69/365 -> 1364.7997 | ... M91: =fr_d*Thesis!M69/365 -> 1553.5253
A92: 應付與應計（期末） | B92: US$M | C92: 1100 | D92: =ap_pct*(PL!D72-PL!D77+PL!D78) -> 1484.3142 | E92: =ap_pct*(PL!E72-PL!E77+PL!E78) -> 1395.8789 | F92: =ap_pct*(PL!F72-PL!F77+PL!F78) -> 1487.4799 | G92: =ap_pct*(PL!G72-PL!G77+PL!G78) -> 1622.1667 | H92: =ap_pct*(PL!H72-PL!H77+PL!H78) -> 1809.6405 | I92: =ap_pct*(PL!I72-PL!I77+PL!I78) -> 2006.0606 | J92: =ap_pct*(PL!J72-PL!J77+PL!J78) -> 2199.9907 | K92: =ap_pct*(PL!K72-PL!K77+PL!K78) -> 2386.4305 | ... M92: =ap_pct*(PL!M72-PL!M77+PL!M78) -> 2715.6924
A93: 證券化受益權（期末，隨發放量縮放） | B93: US$M | C93: =d25_bi -> 486 | D93: =lq_bi*Thesis!D69/Thesis!D69 -> 557 | E93: =lq_bi*Thesis!E69/Thesis!D69 -> 511.326 | F93: =lq_bi*Thesis!F69/Thesis!D69 -> 547.63015 | G93: =lq_bi*Thesis!G69/Thesis!D69 -> 600.47646 | H93: =lq_bi*Thesis!H69/Thesis!D69 -> 673.73458 | I93: =lq_bi*Thesis!I69/Thesis!D69 -> 747.68369 | J93: =lq_bi*Thesis!J69/Thesis!D69 -> 820.5978 | K93: =lq_bi*Thesis!K69/Thesis!D69 -> 890.57838 | L93: =lq_bi*Thesis!L69/Thesis!D69 -> 955.62623 | M93: =lq_bi*Thesis!M69/Thesis!D69 -> 1013.7283
A94: 淨利 | B94: US$M | D94: =PL!D85 -> 1879.6297 | E94: =PL!E85 -> 599.36724 | F94: =PL!F85 -> 909.10955 | G94: =PL!G85 -> 1296.2647 | H94: =PL!H85 -> 1753.3392 | I94: =PL!I85 -> 1983.2141 | J94: =PL!J85 -> 2201.2859 | K94: =PL!K85 -> 2402.0947 | ... M94: =PL!M85 -> 2804.4952
A95: ＋折舊攤銷＋SBC | B95: US$M | D95: =PL!D88+PL!D89 -> 369 | E95: =PL!E88+PL!E89 -> 380.07 | F95: =PL!F88+PL!F89 -> 391.4721 | G95: =PL!G88+PL!G89 -> 403.21626 | H95: =PL!H88+PL!H89 -> 415.31275 | I95: =PL!I88+PL!I89 -> 427.77213 | J95: =PL!J88+PL!J89 -> 440.6053 | K95: =PL!K88+PL!K89 -> 453.82346 | ... M95: =PL!M88+PL!M89 -> 481.4613
A96: ＋帳面稅與現金稅差額（遞延所得稅資產抵用） | B96: US$M | D96: =PL!D84-MAX(0,PL!D83)*ctr -> 166.148 | E96: =PL!E84-MAX(0,PL!E83)*ctr -> 61.298922 | F96: =PL!F84-MAX(0,PL!F83)*ctr -> 116.28145 | G96: =0 -> 0 | H96: =0 -> 0 | I96: =0 -> 0 | J96: =0 -> 0 | K96: =0 -> 0 | L96: =0 -> 0 | M96: =0 -> 0
A97: −營運資金增加（存貨＋待售貸款 − 應付） | B97: US$M | D97: =-((D90-C90)+(D91-C91)-(D92-C92)) -> -539.96143 | E97: =-((E90-D90)+(E91-D91)-(E92-D92)) -> -347.34273 | F97: =-((F90-E90)+(F91-E91)-(F92-E92)) -> 66.877461 | G97: =-((G90-F90)+(G91-F91)-(G92-F92)) -> 20.619647 | H97: =-((H90-G90)+(H91-G91)-(H92-G92)) -> -355.57041 | I97: =-((I90-H90)+(I91-H91)-(I92-H92)) -> -372.02944 | J97: =-((J90-I90)+(J91-I91)-(J92-I92)) -> -368.4777 | K97: =-((K90-J90)+(K91-J91)-(K92-J92)) -> -355.42243 | ... M97: =-((M90-L90)+(M91-L91)-(M92-L92)) -> -298.8923
A98: −風險自留淨現金（受益權增加 ×（1 − 融資成數）） | B98: US$M | D98: =-(D93-C93)*(1-bi_adv) -> -16.570916 | E98: =-(E93-D93)*(1-bi_adv) -> 10.66 | F98: =-(F93-E93)*(1-bi_adv) -> -8.47314 | G98: =-(G93-F93)*(1-bi_adv) -> -12.333968 | H98: =-(H93-G93)*(1-bi_adv) -> -17.097947 | I98: =-(I93-H93)*(1-bi_adv) -> -17.259217 | J98: =-(J93-I93)*(1-bi_adv) -> -17.017657 | K98: =-(K93-J93)*(1-bi_adv) -> -16.33299 | ... M98: =-(M93-L93)*(1-bi_adv) -> -13.560628
A99: 營業現金流（模型口徑） | B99: US$M | D99: =D94+D95+D96+D97+D98 -> 1858.2454 | E99: =E94+E95+E96+E97+E98 -> 704.05343 | F99: =F94+F95+F96+F97+F98 -> 1475.2674 | G99: =G94+G95+G96+G97+G98 -> 1707.7666 | H99: =H94+H95+H96+H97+H98 -> 1795.9835 | I99: =I94+I95+I96+I97+I98 -> 2021.6975 | J99: =J94+J95+J96+J97+J98 -> 2256.3959 | K99: =K94+K95+K96+K97+K98 -> 2484.1627 | ... M99: =M94+M95+M96+M97+M98 -> 2973.5036
A100: 資本支出（維護＋成長） | B100: US$M | D100: =ytd_capex+capex_q4 -> 236 | E100: =PL!E72*mcx+Thesis!E82 -> 134.33061 | F100: =PL!F72*mcx+Thesis!F82 -> 144.62406 | G100: =PL!G72*mcx+Thesis!G82 -> 159.4108 | H100: =PL!H72*mcx+Thesis!H82 -> 179.79249 | I100: =PL!I72*mcx+Thesis!I82 -> 199.43177 | J100: =PL!J72*mcx+Thesis!J82 -> 218.77842 | K100: =PL!K72*mcx+Thesis!K82 -> 237.32737 | L100: =PL!L72*mcx+Thesis!L82 -> 254.54766 | M100: =PL!M72*mcx+Thesis!M82 -> 290.92982
A101: 自由現金流 | B101: US$M | D101: =D99-D100 -> 1622.2454 | E101: =E99-E100 -> 569.72282 | F101: =F99-F100 -> 1330.6434 | G101: =G99-G100 -> 1548.3558 | H101: =H99-H100 -> 1616.1911 | I101: =I99-I100 -> 1822.2658 | J101: =J99-J100 -> 2037.6175 | K101: =K99-K100 -> 2246.8353 | ... M101: =M99-M100 -> 2682.5738
A102: TRA 付款 | B102: US$M | D102: =37+tra_q4 -> 37 | E102: =MIN(tra_0-tra_q4,tra_0/tra_yrs) -> 142 | F102: =MIN(tra_0-tra_q4-SUM(E102:E102),tra_0/tra_yrs) -> 142 | G102: =MIN(tra_0-tra_q4-SUM(E102:F102),tra_0/tra_yrs) -> 142 | H102: =MIN(tra_0-tra_q4-SUM(E102:G102),tra_0/tra_yrs) -> 142 | I102: =MIN(tra_0-tra_q4-SUM(E102:H102),tra_0/tra_yrs) -> 142 | J102: =MIN(tra_0-tra_q4-SUM(E102:I102),tra_0/tra_yrs) -> 142 | K102: =MIN(tra_0-tra_q4-SUM(E102:J102),tra_0/tra_yrs) -> 142 | L102: =MIN(tra_0-tra_q4-SUM(E102:K102),tra_0/tra_yrs) -> 142 | M102: =MIN(tra_0-tra_q4-SUM(E102:L102),tra_0/tra_yrs) -> 142
A103: 代非控制權益繳稅 | B103: US$M | D103: =ncitax -> 8 | E103: =ncitax -> 8 | F103: =ncitax -> 8 | G103: =ncitax -> 8 | H103: =ncitax -> 8 | I103: =ncitax -> 8 | J103: =ncitax -> 8 | K103: =ncitax -> 8 | ... M103: =ncitax -> 8
A104: 排定到期本金（定期貸款攤還、無擔保票據） | B104: US$M | D104: =0 -> 0 | E104: =tlb*0.01+32 -> 48.6 | F104: =tlb*0.01+22 -> 38.6 | G104: =tlb*0.01+26 -> 42.6 | H104: =tlb*0.01+27 -> 43.6 | I104: =tlb*0.01 -> 16.6 | J104: =tlb*0.01 -> 16.6 | K104: =tlb-tlb*0.01*6 -> 1560.4 | L104: =0 -> 0 | M104: =0 -> 0
A105: 贖回溢價與費用 | B105: US$M | D105: =redeem_cost -> 50 | E105: =0 -> 0 | F105: =0 -> 0 | G105: =0 -> 0 | H105: =0 -> 0 | I105: =0 -> 0 | J105: =0 -> 0 | K105: =0 -> 0 | L105: =0 -> 0 | M105: =0 -> 0
A106: 收支關卡：自由現金流扣 TRA 與到期本金 | B106: US$M | D106: =D101-D102-D103-D104-D105 -> 1527.2454 | E106: =E101-E102-E103-E104-E105 -> 371.12282 | F106: =F101-F102-F103-F104-F105 -> 1142.0434 | G106: =G101-G102-G103-G104-G105 -> 1355.7558 | H106: =H101-H102-H103-H104-H105 -> 1422.5911 | I106: =I101-I102-I103-I104-I105 -> 1655.6658 | J106: =J101-J102-J103-J104-J105 -> 1871.0175 | K106: =K101-K102-K103-K104-K105 -> 536.43533 | ... M106: =M101-M102-M103-M104-M105 -> 2532.5738
A107: 期末現金（融資與分配前） | B107: US$M | D107: =C110+D106 -> 3854.2454 | E107: =D110+E106 -> 4225.3682 | F107: =E110+F106 -> 5367.4115 | G107: =F110+G106 -> 6355.7558 | H107: =G110+H106 -> 6422.5911 | I107: =H110+I106 -> 6655.6658 | J107: =I110+J106 -> 6871.0175 | K107: =J110+K106 -> 5536.4353 | ... M107: =L110+M106 -> 7532.5738
...

Sheet Credit
A1: Credit — 信用風險六個角度：(1) 公司債信指標（三情境逐年）(2) 消費信用（管理組合）(3) 出售利得對損失與利差的敏感度 (4) 貸款去化與資金斷點 (5) 盈餘品質與關係人 (6) 清償順位與資產覆蓋；另附壓力格
A2: 評等門檻為 Moody's（2025-10）與 S&P（2025-03）公開說法；2026 年評等動作未找到。所有比率以調整後 EBITDA（公司口徑）計，另列扣除貸款出售利得的版本
A3: 項目 | B3: 單位 | C3: FY2025A | D3: FY2026E | E3: FY2027E | F3: FY2028E | G3: FY2029E | H3: FY2030E | I3: FY2031E | J3: FY2032E | K3: FY2033E | L3: FY2034E | M3: FY2035E
A5: (1) 公司債信指標｜情境 A（樂觀：沿公司 300 萬台路徑、利得率維持）
A6: 債務合計 | B6: US$M | D6: =CF!D46 -> 5275.6242 | E6: =CF!E46 -> 5397.5154 | F6: =CF!F46 -> 5562.3564 | G6: =CF!G46 -> 5749.9794 | H6: =CF!H46 -> 5952.7857 | I6: =CF!I46 -> 6205.1859 | J6: =CF!J46 -> 6471.8342 | K6: =CF!K46 -> 5083.9423 | ... M6: =CF!M46 -> 5169.0824
A7: 現金 | B7: US$M | D7: =CF!D34 -> 3854.2454 | E7: =CF!E34 -> 5000 | F7: =CF!F34 -> 5000 | G7: =CF!G34 -> 5000 | H7: =CF!H34 -> 5000 | I7: =CF!I34 -> 5000 | J7: =CF!J34 -> 5000 | K7: =CF!K34 -> 5000 | ... M7: =CF!M34 -> 5000
A8: TRA 餘額（期末） | B8: US$M | D8: =tra_0-tra_q4 -> 2130 | E8: =tra_0-tra_q4-SUM(CF!E26:E26) -> 1988 | F8: =tra_0-tra_q4-SUM(CF!E26:F26) -> 1846 | G8: =tra_0-tra_q4-SUM(CF!E26:G26) -> 1704 | H8: =tra_0-tra_q4-SUM(CF!E26:H26) -> 1562 | I8: =tra_0-tra_q4-SUM(CF!E26:I26) -> 1420 | J8: =tra_0-tra_q4-SUM(CF!E26:J26) -> 1278 | K8: =tra_0-tra_q4-SUM(CF!E26:K26) -> 1136 | L8: =tra_0-tra_q4-SUM(CF!E26:L26) -> 994 | M8: =tra_0-tra_q4-SUM(CF!E26:M26) -> 852
A9: 調整後 EBITDA | B9: US$M | D9: =PL!D33 -> 2952.2071 | E9: =PL!E33 -> 4515.9715 | F9: =PL!F33 -> 6085.4188 | G9: =PL!G33 -> 7896.5105 | H9: =PL!H33 -> 9860.7406 | I9: =PL!I33 -> 11942.436 | J9: =PL!J33 -> 14133.554 | K9: =PL!K33 -> 15468.541 | ... M9: =PL!M33 -> 16109.618
A10: 調整後 EBITDA 扣除貸款出售利得 | B10: US$M | D10: =D9-Thesis!D17 -> 1479.5871 | E10: =E9-Thesis!E17 -> 2418.5345 | F10: =F9-Thesis!F17 -> 3347.0051 | G10: =G9-Thesis!G17 -> 4432.9648 | H10: =H9-Thesis!H17 -> 5621.3607 | I10: =I9-Thesis!I17 -> 6857.2154 | J10: =J9-Thesis!J17 -> 8158.2162 | K10: =K9-Thesis!K17 -> 8952.3073 | ... M10: =M9-Thesis!M17 -> 9330.1286
A11: 債務／EBITDA | B11: x | D11: =D6/D9 -> 1.7870102 | E11: =E6/E9 -> 1.1952058 | F11: =F6/F9 -> 0.9140466 | G11: =G6/G9 -> 0.72816712 | H11: =H6/H9 -> 0.60368546 | I11: =I6/I9 -> 0.51959128 | J11: =J6/J9 -> 0.45790564 | K11: =K6/K9 -> 0.32866333 | ... M11: =M6/M9 -> 0.32086933
A12: 淨債務／EBITDA | B12: x | D12: =(D6-D7)/D9 -> 0.48146313 | E12: =(E6-E7)/E9 -> 0.088024328 | F12: =(F6-F7)/F9 -> 0.092410463 | G12: =(G6-G7)/G9 -> 0.094976049 | H12: =(H6-H7)/H9 -> 0.096624155 | I12: =(I6-I7)/I9 -> 0.10091625 | J12: =(J6-J7)/J9 -> 0.10413759 | K12: =(K6-K7)/K9 -> 0.0054266476 | ... M12: =(M6-M7)/M9 -> 0.010495743
A13: 債務／扣除出售利得的 EBITDA | B13: x | D13: =IF(D10>0,D6/D10,"EBITDA≤0") -> 3.5656058 | E13: =IF(E10>0,E6/E10,"EBITDA≤0") -> 2.2317297 | F13: =IF(F10>0,F6/F10,"EBITDA≤0") -> 1.6618906 | G13: =IF(G10>0,G6/G10,"EBITDA≤0") -> 1.2970956 | H13: =IF(H10>0,H6/H10,"EBITDA≤0") -> 1.0589582 | I13: =IF(I10>0,I6/I10,"EBITDA≤0") -> 0.90491336 | J13: =IF(J10>0,J6/J10,"EBITDA≤0") -> 0.79329035 | K13: =IF(K10>0,K6/K10,"EBITDA≤0") -> 0.56789185 | ... M13: =IF(M10>0,M6/M10,"EBITDA≤0") -> 0.55402049
A14: （債務＋TRA）／EBITDA | B14: x | D14: =(D6+D8)/D9 -> 2.5085043 | E14: =(E6+E8)/E9 -> 1.6354212 | F14: =(F6+F8)/F9 -> 1.2173947 | G14: =(G6+G8)/G9 -> 0.94395864 | H14: =(H6+H8)/H9 -> 0.76209141 | I14: =(I6+I8)/I9 -> 0.63849499 | J14: =(J6+J8)/J9 -> 0.54832875 | K14: =(K6+K8)/K9 -> 0.40210271 | ... M14: =(M6+M8)/M9 -> 0.37375699
A15: （EBITDA − 資本支出）／利息（利息為淨收入時標示） | B15: x | D15: =IF(CF!D47<=0,"淨利息收入",(D9-CF!D24)/CF!D47) -> 6.9573572 | E15: =IF(CF!E47<=0,"淨利息收入",(E9-CF!E24)/CF!E47) -> 11.553451 | F15: =IF(CF!F47<=0,"淨利息收入",(F9-CF!F24)/CF!F47) -> 16.232917 | G15: =IF(CF!G47<=0,"淨利息收入",(G9-CF!G24)/CF!G47) -> 20.699543 | H15: =IF(CF!H47<=0,"淨利息收入",(H9-CF!H24)/CF!H47) -> 22.879399 | I15: =IF(CF!I47<=0,"淨利息收入",(I9-CF!I24)/CF!I47) -> 24.6273 | J15: =IF(CF!J47<=0,"淨利息收入",(J9-CF!J24)/CF!J47) -> 26.198734 | K15: =IF(CF!K47<=0,"淨利息收入",(K9-CF!K24)/CF!K47) -> 26.741047 | ... M15: =IF(CF!M47<=0,"淨利息收入",(M9-CF!M24)/CF!M47) -> 31.876143
A16: 自由現金流／債務 | B16: % | D16: =CF!D25/D6 -> 0.30749828 | E16: =CF!E25/E6 -> 0.52169993 | F16: =CF!F25/F6 -> 0.70656825 | G16: =CF!G25/G6 -> 0.78493957 | H16: =CF!H25/H6 -> 0.96744887 | I16: =CF!I25/I6 -> 1.16013 | J16: =CF!J25/J6 -> 1.3753412 | K16: =CF!K25/K6 -> 2.1011436 | ... M16: =CF!M25/M6 -> 2.3201293
A17: Moody's 升評門檻（兩項皆符合） | B17: — | D17: =IF(AND(D11<moody_lev,OR(CF!D47<=0,(D9-CF!D24)/CF!D47>moody_cov)),"符合","未符合") -> 符合 | E17: =IF(AND(E11<moody_lev,OR(CF!E47<=0,(E9-CF!E24)/CF!E47>moody_cov)),"符合","未符合") -> 符合 | F17: =IF(AND(F11<moody_lev,OR(CF!F47<=0,(F9-CF!F24)/CF!F47>moody_cov)),"符合","未符合") -> 符合 | G17: =IF(AND(G11<moody_lev,OR(CF!G47<=0,(G9-CF!G24)/CF!G47>moody_cov)),"符合","未符合") -> 符合 | H17: =IF(AND(H11<moody_lev,OR(CF!H47<=0,(H9-CF!H24)/CF!H47>moody_cov)),"符合","未符合") -> 符合 | I17: =IF(AND(I11<moody_lev,OR(CF!I47<=0,(I9-CF!I24)/CF!I47>moody_cov)),"符合","未符合") -> 符合 | J17: =IF(AND(J11<moody_lev,OR(CF!J47<=0,(J9-CF!J24)/CF!J47>moody_cov)),"符合","未符合") -> 符合 | K17: =IF(AND(K11<moody_lev,OR(CF!K47<=0,(K9-CF!K24)/CF!K47>moody_cov)),"符合","未符合") -> 符合 | ... M17: =IF(AND(M11<moody_lev,OR(CF!M47<=0,(M9-CF!M24)/CF!M47>moody_cov)),"符合","未符合") -> 符合
A18: S&P 正向門檻（兩項皆符合） | B18: — | D18: =IF(AND(D11<sp_lev,D16>sp_focf),"符合","未符合") -> 符合 | E18: =IF(AND(E11<sp_lev,E16>sp_focf),"符合","未符合") -> 符合 | F18: =IF(AND(F11<sp_lev,F16>sp_focf),"符合","未符合") -> 符合 | G18: =IF(AND(G11<sp_lev,G16>sp_focf),"符合","未符合") -> 符合 | H18: =IF(AND(H11<sp_lev,H16>sp_focf),"符合","未符合") -> 符合 | I18: =IF(AND(I11<sp_lev,I16>sp_focf),"符合","未符合") -> 符合 | J18: =IF(AND(J11<sp_lev,J16>sp_focf),"符合","未符合") -> 符合 | K18: =IF(AND(K11<sp_lev,K16>sp_focf),"符合","未符合") -> 符合 | ... M18: =IF(AND(M11<sp_lev,M16>sp_focf),"符合","未符合") -> 符合
A19: 已承諾貸款去化 ÷ 貸款發放（Ally＋整批出售，每 12 個月） | B19: % | D19: =(ally_cap+fp_unused/fp_yrs)/Thesis!D15 -> 0.7518241 | E19: =(ally_cap+fp_unused/fp_yrs)/Thesis!E15 -> 0.55839579
A20: 已承諾＋證券化年化量 ÷ 貸款發放 | B20: % | D20: =(ally_cap+fp_unused/fp_yrs+abs_rr)/Thesis!D15 -> 1.005171 | E20: =(ally_cap+fp_unused/fp_yrs+abs_rr)/Thesis!E15 -> 0.74656195
A21: 股權緩衝：現價市值 ÷ 債務（2026 年；市場給債權人的保護） | B21: x | D21: =px*sh_fx/D6 -> 13.6698
A23: (1) 公司債信指標｜情境 B（基準：成長放緩、利得率小降）
A24: 債務合計 | B24: US$M | D24: =CF!D84 -> 5275.6242 | E24: =CF!E84 -> 5362.7657 | F24: =CF!F84 -> 5465.7947 | G24: =CF!G84 -> 5569.0556 | H24: =CF!H84 -> 5666.0753 | I24: =CF!I84 -> 5794.1343 | J24: =CF!J84 -> 5922.3126 | K24: =CF!K84 -> 4502.0974 | ... M24: =CF!M84 -> 4748.0202
A25: 現金 | B25: US$M | D25: =CF!D72 -> 3854.2454 | E25: =CF!E72 -> 5000 | F25: =CF!F72 -> 5000 | G25: =CF!G72 -> 5000 | H25: =CF!H72 -> 5000 | I25: =CF!I72 -> 5000 | J25: =CF!J72 -> 5000 | K25: =CF!K72 -> 5000 | ... M25: =CF!M72 -> 5000
A26: TRA 餘額（期末） | B26: US$M | D26: =tra_0-tra_q4 -> 2130 | E26: =tra_0-tra_q4-SUM(CF!E64:E64) -> 1988 | F26: =tra_0-tra_q4-SUM(CF!E64:F64) -> 1846 | G26: =tra_0-tra_q4-SUM(CF!E64:G64) -> 1704 | H26: =tra_0-tra_q4-SUM(CF!E64:H64) -> 1562 | I26: =tra_0-tra_q4-SUM(CF!E64:I64) -> 1420 | J26: =tra_0-tra_q4-SUM(CF!E64:J64) -> 1278 | K26: =tra_0-tra_q4-SUM(CF!E64:K64) -> 1136 | L26: =tra_0-tra_q4-SUM(CF!E64:L64) -> 994 | M26: =tra_0-tra_q4-SUM(CF!E64:M64) -> 852
A27: 調整後 EBITDA | B27: US$M | D27: =PL!D62 -> 2952.2071 | E27: =PL!E62 -> 3862.0458 | F27: =PL!F62 -> 4725.6852 | G27: =PL!G62 -> 5598.2895 | H27: =PL!H62 -> 6411.5754 | I27: =PL!I62 -> 7317.6951 | J27: =PL!J62 -> 8217.4755 | K27: =PL!K62 -> 9080.0839 | ... M27: =PL!M62 -> 10561.12
A28: 調整後 EBITDA 扣除貸款出售利得 | B28: US$M | D28: =D27-Thesis!D44 -> 1479.5871 | E28: =E27-Thesis!E44 -> 2074.4575 | F28: =F27-Thesis!F44 -> 2557.9364 | G28: =G27-Thesis!G44 -> 3046.4278 | H28: =H27-Thesis!H44 -> 3498.0475 | I28: =I27-Thesis!I44 -> 4007.1116 | J28: =J27-Thesis!J44 -> 4509.7544 | K28: =K27-Thesis!K44 -> 4988.0946 | ... M28: =M27-Thesis!M44 -> 5795.9178
A29: 債務／EBITDA | B29: x | D29: =D24/D27 -> 1.7870102 | E29: =E24/E27 -> 1.3885816 | F29: =F24/F27 -> 1.1566142 | G29: =G24/G27 -> 0.99477806 | H29: =H24/H27 -> 0.8837259 | I29: =I24/I27 -> 0.79179772 | J29: =J24/J27 -> 0.72069732 | K29: =K24/K27 -> 0.49582112 | ... M29: =M24/M27 -> 0.44957544
A30: 淨債務／EBITDA | B30: x | D30: =(D24-D25)/D27 -> 0.48146313 | E30: =(E24-E25)/E27 -> 0.093930978 | F30: =(F24-F25)/F27 -> 0.098566602 | G30: =(G24-G25)/G27 -> 0.10164812 | H30: =(H24-H25)/H27 -> 0.10388637 | I30: =(I24-I25)/I27 -> 0.10852247 | J30: =(J24-J25)/J27 -> 0.11223795 | K30: =(K24-K25)/K27 -> -0.054834582 | ... M30: =(M24-M25)/M27 -> -0.023859192
A31: 債務／扣除出售利得的 EBITDA | B31: x | D31: =IF(D28>0,D24/D28,"EBITDA≤0") -> 3.5656058 | E31: =IF(E28>0,E24/E28,"EBITDA≤0") -> 2.5851413 | F31: =IF(F28>0,F24/F28,"EBITDA≤0") -> 2.1367985 | G31: =IF(G28>0,G24/G28,"EBITDA≤0") -> 1.8280609 | H31: =IF(H28>0,H24/H28,"EBITDA≤0") -> 1.6197823 | I31: =IF(I28>0,I24/I28,"EBITDA≤0") -> 1.4459628 | J31: =IF(J28>0,J24/J28,"EBITDA≤0") -> 1.3132229 | K31: =IF(K28>0,K24/K28,"EBITDA≤0") -> 0.90256857 | ... M31: =IF(M28>0,M24/M28,"EBITDA≤0") -> 0.81920075
A32: （債務＋TRA）／EBITDA | B32: x | D32: =(D24+D26)/D27 -> 2.5085043 | E32: =(E24+E26)/E27 -> 1.9033347 | F32: =(F24+F26)/F27 -> 1.5472454 | G32: =(G24+G26)/G27 -> 1.2991567 | H32: =(H24+H26)/H27 -> 1.1273478 | I32: =(I24+I26)/I27 -> 0.9858479 | J32: =(J24+J26)/J27 -> 0.87621954 | K32: =(K24+K26)/K27 -> 0.6209301 | ... M32: =(M24+M26)/M27 -> 0.5302487
A33: （EBITDA − 資本支出）／利息（利息為淨收入時標示） | B33: x | D33: =IF(CF!D85<=0,"淨利息收入",(D27-CF!D62)/CF!D85) -> 6.9573572 | E33: =IF(CF!E85<=0,"淨利息收入",(E27-CF!E62)/CF!E85) -> 10.167391 | F33: =IF(CF!F85<=0,"淨利息收入",(F27-CF!F62)/CF!F85) -> 13.358287 | G33: =IF(CF!G85<=0,"淨利息收入",(G27-CF!G62)/CF!G85) -> 16.182978 | H33: =IF(CF!H85<=0,"淨利息收入",(H27-CF!H62)/CF!H85) -> 17.135775 | I33: =IF(CF!I85<=0,"淨利息收入",(I27-CF!I62)/CF!I85) -> 18.197054 | J33: =IF(CF!J85<=0,"淨利息收入",(J27-CF!J62)/CF!J85) -> 19.012252 | K33: =IF(CF!K85<=0,"淨利息收入",(K27-CF!K62)/CF!K85) -> 19.675685 | ... M33: =IF(CF!M85<=0,"淨利息收入",(M27-CF!M62)/CF!M85) -> 25.486562
A34: 自由現金流／債務 | B34: % | D34: =CF!D63/D24 -> 0.30749828 | E34: =CF!E63/E24 -> 0.45999274 | F34: =CF!F63/F24 -> 0.57151672 | G34: =CF!G63/G24 -> 0.58403494 | H34: =CF!H63/H24 -> 0.66835448 | I34: =CF!I63/I24 -> 0.76810074 | J34: =CF!J63/J24 -> 0.86624359 | K34: =CF!K63/K24 -> 1.2913044 | ... M34: =CF!M63/M24 -> 1.505962
A35: Moody's 升評門檻（兩項皆符合） | B35: — | D35: =IF(AND(D29<moody_lev,OR(CF!D85<=0,(D27-CF!D62)/CF!D85>moody_cov)),"符合","未符合") -> 符合 | E35: =IF(AND(E29<moody_lev,OR(CF!E85<=0,(E27-CF!E62)/CF!E85>moody_cov)),"符合","未符合") -> 符合 | F35: =IF(AND(F29<moody_lev,OR(CF!F85<=0,(F27-CF!F62)/CF!F85>moody_cov)),"符合","未符合") -> 符合 | G35: =IF(AND(G29<moody_lev,OR(CF!G85<=0,(G27-CF!G62)/CF!G85>moody_cov)),"符合","未符合") -> 符合 | H35: =IF(AND(H29<moody_lev,OR(CF!H85<=0,(H27-CF!H62)/CF!H85>moody_cov)),"符合","未符合") -> 符合 | I35: =IF(AND(I29<moody_lev,OR(CF!I85<=0,(I27-CF!I62)/CF!I85>moody_cov)),"符合","未符合") -> 符合 | J35: =IF(AND(J29<moody_lev,OR(CF!J85<=0,(J27-CF!J62)/CF!J85>moody_cov)),"符合","未符合") -> 符合 | K35: =IF(AND(K29<moody_lev,OR(CF!K85<=0,(K27-CF!K62)/CF!K85>moody_cov)),"符合","未符合") -> 符合 | ... M35: =IF(AND(M29<moody_lev,OR(CF!M85<=0,(M27-CF!M62)/CF!M85>moody_cov)),"符合","未符合") -> 符合
A36: S&P 正向門檻（兩項皆符合） | B36: — | D36: =IF(AND(D29<sp_lev,D34>sp_focf),"符合","未符合") -> 符合 | E36: =IF(AND(E29<sp_lev,E34>sp_focf),"符合","未符合") -> 符合 | F36: =IF(AND(F29<sp_lev,F34>sp_focf),"符合","未符合") -> 符合 | G36: =IF(AND(G29<sp_lev,G34>sp_focf),"符合","未符合") -> 符合 | H36: =IF(AND(H29<sp_lev,H34>sp_focf),"符合","未符合") -> 符合 | I36: =IF(AND(I29<sp_lev,I34>sp_focf),"符合","未符合") -> 符合 | J36: =IF(AND(J29<sp_lev,J34>sp_focf),"符合","未符合") -> 符合 | K36: =IF(AND(K29<sp_lev,K34>sp_focf),"符合","未符合") -> 符合 | ... M36: =IF(AND(M29<sp_lev,M34>sp_focf),"符合","未符合") -> 符合
A37: 已承諾貸款去化 ÷ 貸款發放（Ally＋整批出售，每 12 個月） | B37: % | D37: =(ally_cap+fp_unused/fp_yrs)/Thesis!D42 -> 0.7518241 | E37: =(ally_cap+fp_unused/fp_yrs)/Thesis!E42 -> 0.58966596
A38: 已承諾＋證券化年化量 ÷ 貸款發放 | B38: % | D38: =(ally_cap+fp_unused/fp_yrs+abs_rr)/Thesis!D42 -> 1.005171 | E38: =(ally_cap+fp_unused/fp_yrs+abs_rr)/Thesis!E42 -> 0.78836942
A39: 股權緩衝：現價市值 ÷ 債務（2026 年；市場給債權人的保護） | B39: x | D39: =px*sh_fx/D24 -> 13.6698
A41: (1) 公司債信指標｜情境 C（信用壓力：2027 年次級車貸循環＋二手車價下跌）
A42: 債務合計 | B42: US$M | D42: =CF!D122 -> 5275.6242 | E42: =CF!E122 -> 5198.7672 | F42: =CF!F122 -> 5187.3631 | G42: =CF!G122 -> 5185.9551 | H42: =CF!H122 -> 5207.3651 | I42: =CF!I122 -> 5256.8051 | J42: =CF!J122 -> 5305.3601 | K42: =CF!K122 -> 3807.5364 | ... M42: =CF!M122 -> 3917.7979
A43: 現金 | B43: US$M | D43: =CF!D110 -> 3854.2454 | E43: =CF!E110 -> 4225.3682 | F43: =CF!F110 -> 5000 | G43: =CF!G110 -> 5000 | H43: =CF!H110 -> 5000 | I43: =CF!I110 -> 5000 | J43: =CF!J110 -> 5000 | K43: =CF!K110 -> 5000 | ... M43: =CF!M110 -> 5000
A44: TRA 餘額（期末） | B44: US$M | D44: =tra_0-tra_q4 -> 2130 | E44: =tra_0-tra_q4-SUM(CF!E102:E102) -> 1988 | F44: =tra_0-tra_q4-SUM(CF!E102:F102) -> 1846 | G44: =tra_0-tra_q4-SUM(CF!E102:G102) -> 1704 | H44: =tra_0-tra_q4-SUM(CF!E102:H102) -> 1562 | I44: =tra_0-tra_q4-SUM(CF!E102:I102) -> 1420 | J44: =tra_0-tra_q4-SUM(CF!E102:J102) -> 1278 | K44: =tra_0-tra_q4-SUM(CF!E102:K102) -> 1136 | L44: =tra_0-tra_q4-SUM(CF!E102:L102) -> 994 | M44: =tra_0-tra_q4-SUM(CF!E102:M102) -> 852
A45: 調整後 EBITDA | B45: US$M | D45: =PL!D91 -> 2952.2071 | E45: =PL!E91 -> 1375.5827 | F45: =PL!F91 -> 1749.3606 | G45: =PL!G91 -> 2224.2518 | H45: =PL!H91 -> 2840.9508 | I45: =PL!I91 -> 3143.856 | J45: =PL!J91 -> 3434.7202 | K45: =PL!K91 -> 3705.1411 | ... M45: =PL!M91 -> 4150.9577
A46: 調整後 EBITDA 扣除貸款出售利得 | B46: US$M | D46: =D45-Thesis!D71 -> 1479.5871 | E46: =E45-Thesis!E71 -> 767.80267 | F46: =F45-Thesis!F71 -> 932.50418 | G46: =G45-Thesis!G71 -> 1146.6332 | H46: =H45-Thesis!H71 -> 1427.7309 | I46: =I45-Thesis!I71 -> 1575.5212 | J46: =J45-Thesis!J71 -> 1713.4414 | K46: =K45-Thesis!K71 -> 1837.0715 | ... M46: =M45-Thesis!M71 -> 2024.5699
A47: 債務／EBITDA | B47: x | D47: =D42/D45 -> 1.7870102 | E47: =E42/E45 -> 3.7793199 | F47: =F42/F45 -> 2.965291 | G47: =G42/G45 -> 2.3315504 | H47: =H42/H45 -> 1.8329656 | I47: =I42/I45 -> 1.6720884 | J47: =J42/J45 -> 1.5446265 | K47: =K42/K45 -> 1.027636 | ... M47: =M42/M45 -> 0.94382989
A48: 淨債務／EBITDA | B48: x | D48: =(D42-D43)/D45 -> 0.48146313 | E48: =(E42-E43)/E45 -> 0.70762666 | F48: =(F42-F43)/F45 -> 0.10710378 | G48: =(G42-G43)/G45 -> 0.083603433 | H48: =(H42-H43)/H45 -> 0.072991459 | I48: =(I42-I43)/I45 -> 0.081684746 | J48: =(J42-J43)/J45 -> 0.088903908 | K48: =(K42-K43)/K45 -> -0.32184026 | ... M48: =(M42-M43)/M45 -> -0.26071142
A49: 債務／扣除出售利得的 EBITDA | B49: x | D49: =IF(D46>0,D42/D46,"EBITDA≤0") -> 3.5656058 | E49: =IF(E46>0,E42/E46,"EBITDA≤0") -> 6.7709678 | F49: =IF(F46>0,F42/F46,"EBITDA≤0") -> 5.562831 | G49: =IF(G46>0,G42/G46,"EBITDA≤0") -> 4.5227673 | H49: =IF(H46>0,H42/H46,"EBITDA≤0") -> 3.6473015 | I49: =IF(I46>0,I42/I46,"EBITDA≤0") -> 3.3365499 | J49: =IF(J46>0,J42/J46,"EBITDA≤0") -> 3.0963184 | K49: =IF(K46>0,K42/K46,"EBITDA≤0") -> 2.072612 | ... M49: =IF(M46>0,M42/M46,"EBITDA≤0") -> 1.935126
A50: （債務＋TRA）／EBITDA | B50: x | D50: =(D42+D44)/D45 -> 2.5085043 | E50: =(E42+E44)/E45 -> 5.2245257 | F50: =(F42+F44)/F45 -> 4.0205337 | G50: =(G42+G44)/G45 -> 3.0976507 | H50: =(H42+H44)/H45 -> 2.3827816 | I50: =(I42+I44)/I45 -> 2.123763 | J50: =(J42+J44)/J45 -> 1.9167092 | K50: =(K42+K44)/K45 -> 1.334237 | ... M50: =(M42+M44)/M45 -> 1.1490837
A51: （EBITDA − 資本支出）／利息（利息為淨收入時標示） | B51: x | D51: =IF(CF!D123<=0,"淨利息收入",(D45-CF!D100)/CF!D123) -> 6.9573572 | E51: =IF(CF!E123<=0,"淨利息收入",(E45-CF!E100)/CF!E123) -> 3.7006615 | F51: =IF(CF!F123<=0,"淨利息收入",(F45-CF!F100)/CF!F123) -> 4.9869939 | G51: =IF(CF!G123<=0,"淨利息收入",(G45-CF!G100)/CF!G123) -> 6.9089811 | H51: =IF(CF!H123<=0,"淨利息收入",(H45-CF!H100)/CF!H123) -> 8.6283708 | I51: =IF(CF!I123<=0,"淨利息收入",(I45-CF!I100)/CF!I123) -> 9.2437842 | J51: =IF(CF!J123<=0,"淨利息收入",(J45-CF!J100)/CF!J123) -> 9.7270062 | K51: =IF(CF!K123<=0,"淨利息收入",(K45-CF!K100)/CF!K123) -> 10.112194 | ... M51: =IF(CF!M123<=0,"淨利息收入",(M45-CF!M100)/CF!M123) -> 14.276294
A52: 自由現金流／債務 | B52: % | D52: =CF!D101/D42 -> 0.30749828 | E52: =CF!E101/E42 -> 0.10958806 | F52: =CF!F101/F42 -> 0.25651633 | G52: =CF!G101/G42 -> 0.29856715 | H52: =CF!H101/H42 -> 0.31036638 | I52: =CF!I101/I42 -> 0.34664891 | J52: =CF!J101/J42 -> 0.38406771 | K52: =CF!K101/K42 -> 0.59010212 | ... M52: =CF!M101/M42 -> 0.68471469
A53: Moody's 升評門檻（兩項皆符合） | B53: — | D53: =IF(AND(D47<moody_lev,OR(CF!D123<=0,(D45-CF!D100)/CF!D123>moody_cov)),"符合","未符合") -> 符合 | E53: =IF(AND(E47<moody_lev,OR(CF!E123<=0,(E45-CF!E100)/CF!E123>moody_cov)),"符合","未符合") -> 符合 | F53: =IF(AND(F47<moody_lev,OR(CF!F123<=0,(F45-CF!F100)/CF!F123>moody_cov)),"符合","未符合") -> 符合 | G53: =IF(AND(G47<moody_lev,OR(CF!G123<=0,(G45-CF!G100)/CF!G123>moody_cov)),"符合","未符合") -> 符合 | H53: =IF(AND(H47<moody_lev,OR(CF!H123<=0,(H45-CF!H100)/CF!H123>moody_cov)),"符合","未符合") -> 符合 | I53: =IF(AND(I47<moody_lev,OR(CF!I123<=0,(I45-CF!I100)/CF!I123>moody_cov)),"符合","未符合") -> 符合 | J53: =IF(AND(J47<moody_lev,OR(CF!J123<=0,(J45-CF!J100)/CF!J123>moody_cov)),"符合","未符合") -> 符合 | K53: =IF(AND(K47<moody_lev,OR(CF!K123<=0,(K45-CF!K100)/CF!K123>moody_cov)),"符合","未符合") -> 符合 | ... M53: =IF(AND(M47<moody_lev,OR(CF!M123<=0,(M45-CF!M100)/CF!M123>moody_cov)),"符合","未符合") -> 符合
A54: S&P 正向門檻（兩項皆符合） | B54: — | D54: =IF(AND(D47<sp_lev,D52>sp_focf),"符合","未符合") -> 符合 | E54: =IF(AND(E47<sp_lev,E52>sp_focf),"符合","未符合") -> 符合 | F54: =IF(AND(F47<sp_lev,F52>sp_focf),"符合","未符合") -> 符合 | G54: =IF(AND(G47<sp_lev,G52>sp_focf),"符合","未符合") -> 符合 | H54: =IF(AND(H47<sp_lev,H52>sp_focf),"符合","未符合") -> 符合 | I54: =IF(AND(I47<sp_lev,I52>sp_focf),"符合","未符合") -> 符合 | J54: =IF(AND(J47<sp_lev,J52>sp_focf),"符合","未符合") -> 符合 | K54: =IF(AND(K47<sp_lev,K52>sp_focf),"符合","未符合") -> 符合 | ... M54: =IF(AND(M47<sp_lev,M52>sp_focf),"符合","未符合") -> 符合
A55: 已承諾貸款去化 ÷ 貸款發放（Ally＋整批出售，每 12 個月） | B55: % | D55: =(ally_cap+fp_unused/fp_yrs)/Thesis!D69 -> 0.7518241 | E55: =(ally_cap+fp_unused/fp_yrs)/Thesis!E69 -> 0.8189805
A56: 已承諾＋證券化年化量 ÷ 貸款發放 | B56: % | D56: =(ally_cap+fp_unused/fp_yrs+abs_rr)/Thesis!D69 -> 1.005171 | E56: =(ally_cap+fp_unused/fp_yrs+abs_rr)/Thesis!E69 -> 1.0949575
A57: 股權緩衝：現價市值 ÷ 債務（2026 年；市場給債權人的保護） | B57: x | D57: =px*sh_fx/D42 -> 13.6698
A59: (2) 消費信用：Carvana 發放、Bridgecrest 服務的管理組合（含已出售）｜來源：Carvana Auto Receivables Trust 2026-P3 公開說明書 424B5（2026-08-20）Historical Performance（Bridgecrest 服務的管理組合）
A60: 項目 | B60: 單位 | C60: FY2021 | D60: FY2022 | E60: FY2023 | F60: FY2024 | G60: FY2025 | H60: 2025H1 | I60: 2026H1
A61: 期末本金餘額（全部借款人） | B61: US$M | C61: 9613 | D61: 12262.1 | E61: 13528.3 | F61: 16210.5 | G61: 21570.4 | H61: 18463.2 | I61: 25959.6
A62: 平均月底餘額（全部） | B62: US$M | C62: 7616.6 | D62: 11255.2 | E62: 12911.7 | F62: 14890.3 | G62: 18803 | H62: 17389.1 | I62: 23982.8
A63: 淨沖銷（全部） | B63: US$M | C63: 110.9 | D63: 278.5 | E63: 479.8 | F63: 668.4 | G63: 778 | H63: 364.6 | I63: 378.5
A64: 平均月底餘額（Prime：Deal Score ≥ 50） | B64: US$M | C64: 4200.1 | D64: 6851.7 | E64: 7725.2 | F64: 8498.6 | G64: 10449.6 | H64: 9620.3 | I64: 13661.6
A65: 淨沖銷（Prime） | B65: US$M | C65: 12.4 | D65: 38.5 | E65: 83.5 | F65: 133.1 | G65: 151.4 | H65: 74 | I65: 69.7
A66: 年化淨沖銷率（全部） | B66: % | C66: =C63*1/C62 -> 0.014560302 | D66: =D63*1/D62 -> 0.024744118 | E66: =E63*1/E62 -> 0.037160095 | F66: =F63*1/F62 -> 0.044888283 | G66: =G63*1/G62 -> 0.041376376 | H66: =H63*2/H62 -> 0.041934315 | I66: =I63*2/I62 -> 0.031564288
A67: 年化淨沖銷率（Prime） | B67: % | C67: =C65*1/C64 -> 0.0029523107 | D67: =D65*1/D64 -> 0.0056190434 | E67: =E65*1/E64 -> 0.010808782 | F67: =F65*1/F64 -> 0.015661403 | G67: =G65*1/G64 -> 0.014488593 | H67: =H65*2/H64 -> 0.015384136 | I67: =I65*2/I64 -> 0.010203783
A68: 年化淨沖銷率（非 Prime，推得＝全部 − Prime） | B68: % | C68: =(C63-C65)*1/(C62-C64) -> 0.028830675 | D68: =(D63-D65)*1/(D62-D64) -> 0.054502101 | E68: =(E63-E65)*1/(E62-E64) -> 0.07640991 | F68: =(F63-F65)*1/(F62-F64) -> 0.083749237 | G68: =(G63-G65)*1/(G62-G64) -> 0.075011373 | H68: =(H63-H65)*2/(H62-H64) -> 0.074812069 | I68: =(I63-I65)*2/(I62-I64) -> 0.059838003
A69: 落後 12 個月淨沖銷率（年化淨沖銷 ÷ 一年前餘額；排除快速成長的分母稀釋） | B69: % | D69: =D63/C61 -> 0.028971185 | E69: =E63/D61 -> 0.039128697 | F69: =F63/E61 -> 0.049407538 | G69: =G63/F61 -> 0.047993584 | I69: =I63*2/H61 -> 0.041000477
A70: 61 天以上逾期率（全部，期末） | B70: % | C70: 0.0176 | D70: 0.0239 | E70: 0.0373 | F70: 0.0406 | G70: 0.0376 | H70: 0.0385 | I70: 0.0322
A71: 管理組合餘額年增 | B71: % | D71: =D61/C61-1 -> 0.27557474 | E71: =E61/D61-1 -> 0.10326127 | F71: =F61/E61-1 -> 0.19826586 | G71: =G61/F61-1 -> 0.33064372 | I71: =I61/H61-1 -> 0.40601846
A72: 註：2025-12 起承銷不再使用 FICO（改用 VantageScore 與自有 CarvanaScore 第八代）；Prime 定義為自有 Deal Score ≥ 50，非 FICO 口徑（同一公開說明書）
A74: (3) 出售利得率的信用與利差傳導（情境 C 推導）
A75: 情境 B 2027 年利得率 | B75: % | C75: =gos27_B -> 0.072
A76: − 損失傳導：loss_pt × 終身損失增幅 | B76: pt | C76: =-loss_pt*dcnl_C -> -0.018
A77: − 利差傳導：存續期間 × 利差擴大 | B77: pt | C77: =-dur*dspr_C -> -0.02
A78: 情境 C 2027 年利得率 | B78: % | C78: =C75+C76+C77 -> 0.034
A79: 利得率每降 1 pt，2027 年調整後 EBITDA 減少（情境 B 發放量） | B79: US$M | C79: =Thesis!E42*0.01 -> 248.27616
A80: 占情境 B 2027 年調整後 EBITDA | B80: % | C80: =C79/PL!E62 -> 0.064286177
A82: (4) 貸款去化與資金斷點（2026-09-30 起算；若買方與 ABS 市場停止承接，放款先停在倉儲額度、再用現金）
A83: 每月貸款發放（Q3 2026 ÷ 3） | B83: US$M | C83: =lq_orig/3 -> 1727.3333
A84: 每月營運現金（扣除出售利得；Q3 調整後 EBITDA − 利得 − 利息 − 資本支出，÷ 3） | B84: US$M | C84: =(lq_ebitda-lq_gos-lq_int-lq_capex)/3 -> 85.666667
A85: 可動用現金（現金 − 最低營運現金） | B85: US$M | C85: =lq_cash-min_cash -> 2049
A86: 倉儲額度可容納的貸款（未用額度 ÷ 墊款成數） | B86: US$M | C86: =wh_unused/wh_adv -> 4823.5294
A87: 情境 | C87: 全部停止 | D87: Ally 照常承購
A88: 每月須自行持有的新貸款 | B88: US$M | C88: =C83 -> 1727.3333 | D88: =MAX(0,C83-ally_cap/12) -> 1060.6667
A89: 倉儲額度用盡月數 | B89: 月 | C89: =IF(C88>0,C86/C88,99) -> 2.7924717 | D89: =IF(D88>0,C86/D88,99) -> 4.5476393
A90: 倉儲期間每月現金消耗（自備款 − 營運現金） | B90: US$M | C90: =C88*(1-wh_adv)-C84 -> 173.43333 | D90: =D88*(1-wh_adv)-C84 -> 73.433333
A91: 倉儲用盡後每月現金消耗 | B91: US$M | C91: =C88-C84 -> 1641.6667 | D91: =D88-C84 -> 975
A92: 資金斷點：可撐月數（不減少放款） | B92: 月 | C92: =IF(C90<=0,IF(C91<=0,99,C89+C85/C91),IF(C85<=C89*C90,C85/C90,C89+(C85-C89*C90)/C91)) -> 3.7455838 | D92: =IF(D90<=0,IF(D91<=0,99,D89+C85/D91),IF(C85<=D89*D90,C85/D90,D89+(C85-D89*D90)/D91)) -> 6.3066667
A93: 讀法：撐不過即須減少自營放款（改由第三方放款或現金買車），零售台數與其他毛利同步下降；倉儲額度到期日分布 2026-10 至 2027-11（10-Q 附註 9），續約本身亦受信用循環影響
A95: (5) 盈餘品質與關係人（季度；Q 頁）
A96: 項目 | B96: 單位 | C96: Q4'24 | D96: Q1'25 | E96: Q2'25 | F96: Q3'25 | G96: Q4'25 | H96: Q1'26 | I96: Q2'26 | J96: Q3'26 | K96: FY2025 | L96: TTM
A97: 出售利得 ÷ 調整後 EBITDA | B97: % | C97: =Q!C45 -> 0.59610028 | D97: =Q!D45 -> 0.55942623 | E97: =Q!E45 -> 0.45590682 | F97: =Q!F45 -> 0.51962323 | G97: =Q!G45 -> 0.61643836 | H97: =Q!H45 -> 0.52678571 | I97: =Q!I45 -> 0.45383615 | J97: =Q!J45 -> 0.47625 | K97: =Q!M45 -> 0.53330353
A98: （出售利得＋關係人其他營收）÷ 調整後 EBITDA | B98: % | C98: =Q!C46 -> 0.76044568 | D98: =Q!D46 -> 0.70696721 | E98: =Q!E46 -> 0.59400998 | F98: =Q!F46 -> 0.66562009 | G98: =Q!G46 -> 0.81017613 | H98: =Q!H46 -> 0.69642857 | I98: =Q!I46 -> 0.60598179 | J98: =Q!J46 -> 0.6375 | K98: =Q!M46 -> 0.68842199 | L98: =ttm_gosrp -> 0.67514535
A99: 調整後 EBITDA 扣除出售利得 | B99: US$M | C99: =Q!C47 -> 145 | D99: =Q!D47 -> 215 | E99: =Q!E47 -> 327 | F99: =Q!F47 -> 306 | G99: =Q!G47 -> 196 | H99: =Q!H47 -> 318 | I99: =Q!I47 -> 420 | J99: =Q!J47 -> 419 | K99: =Q!M47 -> 1044
A100: 扣除出售利得的 EBITDA 率 | B100: % | C100: =Q!C48 -> 0.040879617 | D100: =Q!D48 -> 0.050803403 | E100: =Q!E48 -> 0.067561983 | F100: =Q!F48 -> 0.054188064 | G100: =Q!G48 -> 0.03498126 | H100: =Q!H48 -> 0.049440299 | I100: =Q!I48 -> 0.056941432 | J100: =Q!J48 -> 0.052114428 | K100: =Q!M48 -> 0.051372896
A101: 出售利得率 | B101: % | C101: =Q!C39 -> 0.093942054 | D101: =Q!D39 -> 0.10263158 | E101: =Q!E39 -> 0.088788075 | F101: =Q!F39 -> 0.096389051 | G101: =Q!G39 -> 0.086848635 | H101: =Q!H39 -> 0.083215797 | I101: =Q!I39 -> 0.073458219 | J101: =Q!J39 -> 0.073523736 | K101: =Q!M39 -> 0.093152182
A102: 對照：Gotham City Research（放空方）稱 2025 年前三季此比例約 75% | B102: % | K102: 0.75
A103: 債務／扣除出售利得的 EBITDA（TTM，2026-09-30） | B103: x | L103: =ttm_lev_xg -> 3.8640059
A104: 關係人：VSC 由 DriveTime（Garcia 家族控制）承保與管理；Bridgecrest（同一家族）服務 Carvana 發放的貸款；TRA 負債 2,130 中 1,645 應付關係人（10-Q 附註 6）。2025-01 Hindenburg、2026-01 Gotham 指控未揭露關係人交易，公司否認；2025 年 10-K 如期申報、會計師 Grant Thornton 未更換
A106: (6) 清償順位與資產覆蓋（2026-09-30；折扣率為判斷）
A107: 資產 | B107: 單位 | C107: 帳面 | D107: 回收折扣後比例 | E107: 可回收
A108: 現金 | B108: US$M | C108: =lq_cash -> 3049 | D108: 1 | E108: =C108*D108 -> 3049
...

Sheet Val
A1: Val — 估值。DCF：FY2027–FY2035 無槓桿自由現金流＋永續價值（以 2026 年底為基準點折現）；倍數法：2027 年調整後 EBITDA × 同業中位數 × 成長溢價。股權＝EV − 淨債務（2026-09-30）− TRA 負債
A3: 項目 | B3: 單位 | C3: 值 | E3: 說明
A5: 股權成本 ke（CAPM：rf＋β × ERP） | B5: % | C5: =rf+beta*erp -> 0.185425 | E5: β 為 Blume 調整
A6: 股權市值（現價 × 完全轉換股數） | B6: US$M | C6: =px*sh_fx -> 72116.73
A7: 債務（2026-09-30，含融資租賃） | B7: US$M | C7: =lq_debt_bs -> 5228
A8: WACC | B8: % | C8: =C5*C6/(C6+C7)+kd*(1-t_val)*C7/(C6+C7) -> 0.17705715 | E8: 市值權重
A9: 淨債務（2026-09-30） | B9: US$M | C9: =lq_debt_bs-lq_cash -> 2179
A10: TRA 負債（視同債務） | B10: US$M | C10: =tra_0 -> 2130 | E10: 遞延所得稅資產的價值已反映在現金稅率，不另加
A11: 同業 EV/EBITDA 中位數（LAD、AN） | B11: x | C11: =MEDIAN(peer_lad,peer_an) -> 11.38
A12: 適用倍數（中位數 × 成長溢價） | B12: x | C12: =C11*prem -> 17.07
A13: 市場隱含 EV（股權市值＋淨債務＋TRA） | B13: US$M | C13: =C6+C9+C10 -> 76425.73
A14: 市場隱含 EV ÷ 近四季調整後 EBITDA | B14: x | C14: =C13/ttm_ebitda -> 27.770977
A16: DCF（各情境） | B16: 單位 | C16: FY2027E | D16: FY2028E | E16: FY2029E | F16: FY2030E | G16: FY2031E | H16: FY2032E | I16: FY2033E | J16: FY2034E | K16: FY2035E
A17: 情境 A（樂觀：沿公司 300 萬台路徑、利得率維持）
A18: 營業利益 | B18: US$M | C18: =PL!E21 -> 4156.9015 | D18: =PL!F21 -> 5709.443 | E18: =PL!G21 -> 7493.0697 | F18: =PL!H21 -> 9428.9584 | G18: =PL!I21 -> 11481.04 | H18: =PL!J21 -> 13641.902 | I18: =PL!K21 -> 14954.541 | J18: =PL!L21 -> 15263.388 | K18: =PL!M21 -> 15567.981
A19: − 營業利益的現金稅（2027–2028 用 ctr，之後用有效稅率） | B19: US$M | C19: =-MAX(0,PL!E21)*ctr -> -124.70704 | D19: =-MAX(0,PL!F21)*ctr -> -171.28329 | E19: =-MAX(0,PL!G21)*(etr_27+(etr_30-etr_27)*2/3) -> -1198.8912 | F19: =-MAX(0,PL!H21)*etr_30 -> -1697.2125 | G19: =-MAX(0,PL!I21)*etr_30 -> -2066.5872 | H19: =-MAX(0,PL!J21)*etr_30 -> -2455.5424 | I19: =-MAX(0,PL!K21)*etr_30 -> -2691.8174 | J19: =-MAX(0,PL!L21)*etr_30 -> -2747.4099 | K19: =-MAX(0,PL!M21)*etr_30 -> -2802.2365
A20: ＋折舊攤銷＋SBC | B20: US$M | C20: =CF!E19 -> 380.07 | D20: =CF!F19 -> 396.97576 | E20: =CF!G19 -> 424.4408 | F20: =CF!H19 -> 452.7822 | G20: =CF!I19 -> 482.3962 | H20: =CF!J19 -> 512.65223 | I20: =CF!K19 -> 534.99993 | J20: =CF!L19 -> 548.61463 | K20: =CF!M19 -> 562.63778
A21: − 資本支出 | B21: US$M | C21: =-CF!E24 -> -285.60327 | D21: =-CF!F24 -> -500.78145 | E21: =-CF!G24 -> -578.64222 | F21: =-CF!H24 -> -667.12499 | G21: =-CF!I24 -> -752.68256 | H21: =-CF!J24 -> -714.02148 | I21: =-CF!K24 -> -629.03252 | J21: =-CF!L24 -> -641.32941 | K21: =-CF!M24 -> -653.87223
A22: − 營運資金與風險自留 | B22: US$M | C22: =CF!E21+CF!E22 -> -955.60624 | D22: =CF!F21+CF!F22 -> -1170.4589 | E22: =CF!G21+CF!G22 -> -1329.6273 | F22: =CF!H21+CF!H22 -> -1428.8872 | G22: =CF!I21+CF!I22 -> -1572.7658 | H22: =CF!J21+CF!J22 -> -1663.9893 | I22: =CF!K21+CF!K22 -> -1031.5528 | J22: =CF!L21+CF!L22 -> -278.96165 | K22: =CF!M21+CF!M22 -> -283.97758
A23: 無槓桿自由現金流 | B23: US$M | C23: =SUM(C18:C22) -> 3171.0549 | D23: =SUM(D18:D22) -> 4263.8951 | E23: =SUM(E18:E22) -> 4810.3499 | F23: =SUM(F18:F22) -> 6088.5159 | G23: =SUM(G18:G22) -> 7571.4008 | H23: =SUM(H18:H22) -> 9321.0012 | I23: =SUM(I18:I22) -> 11137.139 | J23: =SUM(J18:J22) -> 12144.302 | K23: =SUM(K18:K22) -> 12390.532
A24: 折現因子 | B24: x | C24: =1/(1+$C$8)^1 -> 0.84957642 | D24: =1/(1+$C$8)^2 -> 0.72178009 | E24: =1/(1+$C$8)^3 -> 0.61320735 | F24: =1/(1+$C$8)^4 -> 0.52096651 | G24: =1/(1+$C$8)^5 -> 0.44260086 | H24: =1/(1+$C$8)^6 -> 0.37602325 | I24: =1/(1+$C$8)^7 -> 0.31946049 | J24: =1/(1+$C$8)^8 -> 0.2714061 | K24: =1/(1+$C$8)^9 -> 0.23058022
A25: 現值 | B25: US$M | C25: =C23*C24 -> 2694.0535 | D25: =D23*D24 -> 3077.5946 | E25: =E23*E24 -> 2949.7419 | F25: =F23*F24 -> 3171.9129 | G25: =G23*G24 -> 3351.1085 | H25: =H23*H24 -> 3504.9132 | I25: =I23*I24 -> 3557.8757 | J25: =J23*J24 -> 3296.0376 | K25: =K23*K24 -> 2857.0116
A26: 永續價值現值 | B26: US$M | C26: =K23*(1+g_tv)/($C$8-g_tv)*K24 -> 20010.737
A27: EV（DCF） | B27: US$M | C27: =SUM(C25:K25)+C26 -> 48470.987
A28: 永續價值占 EV | B28: % | C28: =C26/C27 -> 0.41283949
A29: 永續價值隱含 2035 年 EV／調整後 EBITDA（對照倍數法的適用倍數） | B29: x | C29: =C26/K24/PL!M33 -> 5.3871093
A30: 每股價值（DCF） | B30: US$ | C30: =(C27-$C$9-$C$10)/sh_fx -> 39.185437
A31: 每股價值（倍數法：2027 年調整後 EBITDA × 適用倍數） | B31: US$ | C31: =(PL!E33*$C$12-$C$9-$C$10)/sh_fx -> 64.577314
A32: 情境目標價（DCF × w＋倍數法 ×（1 − w）） | B32: US$ | C32: =w_dcf*C30+(1-w_dcf)*C31 -> 51.881376
A33: 現金流序列（C＝2026 年底以市場 EV 買入；D–L＝FY2027–FY2035 無槓桿自由現金流；L 另加 2035 年以適用倍數出場） | B33: US$M | C33: =-$C$13 -> -76425.73 | D33: =C23 -> 3171.0549 | E33: =D23 -> 4263.8951 | F33: =E23 -> 4810.3499 | G33: =F23 -> 6088.5159 | H33: =G23 -> 7571.4008 | I33: =H23 -> 9321.0012 | J33: =I23 -> 11137.139 | K33: =J23 -> 12144.302 | L33: =K23+PL!M33*$C$12 -> 287381.72
A34: 市場隱含報酬率（以現價買入、持有至 2035 年的 IRR） | B34: % | C34: =IRR(C33:L33) -> 0.20542327
A36: 情境 B（基準：成長放緩、利得率小降）
A37: 營業利益 | B37: US$M | C37: =PL!E50 -> 3502.9758 | D37: =PL!F50 -> 4355.2131 | E37: =PL!G50 -> 5208.3249 | F37: =PL!H50 -> 6000.707 | G37: =PL!I50 -> 6885.64 | H37: =PL!J50 -> 7764.2295 | I37: =PL!K50 -> 8605.9412 | J37: =PL!L50 -> 9378.0002 | K37: =PL!M50 -> 10047.252
A38: − 營業利益的現金稅（2027–2028 用 ctr，之後用有效稅率） | B38: US$M | C38: =-MAX(0,PL!E50)*ctr -> -105.08927 | D38: =-MAX(0,PL!F50)*ctr -> -130.65639 | E38: =-MAX(0,PL!G50)*(etr_27+(etr_30-etr_27)*2/3) -> -833.33199 | F38: =-MAX(0,PL!H50)*etr_30 -> -1080.1273 | G38: =-MAX(0,PL!I50)*etr_30 -> -1239.4152 | H38: =-MAX(0,PL!J50)*etr_30 -> -1397.5613 | I38: =-MAX(0,PL!K50)*etr_30 -> -1549.0694 | J38: =-MAX(0,PL!L50)*etr_30 -> -1688.04 | K38: =-MAX(0,PL!M50)*etr_30 -> -1808.5054
A39: ＋折舊攤銷＋SBC | B39: US$M | C39: =CF!E57 -> 380.07 | D39: =CF!F57 -> 391.4721 | E39: =CF!G57 -> 410.96463 | F39: =CF!H57 -> 431.86841 | G39: =CF!I57 -> 453.05514 | H39: =CF!J57 -> 474.24604 | I39: =CF!K57 -> 495.14274 | J39: =CF!L57 -> 515.44451 | K39: =CF!M57 -> 534.86797
A40: − 資本支出 | B40: US$M | C40: =-CF!E62 -> -191.28753 | D40: =-CF!F62 -> -350.14332 | E40: =-CF!G62 -> -409.81725 | F40: =-CF!H62 -> -450.70371 | G40: =-CF!I62 -> -488.56959 | H40: =-CF!J62 -> -521.76337 | I40: =-CF!K62 -> -548.82619 | J40: =-CF!L62 -> -568.47254 | K40: =-CF!M62 -> -606.90504
A41: − 營運資金與風險自留 | B41: US$M | C41: =CF!E59+CF!E60 -> -769.63421 | D41: =CF!F59+CF!F60 -> -824.36639 | E41: =CF!G59+CF!G60 -> -854.30236 | F41: =CF!H59+CF!H60 -> -829.55144 | G41: =CF!I59+CF!I60 -> -852.49575 | H41: =CF!J59+CF!J60 -> -857.06885 | I41: =CF!K59+CF!K60 -> -834.06314 | J41: =CF!L59+CF!L60 -> -780.77289 | K41: =CF!M59+CF!M60 -> -696.1064
A42: 無槓桿自由現金流 | B42: US$M | C42: =SUM(C37:C41) -> 2817.0348 | D42: =SUM(D37:D41) -> 3441.5191 | E42: =SUM(E37:E41) -> 3521.838 | F42: =SUM(F37:F41) -> 4072.193 | G42: =SUM(G37:G41) -> 4758.2146 | H42: =SUM(H37:H41) -> 5462.082 | I42: =SUM(I37:I41) -> 6169.1252 | J42: =SUM(J37:J41) -> 6856.1593 | K42: =SUM(K37:K41) -> 7470.6033
A43: 折現因子 | B43: x | C43: =1/(1+$C$8)^1 -> 0.84957642 | D43: =1/(1+$C$8)^2 -> 0.72178009 | E43: =1/(1+$C$8)^3 -> 0.61320735 | F43: =1/(1+$C$8)^4 -> 0.52096651 | G43: =1/(1+$C$8)^5 -> 0.44260086 | H43: =1/(1+$C$8)^6 -> 0.37602325 | I43: =1/(1+$C$8)^7 -> 0.31946049 | J43: =1/(1+$C$8)^8 -> 0.2714061 | K43: =1/(1+$C$8)^9 -> 0.23058022
A44: 現值 | B44: US$M | C44: =C42*C43 -> 2393.2863 | D44: =D42*D43 -> 2484.02 | E44: =E42*E43 -> 2159.6169 | F44: =F42*F43 -> 2121.4762 | G44: =G42*G43 -> 2105.9899 | H44: =H42*H43 -> 2053.8698 | I44: =I42*I43 -> 1970.7918 | J44: =J42*J43 -> 1860.8034 | K44: =K42*K43 -> 1722.5734
A45: 永續價值現值 | B45: US$M | C45: =K42*(1+g_tv)/($C$8-g_tv)*K43 -> 12065.041
A46: EV（DCF） | B46: US$M | C46: =SUM(C44:K44)+C45 -> 30937.469
A47: 永續價值占 EV | B47: % | C47: =C45/C46 -> 0.38998152
A48: 永續價值隱含 2035 年 EV／調整後 EBITDA（對照倍數法的適用倍數） | B48: x | C48: =C45/K43/PL!M62 -> 4.9544651
A49: 每股價值（DCF） | B49: US$ | C49: =(C46-$C$9-$C$10)/sh_fx -> 23.627745
A50: 每股價值（倍數法：2027 年調整後 EBITDA × 適用倍數） | B50: US$ | C50: =(PL!E62*$C$12-$C$9-$C$10)/sh_fx -> 54.672691
A51: 情境目標價（DCF × w＋倍數法 ×（1 − w）） | B51: US$ | C51: =w_dcf*C49+(1-w_dcf)*C50 -> 39.150218
A52: 現金流序列（C＝2026 年底以市場 EV 買入；D–L＝FY2027–FY2035 無槓桿自由現金流；L 另加 2035 年以適用倍數出場） | B52: US$M | C52: =-$C$13 -> -76425.73 | D52: =C42 -> 2817.0348 | E52: =D42 -> 3441.5191 | F52: =E42 -> 3521.838 | G52: =F42 -> 4072.193 | H52: =G42 -> 4758.2146 | I52: =H42 -> 5462.082 | J52: =I42 -> 6169.1252 | K52: =J42 -> 6856.1593 | L52: =K42+PL!M62*$C$12 -> 187748.92
A53: 市場隱含報酬率（以現價買入、持有至 2035 年的 IRR） | B53: % | C53: =IRR(C52:L52) -> 0.14197505
A55: 情境 C（信用壓力：2027 年次級車貸循環＋二手車價下跌）
A56: 營業利益 | B56: US$M | C56: =PL!E79 -> 1016.5127 | D56: =PL!F79 -> 1378.8885 | E56: =PL!G79 -> 1842.0355 | F56: =PL!H79 -> 2446.638 | G56: =PL!I79 -> 2737.0839 | H56: =PL!J79 -> 3015.115 | I56: =PL!K79 -> 3272.3176 | J56: =PL!L79 -> 3500.1812 | K56: =PL!M79 -> 3690.4964
A57: − 營業利益的現金稅（2027–2028 用 ctr，之後用有效稅率） | B57: US$M | C57: =-MAX(0,PL!E79)*ctr -> -30.495381 | D57: =-MAX(0,PL!F79)*ctr -> -41.366654 | E57: =-MAX(0,PL!G79)*(etr_27+(etr_30-etr_27)*2/3) -> -294.72569 | F57: =-MAX(0,PL!H79)*etr_30 -> -440.39485 | G57: =-MAX(0,PL!I79)*etr_30 -> -492.6751 | H57: =-MAX(0,PL!J79)*etr_30 -> -542.72069 | I57: =-MAX(0,PL!K79)*etr_30 -> -589.01717 | J57: =-MAX(0,PL!L79)*etr_30 -> -630.03262 | K57: =-MAX(0,PL!M79)*etr_30 -> -664.28935
A58: ＋折舊攤銷＋SBC | B58: US$M | C58: =CF!E95 -> 380.07 | D58: =CF!F95 -> 391.4721 | E58: =CF!G95 -> 403.21626 | F58: =CF!H95 -> 415.31275 | G58: =CF!I95 -> 427.77213 | H58: =CF!J95 -> 440.6053 | I58: =CF!K95 -> 453.82346 | J58: =CF!L95 -> 467.43816 | K58: =CF!M95 -> 481.4613
A59: − 資本支出 | B59: US$M | C59: =-CF!E100 -> -134.33061 | D59: =-CF!F100 -> -144.62406 | E59: =-CF!G100 -> -159.4108 | F59: =-CF!H100 -> -179.79249 | G59: =-CF!I100 -> -199.43177 | H59: =-CF!J100 -> -218.77842 | I59: =-CF!K100 -> -237.32737 | J59: =-CF!L100 -> -254.54766 | K59: =-CF!M100 -> -290.92982
A60: − 營運資金與風險自留 | B60: US$M | C60: =CF!E97+CF!E98 -> -336.68273 | D60: =CF!F97+CF!F98 -> 58.404321 | E60: =CF!G97+CF!G98 -> 8.2856786 | F60: =CF!H97+CF!H98 -> -372.66836 | G60: =CF!I97+CF!I98 -> -389.28866 | H60: =CF!J97+CF!J98 -> -385.49536 | I60: =CF!K97+CF!K98 -> -371.75542 | J60: =CF!L97+CF!L98 -> -347.4603 | K60: =CF!M97+CF!M98 -> -312.45292
A61: 無槓桿自由現金流 | B61: US$M | C61: =SUM(C56:C60) -> 895.07399 | D61: =SUM(D56:D60) -> 1642.7742 | E61: =SUM(E56:E60) -> 1799.401 | F61: =SUM(F56:F60) -> 1869.0951 | G61: =SUM(G56:G60) -> 2083.4605 | H61: =SUM(H56:H60) -> 2308.7258 | I61: =SUM(I56:I60) -> 2528.0411 | J61: =SUM(J56:J60) -> 2735.5788 | K61: =SUM(K56:K60) -> 2904.2856
A62: 折現因子 | B62: x | C62: =1/(1+$C$8)^1 -> 0.84957642 | D62: =1/(1+$C$8)^2 -> 0.72178009 | E62: =1/(1+$C$8)^3 -> 0.61320735 | F62: =1/(1+$C$8)^4 -> 0.52096651 | G62: =1/(1+$C$8)^5 -> 0.44260086 | H62: =1/(1+$C$8)^6 -> 0.37602325 | I62: =1/(1+$C$8)^7 -> 0.31946049 | J62: =1/(1+$C$8)^8 -> 0.2714061 | K62: =1/(1+$C$8)^9 -> 0.23058022
A63: 現值 | B63: US$M | C63: =C61*C62 -> 760.43376 | D63: =D61*D62 -> 1185.7217 | E63: =E61*E62 -> 1103.4059 | F63: =F61*F62 -> 973.73594 | G63: =G61*G62 -> 922.14141 | H63: =H61*H62 -> 868.13458 | I63: =I61*I62 -> 807.60925 | J63: =J61*J62 -> 742.45277 | K63: =K61*K62 -> 669.67082
A64: 永續價值現值 | B64: US$M | C64: =K61*(1+g_tv)/($C$8-g_tv)*K62 -> 4690.4278
A65: EV（DCF） | B65: US$M | C65: =SUM(C63:K63)+C64 -> 12723.734
A66: 永續價值占 EV | B66: % | C66: =C64/C65 -> 0.36863611
A67: 永續價值隱含 2035 年 EV／調整後 EBITDA（對照倍數法的適用倍數） | B67: x | C67: =C64/K62/PL!M91 -> 4.9005192
A68: 每股價值（DCF） | B68: US$ | C68: =(C65-$C$9-$C$10)/sh_fx -> 7.4664898
A69: 每股價值（倍數法：2027 年調整後 EBITDA × 適用倍數） | B69: US$ | C69: =(PL!E91*$C$12-$C$9-$C$10)/sh_fx -> 17.01171
A70: 情境目標價（DCF × w＋倍數法 ×（1 − w）） | B70: US$ | C70: =w_dcf*C68+(1-w_dcf)*C69 -> 12.2391
A71: 現金流序列（C＝2026 年底以市場 EV 買入；D–L＝FY2027–FY2035 無槓桿自由現金流；L 另加 2035 年以適用倍數出場） | B71: US$M | C71: =-$C$13 -> -76425.73 | D71: =C61 -> 895.07399 | E71: =D61 -> 1642.7742 | F71: =E61 -> 1799.401 | G71: =F61 -> 1869.0951 | H71: =G61 -> 2083.4605 | I71: =H61 -> 2308.7258 | J71: =I61 -> 2528.0411 | K71: =J61 -> 2735.5788 | L71: =K61+PL!M91*$C$12 -> 73761.133
A72: 市場隱含報酬率（以現價買入、持有至 2035 年的 IRR） | B72: % | C72: =IRR(C71:L71) -> 0.019425823
A74: 彙總 | B74: 單位 | C74: 情境 A | D74: 情境 B | E74: 情境 C
A75: 每股價值（DCF） | B75: US$ | C75: =C30 -> 39.185437 | D75: =C49 -> 23.627745 | E75: =C68 -> 7.4664898
A76: 每股價值（倍數法） | B76: US$ | C76: =C31 -> 64.577314 | D76: =C50 -> 54.672691 | E76: =C69 -> 17.01171
A77: 情境目標價 | B77: US$ | C77: =C32 -> 51.881376 | D77: =C51 -> 39.150218 | E77: =C70 -> 12.2391
A78: 永續價值占 EV | B78: % | C78: =C28 -> 0.41283949 | D78: =C47 -> 0.38998152 | E78: =C66 -> 0.36863611
A79: 永續價值隱含 2035 年 EV／EBITDA | B79: x | C79: =C29 -> 5.3871093 | D79: =C48 -> 4.9544651 | E79: =C67 -> 4.9005192
A80: 市場隱含報酬率（IRR，對照 WACC） | B80: % | C80: =C34 -> 0.20542327 | D80: =C53 -> 0.14197505 | E80: =C72 -> 0.019425823
A81: 情境機率 | B81: % | C81: =p_A -> 0.25 | D81: =p_B -> 0.5 | E81: =p_C -> 0.25
A82: 機率加權市場隱含報酬率（IRR） | B82: % | C82: =SUMPRODUCT(C80:E80,C81:E81) -> 0.1271998
A84: 結論 | B84: 單位 | C84: 值 | E84: 說明
A85: 加權目標價 | B85: US$ | C85: =SUMPRODUCT(C77:E77,C81:E81) -> 35.605228 | E85: 情境 25／50／25
A86: 現價（2026-10-28 盤後） | B86: US$ | C86: =px -> 63.99
A87: 上檔空間（加權目標價 ÷ 現價 − 1） | B87: % | C87: =C85/C86-1 -> -0.44358138
A88: 加權每股價值：DCF | B88: US$ | C88: =SUMPRODUCT(C75:E75,C81:E81) -> 23.476854
A89: 加權每股價值：倍數法 | B89: US$ | C89: =SUMPRODUCT(C76:E76,C81:E81) -> 47.733601
A90: 分析師平均目標價（對照） | B90: US$ | C90: =an_tgt -> 82 | E90: TIKR 2026-10-13
A91: 市場隱含：2030 年須達到的調整後 EBITDA（市場 EV 以 WACC 滾至 2030 年 ÷ 適用倍數） | B91: US$M | C91: =C13*(1+C8)^4/C12 -> 8594.0183
A92: 情境 B 2030 年調整後 EBITDA | B92: US$M | C92: =PL!H62 -> 6411.5754
A93: 市場隱含：2030 年零售台數（以情境 B 2030 年每台 EBITDA 換算） | B93: 輛 | C93: =C91/(C92/Thesis!H34) -> 2180558.6
A94: 投資建議 | B94: — | C94: =IF(C87>=0.5,"強力買進",IF(C87>=0.25,"買進",IF(C87>-0.25,"中立",IF(C87>-0.5,"放空","強力放空")))) -> 放空 | E94: 五級固定規則：≥ +50% 強力買進、+25%～+50% 買進、−25%～+25% 中立、−50%～−25% 放空、≤ −50% 強力放空

Sheet Recon
A1: Recon — 對帳（不作校準）：模型值與公司指引、市場共識、評等機構指標、放空報告主張逐列比較
A3: 項目 | B3: 單位 | C3: 模型（情境 B）／實績 | D3: 外部值 | E3: 差距 | F3: 外部來源 | G3: 標記 | H3: 說明
A4: 2026 年調整後 EBITDA vs 公司指引「區間高端」（取 2.85–3.0B 中點） | B4: US$M | C4: =PL!D62 -> 2952.2071 | D4: =(guide_lo+guide_hi)/2+75 -> 2925 | E4: =C4-D4 -> 27.207053 | F4: Carvana Q3 2026 股東信（8-K 2026-10-28 附件 99.1）：2.7–3.0B 的 higher end | G4: Interested-party | H4: 共識約 2.95B（TIKR 2026-10-13）
A5: 2026 年調整後 EBITDA vs 市場共識 | B5: US$M | C5: =PL!D62 -> 2952.2071 | D5: 2950 | E5: =C5-D5 -> 2.2070528 | F5: TIKR（2026-10-13）：全年約 2.95B（Q3 約 795、Q4 約 710） | G5: Interested-party | H5: —
A6: Q3 2026 零售台數：實績 vs 共識 | B6: 輛 | C6: =Q!J4 -> 217385 | D6: =cons_q3_units -> 210299 | E6: =C6-D6 -> 7086 | F6: Zacks（2026-10-23） | G6: Interested-party | H6: 實績高 3.4%
A7: Q3 2026 營收：實績 vs 共識 | B7: US$M | C7: =Q!J9 -> 8040 | D7: =cons_q3_rev -> 7670 | E7: =C7-D7 -> 370 | F7: Zacks（2026-10-23） | G7: Interested-party | H7: —
A8: Q3 2026 調整後 EBITDA：實績 vs 共識 | B8: US$M | C8: =Q!J19 -> 800 | D8: =cons_q3_ebitda -> 791.3 | E8: =C8-D8 -> 8.7 | F8: StockStory（2026-10-28） | G8: Interested-party | H8: —
A9: Q3 2026 零售 GPU：實績 vs 共識 | B9: US$ | C9: =Q!J10*1000000/Q!J4 -> 3555.9031 | D9: =cons_q3_gpr -> 3404 | E9: =C9-D9 -> 151.90312 | F9: Zacks | G9: Interested-party | H9: —
A10: Q3 2026 其他 GPU：實績 vs 共識 | B10: US$ | C10: =Q!J8*1000000/Q!J4 -> 2732.4792 | D10: =cons_q3_gpo -> 2722 | E10: =C10-D10 -> 10.479242 | F10: Zacks | G10: Interested-party | H10: 利率上升下仍持平
A11: Q3 2026 批發 GPU：實績 vs 共識 | B11: US$ | C11: =Q!J11*1000000/Q!J4 -> 708.42054 | D11: =cons_q3_gpw -> 812 | E11: =C11-D11 -> -103.57946 | F11: Zacks | G11: Interested-party | H11: —
A12: 情境 B 2030 年營業利益率 vs 公司中期目標（300 萬台） | B12: % | C12: =PL!H51 -> 0.093821581 | D12: =om_tgt -> 0.125 | E12: =C12-D12 -> -0.031178419 | F12: Carvana Q3 2026 股東信（8-K 2026-10-28 附件 99.1） | G12: Interested-party | H12: 公司目標對應 300 萬台；情境 B 2030 年約 160 萬台
A13: 債務／EBITDA（2026 年底 vs 2026-09-30 TTM） | B13: x | C13: =Credit!D29 -> 1.7870102 | D13: =ttm_lev -> 1.8997093 | E13: =C13-D13 -> -0.11269907 | F13: Q 頁 TTM | G13: Derived | H13: —
A14: 淨債務／EBITDA（2026 年底 vs 2026-09-30 TTM） | B14: x | C14: =Credit!D30 -> 0.48146313 | D14: =ttm_nlev -> 0.79178779 | E14: =C14-D14 -> -0.31032466 | F14: Q 頁 TTM（公司 Q2 口徑 1.0x） | G14: Derived | H14: —
A15: （EBITDA − 資本支出）／利息（2026 年 vs Moody's 升評門檻） | B15: x | C15: =Credit!D33 -> 6.9573572 | D15: =moody_cov -> 3 | E15: =C15-D15 -> 3.9573572 | F15: Moody's 2025-10-02 | G15: Interested-party | H15: 2025-06 時為約 2.8x
A16: （出售利得＋關係人其他營收）÷ 調整後 EBITDA（TTM vs Gotham 主張） | B16: % | C16: =ttm_gosrp -> 0.67514535 | D16: 0.75 | E16: =C16-D16 -> -0.074854651 | F16: Gotham City Research（2026-01-28，經 Hedge Fund Alpha 報導） | G16: Interested-party | H16: 放空方；本模型以公司揭露數字推得，口徑可能不同
A17: 加權目標價 vs 分析師平均 | B17: US$ | C17: =v_tp_w -> 35.605228 | D17: =an_tgt -> 82 | E17: =C17-D17 -> -46.394772 | F17: TIKR（2026-10-13） | G17: Interested-party | H17: —
A18: 市場隱含 EV ÷ TTM 調整後 EBITDA vs 同業中位數 | B18: x | C18: =Val!C14 -> 27.770977 | D18: =Val!C11 -> 11.38 | E18: =C18-D18 -> 16.390977 | F18: stockanalysis.com（LAD、AN，近四季） | G18: Verified | H18: —
A20: 未找到：2026 年 Moody's／S&P 評等動作；2031 年票據贖回價格表；ADESA 全面改建成本；TRA 償付時程；非 Prime 貸款的終身損失預期（144A 發行未公開）

Sheet Sens
A1: Sens — 一次動一個輸入（低／高），完整重算整本模型；輸出：加權目標價、情境 B 2027 年債務／EBITDA、情境 C 收支關卡（FY2027–FY2031 合計）
A3: 輸入 | B3: 鍵 | C3: 低值 | D3: 高值 | E3: 基準：加權目標價 | F3: 低值：目標價變化 | G3: 高值：目標價變化 | H3: 低值：B 2027 債務／EBITDA | I3: 高值：B 2027 債務／EBITDA | J3: 低值：C 收支關卡 | K3: 高值：C 收支關卡
A4: 2026Q4 台數相對 Q3 變化 | B4: q4_seq | C4: 0 | D4: 0.05 | E4: 35.605228 | F4: -0.0059330891 | G4: 0.0088995091 | H4: 1.3965784 | I4: 1.3767592 | J4: 5895.572 | K4: 6024.589
A5: 情境 B：2027 年零售台數年增 | B5: g27_B | C5: 0.17 | D5: 0.33 | E5: 35.605228 | F5: -0.040427737 | G5: 0.040413776 | H5: 1.4813187 | I5: 1.3079226 | J5: 5947.1788 | K5: 5947.1788
A6: 情境 B：2028 年零售台數年增 | B6: g28_B | C6: 0.12 | D6: 0.28 | E6: 35.605228 | F6: -0.015900271 | G6: 0.016566599 | H6: 1.3885816 | I6: 1.3885816 | J6: 5947.1788 | K6: 5947.1788
A7: 情境 B：2030 年零售台數年增（2029 年取 2028 與 2030 中點） | B7: g30_B | C7: 0.08 | D7: 0.18 | E7: 35.605228 | F7: -0.017932253 | G7: 0.020040679 | H7: 1.3885816 | I7: 1.3885816 | J7: 5947.1788 | K7: 5947.1788
A8: 情境 B：2035 年零售台數年增（2031–2034 線性） | B8: g35_B | C8: 0.02 | D8: 0.08 | E8: 35.605228 | F8: -0.0040662413 | G8: 0.0040862443 | H8: 1.3885816 | I8: 1.3885816 | J8: 5947.1788 | K8: 5947.1788
A9: 情境 B：2027 年零售 GPU | B9: gpr27_B | C9: 3150 | D9: 3750 | E9: 35.605228 | F9: -0.036036436 | G9: 0.036036436 | H9: 1.5096107 | I9: 1.2854814 | J9: 5947.1788 | K9: 5947.1788
A10: 情境 B：2030 年起零售 GPU | B10: gprLT_B | C10: 3050 | D10: 3650 | E10: 35.605228 | F10: -0.014258996 | G10: 0.014258996 | H10: 1.3885816 | I10: 1.3885816 | J10: 5947.1788 | K10: 5947.1788
A11: 情境 B：2027 年貸款出售利得率 | B11: gos27_B | C11: 0.062 | D11: 0.082 | E11: 35.605228 | F11: -0.039285878 | G11: 0.039285878 | H11: 1.4839811 | I11: 1.304707 | J11: 5587.2241 | K11: 6307.1335
A12: 情境 B：2030 年起貸款出售利得率 | B12: gosLT_B | C12: 0.06 | D12: 0.08 | E12: 35.605228 | F12: -0.012586253 | G12: 0.012586253 | H12: 1.3885816 | I12: 1.3885816 | J12: 5947.1788 | K12: 5947.1788
A13: SG&A 固定部分（每季） | B13: sga_fix | C13: 140 | D13: 200 | E13: 35.605228 | F13: 0.035197482 | G13: -0.035197482 | H13: 1.3455199 | I13: 1.4344907 | J13: 6525.4333 | K13: 5368.9243
A14: SG&A 變動部分／台（2026 年） | B14: sga_var | C14: 2700 | D14: 2900 | E14: 35.605228 | F14: 0.030017284 | G14: -0.030017284 | H14: 1.3530445 | I14: 1.4260357 | J14: 6322.0773 | K14: 5572.2803
A15: 情境 B：變動 SG&A／台每年下降 | B15: eff_B | C15: 0 | D15: 0.03 | E15: 35.605228 | F15: -0.018221869 | G15: 0.016956423 | H15: 1.4043086 | I15: 1.373203 | J15: 5947.1788 | K15: 5947.1788
... A31: 零售每台售價年增（2027 起） | B31: asp_g | C31: 0 | D31: 0.04 | E31: 35.605228 | F31: -0.01324378 | G31: 0.013359782 | H31: 1.3980082 | I31: 1.3793246 | J31: 6127.74 | K31: 5747.1636
A33: 基準值：加權目標價（美元） | C33: 35.605228
A34: 基準值：情境 B 2027 年債務／EBITDA | C34: 1.3885816
A35: 基準值：情境 C 收支關卡（FY2027–FY2031 合計） | C35: 5947.1788

Sheet Sources
A1: Sources — 出處（擷取日 2026-10-27／28）
A3: 序 | B3: 出處 | C3: 內容 | D3: 標記
A4: 1 | B4: SEC EDGAR：Carvana 8-K 附件 99.1 股東信 Q4 2024–Q2 2026（CIK 1690820） | C4: 季度營收線、毛利、台數、調整後 EBITDA 對帳、流動性 | D4: Interested-party
A5: 2 | B5: SEC EDGAR：Carvana 10-Q Q2 2026（2026-07-29）附註 6–10、19 | C5: 關係人、貸款出售協議（Ally、整批出售、證券化）、受益權、債務、股權 | D5: Interested-party
A6: 3 | B6: SEC EDGAR：Carvana 10-K FY2025（2026-02-18） | C6: 評價備抵釋放、TRA、會計師 Grant Thornton | D6: Interested-party
A7: 4 | B7: SEC EDGAR：8-K 2026-08-14（定期貸款 B 信用協議）；Carvana 新聞稿 2026-08-12 | C7: 1.66B、SOFR＋2.25%、2033 到期、贖回 2030 年票據；淨債務／EBITDA 1.0x | D7: Interested-party
A8: 5 | B8: SEC EDGAR：8-K 2026-05-06（章程修正，1 拆 5） | C8: 股票分割 | D8: Interested-party
A9: 6 | B9: SEC EDGAR：Carvana Auto Receivables Trust 2026-P3 424B5（2026-08-20，CIK 1770373） | C9: 管理組合逾期與淨沖銷（全部／Prime）、承銷模型變更 | D9: Interested-party
A10: 7 | B10: SEC XBRL companyfacts CIK0001690820 | C10: 季末資產負債表、2024 年九個月現金流 | D10: Interested-party
A11: 8 | B11: stockanalysis.com：CVNA、LAD、AN、KMX 統計頁（2026-10-23～27） | C11: 現價、Beta、EV/EBITDA | D11: Verified
A12: 9 | B12: sofrrate.com 2026-10 SOFR 每日表 | C12: SOFR 3.93%（2026-10-26） | D12: Verified
A13: 10 | B13: Yahoo Finance／Zacks（2026-10-23）Q3 2026 共識 | C13: 台數 210,299、營收 7.67B、EPS 0.47、各 GPU | D13: Interested-party
A14: 11 | B14: TIKR（2026-10-13） | C14: 2026 年 EBITDA 共識約 2.95B、目標價平均約 82 | D14: Interested-party
A15: 12 | B15: Investing.com：Moody's 升 B2（2025-10-02）、S&P 升 B（2025-03） | C15: 評等門檻與槓桿指標 | D15: Interested-party
... A19: 16 | B19: YinchenChang/company-models：oracle v0.4、docs/plan/個股模型原則_命題加營收分部.md；crwv-model v4.5 | C19: 模型架構、估值規則、無風險利率輸入 | D19: —
